Workbook

Sheet Resumo
A1: JUSFY — DRE contábil × gerencial · Janeiro a Junho 2026
A2: Três degraus, por mês: (1) como está hoje; (2) depois dos 138 lançamentos da Syhus (aba O QUE FAZER) — a única nota explicativa é a competência 2025, que fica em 2026 porque o exercício de 2025 já fechou; (3) depois das pendências que dependem de resposta da Jusfy (aba Notas e pendências). Meta: até 0,5%.
A4: CUSTO (contas 6.2)
B5: Jan | C5: Fev | D5: Mar | E5: Abr | F5: Mai | G5: Jun | H5: Total
A6: Gerencial (P&L oficial) | B6: 1021126.4 | C6: 1037755.6 | D6: 1158496.6 | E6: 1231075.9 | F6: 1323802.1 | G6: 1473722.3 | H6: 7245978.9
A7: Razão como está hoje | B7: 1478048.7 | C7: 801849.28 | D7: 919365.25 | E7: 1057146.9 | F7: 779107.5 | G7: 1239333.6 | H7: 6274851.2
A8: (−) Competência 2025 lançada em 2026 — NOTA EXPLICATIVA (exercício encerrado, fica em 2026) | B8: 618680.1 | C8: 11002.1 | D8: 26786.67 | E8: 0 | F8: -18576.33 | G8: 0 | H8: 637892.54
A9: 1) Diferença HOJE | B9: -161757.86 | C9: -246908.42 | D9: -265918.04 | E9: -173928.99 | F9: -526118.28 | G9: -234388.71 | H9: -1609020.3
A10: % sobre o gerencial | B10: -0.1584112 | C10: -0.2379254 | D10: -0.22953717 | E10: -0.1412821 | F10: -0.3974297 | G10: -0.15904537 | H10: -0.22205699
A11: (+) Lançamentos da Syhus (aba O QUE FAZER) | B11: 150401.43 | C11: 242692.39 | D11: 286844.54 | E11: 171009.44 | F11: 532804.28 | G11: 233640.04 | H11: 1617392.1
A12: 2) Diferença DEPOIS DA SYHUS | B12: -11356.43 | C12: -4216.03 | D12: 20926.5 | E12: -2919.55 | F12: 6686 | G12: -748.67 | H12: 8371.82
A13: % sobre o gerencial | B13: -0.011121473 | C13: -0.0040626425 | D13: 0.018063497 | E13: -0.0023715435 | F13: 0.0050506038 | G13: -0.00050801295 | H13: 0.0011553746
A14: (−) Google Ads: razão = base da Mari (ERP); o P&L está diferente — ajustar o P&L | B14: 0 | C14: 0 | D14: 0 | E14: 0 | F14: 0 | G14: 0 | H14: 0
A15: (−) NF que não está na base da Mari — tesouraria valida (aba Validar Tesouraria) | B15: 0 | C15: 493.83 | D15: 17878.21 | E15: 4756.07 | F15: 4879.32 | G15: 0 | H15: 28007.43
A16: (−) Lançamento sem nº de NF e fora do ERP — pedir a nota à Syhus (aba Pedir NF à Syhus) | B16: 0 | C16: 53.97 | D16: 0 | E16: 0 | F16: 0 | G16: 0 | H16: 53.97
A17: (−) Imposto retido: razão pelo valor bruto da NF, ERP/P&L pelo líquido pago | B17: 0 | C17: 730 | D17: 1628 | E17: 2835 | F17: 2976 | G17: 2447 | H17: 10616
... A24: % sobre o gerencial | B24: -0.0038732422 | C24: -0.0049675087 | D24: -0.0008173783 | E24: -0.0045282505 | F24: -0.0032567859 | G24: -0.0021000497 | H24: -0.0031794062
A26: DESPESA (contas 4.1)
B27: Jan | C27: Fev | D27: Mar | E27: Abr | F27: Mai | G27: Jun | H27: Total
A28: Gerencial (P&L oficial) | B28: 2029394.9 | C28: 1891722.3 | D28: 2172723.6 | E28: 2485367.1 | F28: 3050632.3 | G28: 3065504.4 | H28: 14695345
A29: Razão como está hoje | B29: 2452976.2 | C29: 2305424.9 | D29: 2250602.1 | E29: 2740110.4 | F29: 3273376.2 | G29: 3122469.3 | H29: 16144959
A30: (−) Competência 2025 lançada em 2026 — NOTA EXPLICATIVA (exercício encerrado, fica em 2026) | B30: 481163.62 | C30: 110748.25 | D30: 14335 | E30: 0 | F30: -27403.81 | G30: 0 | H30: 578843.06
A31: 1) Diferença HOJE | B31: -57582.29 | C31: 302954.34 | D31: 63543.5 | E31: 254743.3 | F31: 250147.7 | G31: 56964.9 | H31: 870771.45
A32: % sobre o gerencial | B32: -0.028374119 | C32: 0.16014736 | D32: 0.029246012 | E32: 0.10249725 | F32: 0.08199864 | G32: 0.018582554 | H32: 0.059254919
A33: (+) Lançamentos da Syhus (aba O QUE FAZER) | B33: 24409.44 | C33: -243782.41 | D33: -40690.82 | E33: -236170.79 | F33: -270171.26 | G33: -9026.75 | H33: -775432.59
A34: 2) Diferença DEPOIS DA SYHUS | B34: -33172.85 | C34: 59171.93 | D34: 22852.68 | E34: 18572.51 | F34: -20023.56 | G34: 47938.15 | H34: 95338.86
A35: % sobre o gerencial | B35: -0.016346178 | C35: 0.031279395 | D35: 0.010517988 | E35: 0.0074727432 | F35: -0.0065637409 | G35: 0.015637932 | H35: 0.0064876914
A36: (−) Google Ads: razão = base da Mari (ERP); o P&L está diferente — ajustar o P&L | B36: 6158.49 | C36: 0 | D36: 20003.17 | E36: 12688.86 | F36: 0 | G36: 5034.06 | H36: 43884.58
A37: (−) NF que não está na base da Mari — tesouraria valida (aba Validar Tesouraria) | B37: 22298.56 | C37: 6467.02 | D37: 5127.79 | E37: 2183 | F37: 31609.24 | G37: 4730.43 | H37: 72416.04
A38: (−) Lançamento sem nº de NF e fora do ERP — pedir a nota à Syhus (aba Pedir NF à Syhus) | B38: 267 | C38: 2741.04 | D38: 0 | E38: 0 | F38: 0 | G38: 110.26 | H38: 3118.3
A39: (−) Imposto retido: razão pelo valor bruto da NF, ERP/P&L pelo líquido pago | B39: 149 | C39: 149 | D39: 149.01 | E39: 393.23 | F39: 0 | G39: 660.36 | H39: 1500.6
... A46: % sobre o gerencial | B46: -0.0049685008 | C46: -0.0016715191 | D46: -0.0032766616 | E46: -0.0046960668 | F46: -0.0028910892 | G46: -0.0049087648 | H46: -0.0038041517
A48: TOTAL (custo + despesa)
B49: Jan | C49: Fev | D49: Mar | E49: Abr | F49: Mai | G49: Jun | H49: Total
A50: Gerencial (P&L oficial) | B50: 3050521.3 | C50: 2929477.9 | D50: 3331220.2 | E50: 3716443 | F50: 4374434.4 | G50: 4539226.7 | H50: 21941323
A51: Razão como está hoje | B51: 3931024.9 | C51: 3107274.2 | D51: 3169967.3 | E51: 3797257.3 | F51: 4052483.7 | G51: 4361802.9 | H51: 22419810
A52: (−) Competência 2025 lançada em 2026 — NOTA EXPLICATIVA (exercício encerrado, fica em 2026) | B52: 1099843.7 | C52: 121750.35 | D52: 41121.67 | E52: 0 | F52: -45980.14 | G52: 0 | H52: 1216735.6
A53: 1) Diferença HOJE | B53: -219340.15 | C53: 56045.92 | D53: -202374.54 | E53: 80814.31 | F53: -275970.58 | G53: -177423.81 | H53: -738248.85
A54: % sobre o gerencial | B54: -0.071902514 | C54: 0.019131709 | D54: -0.060750874 | E54: 0.021745069 | F54: -0.063087145 | G54: -0.039086792 | H54: -0.033646505
A55: (+) Lançamentos da Syhus (aba O QUE FAZER) | B55: 174810.87 | C55: -1090.02 | D55: 246153.72 | E55: -65161.35 | F55: 262633.02 | G55: 224613.29 | H55: 841959.53
A56: 2) Diferença DEPOIS DA SYHUS | B56: -44529.28 | C56: 54955.9 | D56: 43779.18 | E56: 15652.96 | F56: -13337.56 | G56: 47189.48 | H56: 103710.68
A57: % sobre o gerencial | B57: -0.014597269 | C57: 0.018759623 | D57: 0.013142085 | E57: 0.0042118122 | F57: -0.0030489793 | G57: 0.010395929 | H57: 0.0047267285
A58: (−) Google Ads: razão = base da Mari (ERP); o P&L está diferente — ajustar o P&L | B58: 6158.49 | C58: 0 | D58: 20003.17 | E58: 12688.86 | F58: 0 | G58: 5034.06 | H58: 43884.58
A59: (−) NF que não está na base da Mari — tesouraria valida (aba Validar Tesouraria) | B59: 22298.56 | C59: 6960.85 | D59: 23006 | E59: 6939.07 | F59: 36488.56 | G59: 4730.43 | H59: 100423.47
A60: (−) Lançamento sem nº de NF e fora do ERP — pedir a nota à Syhus (aba Pedir NF à Syhus) | B60: 267 | C60: 2795.01 | D60: 0 | E60: 0 | F60: 0 | G60: 110.26 | H60: 3172.27
A61: (−) Imposto retido: razão pelo valor bruto da NF, ERP/P&L pelo líquido pago | B61: 149 | C61: 879 | D61: 1777.01 | E61: 3228.23 | F61: 2976 | G61: 3107.36 | H61: 12116.6
... A68: % sobre o gerencial | B68: -0.0046018758 | C68: -0.00283911 | D68: -0.002421398 | E68: -0.0046404775 | F68: -0.0030017572 | G68: -0.0039968768 | H68: -0.0035978336

Sheet O QUE FAZER
A1: O QUE FAZER — 138 lançamentos (é só isso)
A2: Todos os erros claros (lançamento em dobro, provisão que nunca foi baixada, MDR da Pagar.me) mais o mínimo que falta pra custo, despesa e total ficarem dentro de 0,5% do gerencial (depois das pendências da Jusfy). Cada linha é um fornecedor, com o nome como está no razão, débito, crédito, NF e a prova. Provisão e baixa do mesmo fornecedor andam juntas. Coluna "Status" é pra Syhus marcar.
A4: Nº | B4: Mês | C4: Fornecedor (razão) | D4: O que fazer | E4: Débito | F4: Crédito | G4: Valor | H4: NF | I4: Por quê (a prova) | J4: Status Syhus
A5: 1 | B5: Jan | C5: DELAINE ILHA DA SILVA 02466060027 | D5: Excluir — lançado em dobro | E5: 342 - Cartão de Crédito - Kamino | F5: 4.1.8.09.002 - Confraternização | G5: 267 | H5: — | I5: Mesmo valor (R$ 267) lançado duas vezes em Jan: a NF 64654684 já está lançada e o pagamento no cartão do mesmo valor também foi lançado como despesa. Excluir o lançamento do cartão.
A6: 2 | B6: Jan | C6: LUCAS ARAUJO SANTOS CONSULTORIA E DESENVOLVIMENTO EM TECNOLOGIA DA INFORMAC | D6: Estornar provisão que nunca foi baixada | E6: 930 - Provisão de Fornecedores | F6: 6.2.1.01.001 - Custos com Serviços de Terceiros - Internos | G6: 49296 | H6: — | I6: Provisão de Jan (R$ 49.296) nunca foi revertida e a NF 17 do mesmo valor entrou em Jan. Estornar a provisão em Jan.
A7: 3 | B7: Jan | C7: ALEXANDER MAX YOKOGAWA CONSULTORIA EM TECNOLOGIA DA INFORMACAO LTDA | D7: Estornar provisão que nunca foi baixada | E7: 930 - Provisão de Fornecedores | F7: 6.2.1.01.001 - Custos com Serviços de Terceiros - Internos | G7: 31667 | H7: — | I7: Provisão de Jan (R$ 31.667) nunca foi revertida. Não há NF desse valor no semestre: estornar.
A8: 4 | B8: Jan | C8: AVA TREINAMENTOS E MENTORIAS LTDA | D8: Estornar provisão que nunca foi baixada | E8: 930 - Provisão de Fornecedores | F8: 4.1.3.01.005 - Influenciadores | G8: 20000 | H8: — | I8: Provisão de Jan (R$ 20.000) nunca foi revertida e a NF 10490 do mesmo valor entrou em Jan. Estornar a provisão em Jan.
A9: 5 | B9: Jan | C9: MONTANDON SARAIVA SERVICOS ADMINISTRATIVOS LTDA | D9: Estornar provisão que nunca foi baixada | E9: 930 - Provisão de Fornecedores | F9: 4.1.3.01.005 - Influenciadores | G9: 5000 | H9: — | I9: Provisão de Jan (R$ 5.000) nunca foi revertida e a NF 1 do mesmo valor entrou em Jan. Estornar a provisão em Jan.
A10: 6 | B10: Jan | C10: 35.376.951 ALBERTO PEREIRA LOPES DA SILVA JUNIOR | D10: Estornar provisão que nunca foi baixada | E10: 930 - Provisão de Fornecedores | F10: 4.1.3.01.005 - Influenciadores | G10: 2000 | H10: — | I10: Provisão de Jan (R$ 2.000) nunca foi revertida. Não há NF desse valor no semestre: estornar.
A11: 7 | B11: Jan | C11: TRETAS JURIDICAS CURSOS E TREINAMENTOS LTDA | D11: Estornar provisão que nunca foi baixada | E11: 930 - Provisão de Fornecedores | F11: 4.1.3.01.005 - Influenciadores | G11: 1000 | H11: — | I11: Provisão de Jan (R$ 1.000) nunca foi revertida e a NF 1 do mesmo valor entrou em Jan. Estornar a provisão em Jan.
A12: 8 | B12: Jan | C12: 52.406.739 BEATRIZ FONSECA SALES | D12: Estornar provisão que nunca foi baixada | E12: 930 - Provisão de Fornecedores | F12: 4.1.3.01.005 - Influenciadores | G12: 900 | H12: — | I12: Provisão de Jan (R$ 900) nunca foi revertida e a NF 9 do mesmo valor entrou em Jan. Estornar a provisão em Jan.
A13: 9 | B13: Jan | C13: MATHEUS JOSE SANTOS DUARTE SOCIEDADE INDIVIDUAL DE ADVOCACIA | D13: Estornar provisão que nunca foi baixada | E13: 930 - Provisão de Fornecedores | F13: 4.1.3.01.005 - Influenciadores | G13: 800 | H13: — | I13: Provisão de Jan (R$ 800) nunca foi revertida e a NF 88 do mesmo valor entrou em Jan. Estornar a provisão em Jan.
A14: 10 | B14: Jan | C14: ZACHARIAS VIEIRA SOCIEDADE INDIVIDUAL DE ADVOCACIA | D14: Estornar provisão que nunca foi baixada | E14: 930 - Provisão de Fornecedores | F14: 4.1.3.01.005 - Influenciadores | G14: 700 | H14: — | I14: Provisão de Jan (R$ 700) nunca foi revertida e a NF 16 do mesmo valor entrou em Jan. Estornar a provisão em Jan.
A15: 11 | B15: Jan | C15: AVA BRASIL EDUCACAO E TECNOLOGIA LTDA | D15: Estornar provisão que nunca foi baixada | E15: 930 - Provisão de Fornecedores | F15: 4.1.3.01.005 - Influenciadores | G15: 582 | H15: — | I15: Provisão de Jan (R$ 582) nunca foi revertida e a NF 77389 do mesmo valor entrou em Jan. Estornar a provisão em Jan.
A16: 12 | B16: Jan | C16: BEYAUT LTDA | D16: Trocar de conta | E16: 6.2.1.01.001 - Custos com Serviços de Terceiros - Internos | F16: 4.1.6.01.007 - Serviços de Terceiros - Internos | G16: 33333.33 | H16: 2, 3 | I16: PJ da área Engenharia (Cadastro). No P&L oficial, só a folha de Engenharia é custo; as demais áreas são despesa. Está na conta 4.1.6.01.007. Mover para 6.2.1.01.001.
... A142: 138 | B142: Jun | C142: PAGAR.ME INSTITUICAO DE PAGAMENTO S.A | D142: Lançar o MDR da Pagar.me (retido no repasse) | E142: 6.2.1.01.003 - Custos com Transações | F142: Pagar.me — valores a receber (conta do repasse) | G142: 57078.91 | H142: — | I142: O P&L tem a taxa cheia da Pagar.me (Payment Processing Fees) e o razão só as NFs de serviço: o MDR retido no repasse (R$ 57.079 no mês) não foi lançado. Lançar pelo extrato de liquidação da Pagar.me.
C143: TOTAL (138 lançamentos, 82 fornecedores)

Sheet Onde a Syhus erra
A1: Onde a Syhus erra — e a regra pra não repetir
A2: Contagem no semestre inteiro (jan a jun), com todos os erros encontrados — não só os 138 lançamentos desta revisão. Seguindo estas regras daqui pra frente, a conciliação do mês fica pequena.
A4: Erro | B4: Vezes | C4: Valor | D4: Exemplos (fornecedor como está no razão) | E4: Regra pra não errar mais
A5: PJ de engenharia lançado como despesa | B5: 78 | C5: 1223585.9 | D5: L. A. B. CAMPOS LTDA; LACERDA GUILHERME CONSULTORIA EM TECNOLOGIA DA INFORMACAO LTDA; DKSWEB DESENVOLVIMENTO DE SOFTWARE LTDA; BEYAUT LTDA | E5: Todo PJ da área de Engenharia (Cadastro) vai em 6.2.1.01.001 (custo). Produto e as demais áreas ficam em 4.1.6.01.007 (despesa) — é assim que está no P&L oficial.
A6: Fornecedor de dados/API lançado como licença ou consultoria | B6: 38 | C6: 1461188.2 | D6: DIGESTO PESQUISA E BANCO DE DADOS LTDA; VIR SERVICOS DE INFORMACOES LTDA; CARBIGDATA TECNOLOGIA E INTELIGENCIA S/A; JUDIT TECNOLOGIA DA INFORMACAO LTDA | E6: Fornecedor de dados/API (Digesto, VIR, Judit, Nova DD, Big Data, Datacube, Carbigdata…) vai em 6.2.1.03.003 — Custo de APIs de Terceiros.
A7: "Mera importação" (4.1.2.05.011) usada como conta de passagem | B7: 37 | C7: 403748.25 | D7: JUDIT TECNOLOGIA DA INFORMACAO LTDA; SOFIA ANY COSTA KALOUSTIAN APOIO ADMINISTRATIVO LTDA; DKSWEB DESENVOLVIMENTO DE SOFTWARE LTDA; ROCHA CASTANHA SOLUCOES LTDA | E7: Não deixar NF parada em 4.1.2.05.011: toda NF importada vai direto pra conta do fornecedor (a mesma dos outros meses).
A8: Compra de equipamento/móvel lançada como despesa | B8: 15 | C8: 205422.35 | D8: EMESUL DECORANDOBEM MATERIAIS DE REVESTIMENTOS; DELL COMPUTADORES DO BRASIL LTDA; KABUM S.A.; PILOTO COMERCIO LTDA | E8: Computador, monitor, móvel e revestimento da sede são imobilizado (1.2.2.01.003), não despesa.
A9: Distrato (rescisão) lançado como custo | B9: 3 | C9: 56525.13 | D9: LUCAS ARAUJO SANTOS CONSULTORIA E DESENVOLVIMENTO EM TECNOLOGIA DA INFORMAC; 50.202.927 FELIPE ALVES DA SILVA; MARCELINO RAMOS DE AVELAR DESENVOLVIMENTO DE SOFTWARES LTDA | E9: Distrato é sempre despesa de RH — Contract Termination (4.1.6.02.007), qualquer que seja a área da pessoa. Não vai em 6.2.1.01.001 nem junto com a NF de serviço.
A10: Outras trocas de conta | B10: 206 | C10: 1469294.2 | D10: MICROSOFT DO BRASIL IMPORTACAO E COMERCIO DE SOFTWARE E VIDEO GAMES LTDA; CORE PRODUCT LTDA; 22793 CONSULTORIA EM TECNOLOGIA DA INFORMACAO LTDA; Renato Sacramento Horta Moreira | E10: Usar sempre a conta que o fornecedor já tem nos outros meses; na dúvida, perguntar à Jusfy antes de lançar.
A11: MDR da Pagar.me não lançado | B11: 6 | C11: 361743.38 | D11: Pagar.me | E11: Todo mês lançar a taxa cheia da Pagar.me pelo extrato de liquidação (o MDR retido no repasse), não só as NFs de serviço.
A12: NF lançada pela data de chegada, não pela competência | B12: 239 | C12: 2266713.9 | D12: AMAZON AWS SERVICOS BRASIL LTDA; DIGESTO PESQUISA E BANCO DE DADOS LTDA; 944279429428 - 005/026 - AMAZON AWS SERVICOS BRASIL LTDA; MICROSOFT DO BRASIL IMPORTACAO E COMERCIO DE SOFTWARE E VIDEO GAMES LTDA | E12: Quando a NF chega depois do mês do serviço: provisionar no mês do serviço (conta 930) e baixar a provisão quando a NF chegar.
A13: Mês sem a despesa do fornecedor (sem NF e sem provisão) | B13: 181 | C13: 1553761.8 | D13: Digesto Pesquisa e Banco de Dados Ltda (Jusbrasil); Amazon Cloud; Vir Servicos de Informacoes Ltda (Correct Data); Microsoft Ads | E13: No fechamento, conferir com a Jusfy os fornecedores recorrentes que ainda não mandaram NF e provisionar pelo valor do mês.
A14: Provisão que nunca foi baixada | B14: 45 | C14: 466957.67 | D14: FACEBOOK SERVICOS ONLINE DO BRASIL LTDA.; LACERDA GUILHERME CONSULTORIA EM TECNOLOGIA DA INFORMACAO LTDA; LUCAS ARAUJO SANTOS CONSULTORIA E DESENVOLVIMENTO EM TECNOLOGIA DA INFORMAC; LATAM AIRLINES BRASIL | E14: Toda provisão tem que ser baixada no mês em que a NF chega — conferir a conta 930 todo fechamento.
A15: Lançado em dobro | B15: 15 | C15: 313512.81 | D15: TREBLE.AI DO BRASIL SERVICOS DIGITAIS LTDA.; Renato Sacramento Horta Moreira; VILA VENTURA HOTEIS LTDA; AVA TREINAMENTOS E MENTORIAS LTDA | E15: Antes de lançar pagamento (cartão, PIX, boleto), conferir se a NF daquele valor já está no razão.
A16: Despesa de 2025 lançada em 2026 | B16: 239 | C16: 1389099 | D16: SWILE DO BRASIL S.A.; DIGESTO PESQUISA E BANCO DE DADOS LTDA; AMAZON AWS SERVICOS BRASIL LTDA; VIR SERVICOS DE INFORMACOES LTDA | E16: No fechamento de dezembro, provisionar o que já se sabe que vai chegar atrasado. (O que já caiu em 2026 fica em 2026 — é só nota explicativa.)
A18: Mudança de regra nesta revisão
A19: Folha de Produto é despesa | E19: No P&L oficial, só a folha de Engenharia é custo ("Engineering & Technology Payroll"). Os PJs de Produto ficam em 4.1.6.01.007 (despesa). As pessoas de Produto que já estão em despesa estão certas.

Sheet DRE Consolidado
A1: DRE contábil consolidado — como vai ficar, conta por conta
A2: Cada célula puxa o subtotal da conta na aba do mês ("Como deve ficar" e "Ajuste"). Embaixo, o gerencial (P&L oficial) e a diferença por grupo. As notas aceitas (competência 2025, taxa Pagar.me, folha) estão explicadas no Resumo.
A4: COMO VAI FICAR (contábil depois dos lançamentos)
A5: Conta | B5: Descrição | C5: Jan | D5: Fev | E5: Mar | F5: Abr | G5: Mai | H5: Jun | I5: Total
A6: 6.2.1.01.001 | B6: Custos com Serviços de Terceiros - Internos | C6: ='Jan'!F5 -> 639620.29 | D6: ='Fev'!F5 -> 470235.67 | E6: ='Mar'!F5 -> 480003.21 | F6: ='Abr'!F5 -> 409310.42 | G6: ='Mai'!F5 -> 367458.8 | H6: ='Jun'!F5 -> 525051.53 | I6: =SUM(C6:H6) -> 2891679.9
A7: 6.2.1.01.003 | B7: Custos com Transações | C7: ='Jan'!F37 -> 82855.93 | D7: ='Fev'!F34 -> 77297.77 | E7: ='Mar'!F36 -> 90261.14 | F7: ='Abr'!F35 -> 88237 | G7: ='Mai'!F41 -> 83647.95 | H7: ='Jun'!F42 -> 81710.51 | I7: =SUM(C7:H7) -> 504010.3
A8: 6.2.1.03.001 | B8: Custo de Hospedagem e Infraestrutura (Cloud) | C8: ='Jan'!F39 -> 221658.88 | D8: ='Fev'!F36 -> 104342.26 | E8: ='Mar'!F38 -> 140383.78 | F8: ='Abr'!F37 -> 269754.87 | G8: ='Mai'!F43 -> 249354.54 | H8: ='Jun'!F44 -> 320313.47 | I8: =SUM(C8:H8) -> 1305807.8
A9: 6.2.1.03.002 | B9: Custo de Licença de Sofware e Sistemas | C9: ='Jan'!F45 -> 350882.47 | D9: ='Fev'!F41 -> 159560.04 | E9: ='Mar'!F43 -> 393235.14 | F9: ='Abr'!F41 -> 385424.66 | G9: ='Mai'!F50 -> 182706.33 | H9: ='Jun'!F53 -> 119226.56 | I9: =SUM(C9:H9) -> 1591035.2
A10: 6.2.1.03.003 | B10: Custo de APIs de Terceiros | C10: ='Jan'!F71 -> 333432.53 | D10: ='Fev'!F60 -> 233105.93 | E10: ='Mar'!F62 -> 102326.52 | F10: ='Abr'!F65 -> 75429.38 | G10: ='Mai'!F72 -> 428744.16 | H10: ='Jun'!F78 -> 426671.54 | I10: =SUM(C10:H10) -> 1599710.1
A11: 4.1.1.01.001 | B11: Salários | C11: ='Jan'!F80 -> 5575.24 | D11: 0 | E11: 0 | F11: 0 | G11: 0 | H11: 0 | I11: =SUM(C11:H11) -> 5575.24
A12: 4.1.1.01.003 | B12: Bolsa Estágio | C12: ='Jan'!F83 -> 1300 | D12: ='Fev'!F70 -> 1500 | E12: ='Mar'!F72 -> 1500 | F12: ='Abr'!F75 -> 1500 | G12: ='Mai'!F86 -> 1500 | H12: ='Jun'!F91 -> 1500 | I12: =SUM(C12:H12) -> 8800
A13: 4.1.1.01.005 | B13: Férias | C13: ='Jan'!F85 -> 125 | D13: ='Fev'!F72 -> 125 | E13: ='Mar'!F74 -> 125 | F13: ='Abr'!F77 -> 125 | G13: ='Mai'!F88 -> 125 | H13: ='Jun'!F93 -> 125 | I13: =SUM(C13:H13) -> 750
A14: 4.1.2.01.001 | B14: Telefonia e Internet | C14: ='Jan'!F87 -> 2897.76 | D14: ='Fev'!F74 -> 2576.51 | E14: ='Mar'!F76 -> 235.52 | F14: ='Abr'!F79 -> 345.42 | G14: ='Mai'!F90 -> 1158.74 | H14: ='Jun'!F95 -> 1800.91 | I14: =SUM(C14:H14) -> 9014.86
A15: 4.1.2.01.002 | B15: Serviços e Equipamentos de TI | C15: 0 | D15: 0 | E15: ='Mar'!F78 -> 13957.29 | F15: ='Abr'!F82 -> 1744.29 | G15: ='Mai'!F93 -> 30963.37 | H15: ='Jun'!F99 -> 16377.65 | I15: =SUM(C15:H15) -> 63042.6
A16: 4.1.2.01.003 | B16: Licença de Sofware e Sistemas (SaaS) | C16: ='Jan'!F94 -> 250115.66 | D16: ='Fev'!F79 -> 83489.94 | E16: ='Mar'!F83 -> 129339.92 | F16: ='Abr'!F85 -> 258182.39 | G16: ='Mai'!F100 -> 150936.52 | H16: ='Jun'!F103 -> 222367.92 | I16: =SUM(C16:H16) -> 1094432.4
A17: 4.1.2.02.001 | B17: Aluguel | C17: ='Jan'!F127 -> 14835.11 | D17: ='Fev'!F106 -> 9105.76 | E17: ='Mar'!F109 -> 17762.35 | F17: ='Abr'!F114 -> 19568.98 | G17: ='Mai'!F137 -> 21930.12 | H17: ='Jun'!F132 -> 18767.06 | I17: =SUM(C17:H17) -> 101969.38
A18: 4.1.2.02.002 | B18: Energia Elétrica | C18: ='Jan'!F131 -> 2983.71 | D18: ='Fev'!F110 -> 3002.34 | E18: ='Mar'!F113 -> 2883.64 | F18: ='Abr'!F118 -> 2882.62 | G18: ='Mai'!F141 -> 2473.96 | H18: ='Jun'!F135 -> 703.71 | I18: =SUM(C18:H18) -> 14929.98
A19: 4.1.2.02.004 | B19: Serviços de Limpeza | C19: 0 | D19: 0 | E19: ='Mar'!F116 -> 2000 | F19: ='Abr'!F121 -> 2000 | G19: ='Mai'!F144 -> 2000 | H19: 0 | I19: =SUM(C19:H19) -> 6000
A20: 4.1.2.02.005 | B20: Manutenções Prediais | C20: ='Jan'!F134 -> 569 | D20: ='Fev'!F113 -> 2769 | E20: 0 | F20: ='Abr'!F123 -> 1453.58 | G20: ='Mai'!F146 -> -473.05 | H20: ='Jun'!F137 -> 1141 | I20: =SUM(C20:H20) -> 5459.53
A21: 4.1.2.04.001 | B21: Passagens Aereas e Rodoviárias | C21: ='Jan'!F136 -> 34210.65 | D21: ='Fev'!F116 -> 58359.7 | E21: ='Mar'!F118 -> 11862.57 | F21: ='Abr'!F128 -> 18995.22 | G21: ='Mai'!F152 -> 14261.79 | H21: ='Jun'!F142 -> 7153.7 | I21: =SUM(C21:H21) -> 144843.63
A22: 4.1.2.04.002 | B22: Lanches e Refeições | C22: ='Jan'!F143 -> 2333.82 | D22: ='Fev'!F127 -> 3814.37 | E22: ='Mar'!F122 -> 1131.89 | F22: ='Abr'!F136 -> 793.24 | G22: ='Mai'!F160 -> 1300.59 | H22: ='Jun'!F145 -> 1422.09 | I22: =SUM(C22:H22) -> 10796
A23: 4.1.2.04.003 | B23: Táxi ou Transportes Executivo | C23: ='Jan'!F146 -> 13412.1 | D23: ='Fev'!F134 -> 3387.44 | E23: ='Mar'!F132 -> 593.99 | F23: ='Abr'!F148 -> 236.84 | G23: ='Mai'!F166 -> 3812.63 | H23: ='Jun'!F160 -> 120.86 | I23: =SUM(C23:H23) -> 21563.86
A24: 4.1.2.04.004 | B24: Pedágio | C24: 0 | D24: ='Fev'!F150 -> 564.5 | E24: ='Mar'!F136 -> 33 | F24: 0 | G24: 0 | H24: 0 | I24: =SUM(C24:H24) -> 597.5
A25: 4.1.2.04.005 | B25: Hotel e Pousadas | C25: ='Jan'!F150 -> 3001.06 | D25: ='Fev'!F153 -> 182073.72 | E25: ='Mar'!F138 -> 3207.72 | F25: ='Abr'!F150 -> 4270.64 | G25: ='Mai'!F173 -> 3417.46 | H25: ='Jun'!F162 -> 3248.8 | I25: =SUM(C25:H25) -> 199219.4
A26: 4.1.2.04.006 | B26: Estacionamento | C26: 0 | D26: 0 | E26: ='Mar'!F142 -> 470 | F26: ='Abr'!F155 -> 193277.8 | G26: ='Mai'!F177 -> 994.76 | H26: 0 | I26: =SUM(C26:H26) -> 194742.56
A27: 4.1.2.04.007 | B27: Combustível | C27: ='Jan'!F153 -> 648.33 | D27: 0 | E27: 0 | F27: 0 | G27: 0 | H27: 0 | I27: =SUM(C27:H27) -> 648.33
A28: 4.1.2.05.001 | B28: Copa e Cozinha | C28: ='Jan'!F155 -> 4589.63 | D28: 0 | E28: ='Mar'!F144 -> 784.95 | F28: ='Abr'!F165 -> 1166.94 | G28: ='Mai'!F179 -> 1767.62 | H28: ='Jun'!F166 -> 1510.32 | I28: =SUM(C28:H28) -> 9819.46
A29: 4.1.2.05.002 | B29: Materiais de Limpeza | C29: ='Jan'!F164 -> 800 | D29: 0 | E29: ='Mar'!F147 -> 6 | F29: ='Abr'!F168 -> 130.6 | G29: ='Mai'!F182 -> 183.45 | H29: ='Jun'!F172 -> 121.25 | I29: =SUM(C29:H29) -> 1241.3
A30: 4.1.2.05.003 | B30: Material de Escritório | C30: ='Jan'!F166 -> 9494.44 | D30: ='Fev'!F157 -> 7452.94 | E30: ='Mar'!F149 -> 407.67 | F30: ='Abr'!F170 -> 206.49 | G30: ='Mai'!F185 -> 450.08 | H30: ='Jun'!F174 -> 519.01 | I30: =SUM(C30:H30) -> 18530.63
A31: 4.1.2.05.005 | B31: Cartório | C31: 0 | D31: 0 | E31: ='Mar'!F154 -> 240.66 | F31: ='Abr'!F173 -> 97.18 | G31: 0 | H31: 0 | I31: =SUM(C31:H31) -> 337.84
A32: 4.1.2.05.007 | B32: Feiras e Eventos | C32: ='Jan'!F176 -> 7000 | D32: ='Fev'!F164 -> 4544.97 | E32: ='Mar'!F157 -> 776.79 | F32: ='Abr'!F175 -> 11875.76 | G32: ='Mai'!F190 -> 4018.9 | H32: ='Jun'!F182 -> 557.7 | I32: =SUM(C32:H32) -> 28774.12
A33: 4.1.2.05.009 | B33: Bens de pequeno valor | C33: ='Jan'!F178 -> 1043.72 | D33: ='Fev'!F168 -> 1177.8 | E33: 0 | F33: 0 | G33: 0 | H33: ='Jun'!F184 -> 4465.87 | I33: =SUM(C33:H33) -> 6687.39
A34: 4.1.2.05.011 | B34: Mera importação | C34: 0 | D34: ='Fev'!F170 -> 267493.78 | E34: 0 | F34: 0 | G34: ='Mai'!F194 -> 8649.77 | H34: 0 | I34: =SUM(C34:H34) -> 276143.55
A35: 4.1.2.05.012 | B35: Fretes | C35: 0 | D35: 0 | E35: 0 | F35: 0 | G35: 0 | H35: ='Jun'!F189 -> 346.82 | I35: =SUM(C35:H35) -> 346.82
A36: 4.1.3.01.001 | B36: Publicidade e Propaganda | C36: ='Jan'!F180 -> 5400 | D36: ='Fev'!F212 -> 2060 | E36: ='Mar'!F160 -> 7464.74 | F36: ='Abr'!F179 -> 260 | G36: ='Mai'!F200 -> 995.26 | H36: ='Jun'!F191 -> 500 | I36: =SUM(C36:H36) -> 16680
A37: 4.1.3.01.002 | B37: Google Ads | C37: ='Jan'!F182 -> 507493.95 | D37: ='Fev'!F215 -> 587911.77 | E37: ='Mar'!F165 -> 832108.38 | F37: ='Abr'!F181 -> 714588.92 | G37: ='Mai'!F203 -> 1057894.2 | H37: ='Jun'!F193 -> 1182057.7 | I37: =SUM(C37:H37) -> 4882054.8
A38: 4.1.3.01.003 | B38: Facebook Ads | C38: ='Jan'!F184 -> 213859 | D38: ='Fev'!F217 -> 127102.17 | E38: ='Mar'!F167 -> 184568.47 | F38: ='Abr'!F183 -> 606552.85 | G38: ='Mai'!F205 -> 732474.29 | H38: ='Jun'!F195 -> 699509.67 | I38: =SUM(C38:H38) -> 2564066.5
A39: 4.1.3.01.004 | B39: Tiktok Ads | C39: ='Jan'!F186 -> 12376.9 | D39: 0 | E39: 0 | F39: 0 | G39: 0 | H39: 0 | I39: =SUM(C39:H39) -> 12376.9
A40: 4.1.3.01.005 | B40: Influenciadores | C40: ='Jan'!F188 -> 59878.64 | D40: ='Fev'!F219 -> 58230 | E40: ='Mar'!F169 -> 63542 | F40: ='Abr'!F185 -> 57095.5 | G40: ='Mai'!F207 -> 33854.5 | H40: ='Jun'!F197 -> 59310.11 | I40: =SUM(C40:H40) -> 331910.75
A41: 4.1.3.01.006 | B41: Microsoft Ads | C41: ='Jan'!F199 -> 35000 | D41: 0 | E41: ='Mar'!F182 -> 49131.91 | F41: 0 | G41: 0 | H41: 0 | I41: =SUM(C41:H41) -> 84131.91
A42: 4.1.3.01.007 | B42: Reddit Ads | C42: 0 | D42: 0 | E42: 0 | F42: 0 | G42: ='Mai'!F219 -> 28.98 | H42: ='Jun'!F208 -> 28.98 | I42: =SUM(C42:H42) -> 57.96
A43: 4.1.3.01.008 | B43: Linkedin Ads | C43: 0 | D43: 0 | E43: ='Mar'!F184 -> 51.21 | F43: ='Abr'!F196 -> 6869.98 | G43: ='Mai'!F221 -> 256.16 | H43: 0 | I43: =SUM(C43:H43) -> 7177.35
A44: 4.1.4.01.001 | B44: Taxa de Fiscalização e Licença e Funcionamento | C44: 0 | D44: 0 | E44: ='Mar'!F186 -> 197.5 | F44: 0 | G44: 0 | H44: 0 | I44: =SUM(C44:H44) -> 197.5
A45: 4.1.4.01.002 | B45: IPTU | C45: ='Jan'!F201 -> 7602.7 | D45: 0 | E45: 0 | F45: 0 | G45: 0 | H45: 0 | I45: =SUM(C45:H45) -> 7602.7
A46: 4.1.4.01.004 | B46: Taxas Municipais Diversas | C46: 0 | D46: ='Fev'!F230 -> 2509 | E46: 0 | F46: 0 | G46: 0 | H46: 0 | I46: =SUM(C46:H46) -> 2509
A47: 4.1.4.02.002 | B47: Taxas Estaduais Diversas | C47: 0 | D47: 0 | E47: 0 | F47: ='Abr'!F198 -> 7.52 | G47: 0 | H47: 0 | I47: =SUM(C47:H47) -> 7.52
A48: 4.1.4.03.001 | B48: Taxas Federais Diversas | C48: 0 | D48: 0 | E48: ='Mar'!F188 -> 260 | F48: ='Abr'!F200 -> 2640 | G48: ='Mai'!F223 -> 3860 | H48: 0 | I48: =SUM(C48:H48) -> 6760
A49: 4.1.5.01.003 | B49: Tarifa e Comissões Bancárias | C49: ='Jan'!F203 -> 77.07 | D49: ='Fev'!F232 -> 450.23 | E49: ='Mar'!F190 -> 17.86 | F49: 0 | G49: ='Mai'!F225 -> 662.05 | H49: ='Jun'!F210 -> 1145.49 | I49: =SUM(C49:H49) -> 2352.7
A50: 4.1.6.01.001 | B50: Serviços Contábeis | C50: ='Jan'!F205 -> 19289.18 | D50: ='Fev'!F235 -> 10309.18 | E50: ='Mar'!F192 -> 10309.18 | F50: ='Abr'!F207 -> 14209.18 | G50: ='Mai'!F227 -> 13309.18 | H50: ='Jun'!F214 -> 13309.18 | I50: =SUM(C50:H50) -> 80735.08
A51: 4.1.6.01.002 | B51: Serviços de Consultoria | C51: ='Jan'!F207 -> 41323.55 | D51: ='Fev'!F237 -> 12549.89 | E51: ='Mar'!F194 -> 12942.74 | F51: ='Abr'!F209 -> 9916 | G51: ='Mai'!F229 -> -5415.32 | H51: 0 | I51: =SUM(C51:H51) -> 71316.86
A52: 4.1.6.01.003 | B52: Serviços Jurídicos | C52: ='Jan'!F211 -> 7580 | D52: ='Fev'!F240 -> 10094.89 | E52: ='Mar'!F197 -> 11090 | F52: ='Abr'!F213 -> 9180 | G52: ='Mai'!F232 -> 11560 | H52: ='Jun'!F216 -> 8780 | I52: =SUM(C52:H52) -> 58284.89
A53: 4.1.6.01.005 | B53: Assessoria de Imprensa | C53: ='Jan'!F215 -> 7500 | D53: ='Fev'!F246 -> 7500 | E53: ='Mar'!F204 -> 7500 | F53: ='Abr'!F217 -> 7500 | G53: ='Mai'!F235 -> 7500 | H53: ='Jun'!F220 -> 7500 | I53: =SUM(C53:H53) -> 45000
A54: 4.1.6.01.007 | B54: Serviços de Terceiros - Internos | C54: ='Jan'!F217 -> 1091975.8 | D54: ='Fev'!F248 -> 402182.92 | E54: ='Mar'!F206 -> 780466.91 | F54: ='Abr'!F219 -> 433633.26 | G54: ='Mai'!F237 -> 841031.26 | H54: ='Jun'!F222 -> 780634.78 | I54: =SUM(C54:H54) -> 4329924.9
A55: 4.1.6.01.008 | B55: Serviços de Terceiros - Externos | C55: ='Jan'!F280 -> 26951.61 | D55: ='Fev'!F290 -> 28714.23 | E55: ='Mar'!F275 -> 27500 | F55: ='Abr'!F276 -> 27500 | G55: ='Mai'!F309 -> -2131 | H55: ='Jun'!F285 -> 120 | I55: =SUM(C55:H55) -> 108654.84
A56: 4.1.6.02.001 | B56: Cursos e Treinamentos | C56: ='Jan'!F283 -> 13800 | D56: ='Fev'!F293 -> 6760 | E56: ='Mar'!F277 -> 5780 | F56: ='Abr'!F278 -> 7160 | G56: ='Mai'!F312 -> 2580 | H56: ='Jun'!F287 -> 3600 | I56: =SUM(C56:H56) -> 39680
A57: 4.1.6.02.002 | B57: Auxílio Ifood | C57: ='Jan'!F287 -> 27890.01 | D57: ='Fev'!F297 -> 23711.09 | E57: ='Mar'!F280 -> 22350.95 | F57: ='Abr'!F281 -> 33307.14 | G57: ='Mai'!F317 -> 13889.39 | H57: ='Jun'!F289 -> 24241.2 | I57: =SUM(C57:H57) -> 145389.78
A58: 4.1.6.02.003 | B58: Despesas com Uniformes | C58: 0 | D58: ='Fev'!F299 -> 1000 | E58: 0 | F58: 0 | G58: ='Mai'!F320 -> 1500.01 | H58: 0 | I58: =SUM(C58:H58) -> 2500.01
A59: 4.1.6.02.004 | B59: Bônus - Internos | C59: 0 | D59: 0 | E59: 0 | F59: ='Abr'!F283 -> 45000 | G59: 0 | H59: ='Jun'!F294 -> 40686.62 | I59: =SUM(C59:H59) -> 85686.62
A60: 4.1.6.02.006 | B60: Beneficio Psicológico | C60: ='Jan'!F289 -> 3594 | D60: 0 | E60: ='Mar'!F282 -> -1797 | F60: 0 | G60: 0 | H60: ='Jun'!F296 -> 1874 | I60: =SUM(C60:H60) -> 3671
A61: 4.1.8.09.001 | B61: Brindes | C61: ='Jan'!F292 -> 2397.11 | D61: ='Fev'!F301 -> 126.7 | E61: ='Mar'!F284 -> 1945 | F61: ='Abr'!F285 -> 5154.73 | G61: ='Mai'!F322 -> 35449.9 | H61: ='Jun'!F298 -> 6786.18 | I61: =SUM(C61:H61) -> 51859.62
A62: 4.1.8.09.002 | B62: Confraternização | C62: ='Jan'!F296 -> 3431.15 | D62: ='Fev'!F304 -> 4484.09 | E62: ='Mar'!F287 -> 534 | F62: ='Abr'!F287 -> 171.84 | G62: ='Mai'!F325 -> 1940.65 | H62: ='Jun'!F307 -> 1109.01 | I62: =SUM(C62:H62) -> 11670.74
A63: 4.1.8.09.004 | B63: Despesa com Contingências | C63: 0 | D63: ='Fev'!F310 -> 1937.8 | E63: ='Mar'!F289 -> 1555.45 | F63: 0 | G63: ='Mai'!F331 -> 0 | H63: 0 | I63: =SUM(C63:H63) -> 3493.25
A64: 4.1.8.09.005 | B64: Despesa com Contingências | C64: 0 | D64: 0 | E64: 0 | F64: 0 | G64: ='Mai'!F333 -> 0 | H64: 0 | I64: =SUM(C64:H64) -> 0
A65: 4.1.8.10.001 | B65: Despesas Indedutíveis | C65: ='Jan'!F304 -> 32104.1 | D65: ='Fev'!F312 -> 142570.77 | E65: ='Mar'!F291 -> 4598.61 | F65: ='Abr'!F289 -> 2769.1 | G65: 0 | H65: 0 | I65: =SUM(C65:H65) -> 182042.58
A66: 4.1.8.10.002 | B66: Perdas Efetivas com Clientes | C66: ='Jan'!F308 -> 2925.67 | D66: 0 | E66: ='Mar'!F295 -> 474.4 | F66: 0 | G66: ='Mai'!F342 -> 2493.74 | H66: 0 | I66: =SUM(C66:H66) -> 5893.81
A67: 4.1.9.01.002 | B67: Perdas Efetivas com Clientes | C67: 0 | D67: 0 | E67: 0 | F67: ='Abr'!F291 -> 1570.59 | G67: 0 | H67: 0 | I67: =SUM(C67:H67) -> 1570.59
B68: TOTAL CUSTO (6.2) | C68: =SUM(C6,C7,C8,C9,C10) -> 1628450.1 | D68: =SUM(D6,D7,D8,D9,D10) -> 1044541.7 | E68: =SUM(E6,E7,E8,E9,E10) -> 1206209.8 | F68: =SUM(F6,F7,F8,F9,F10) -> 1228156.3 | G68: =SUM(G6,G7,G8,G9,G10) -> 1311911.8 | H68: =SUM(H6,H7,H8,H9,H10) -> 1472973.6 | I68: =SUM(C68:H68) -> 7892243.3
B69: TOTAL DESPESA (4.1) | C69: =SUM(C11,C12,C13,C14,C15,C16,C17,C18,C19,C20,C21,C22,C23,C24,C25,C26,C27,C28,C29,C30,C31,C32,C33,C34,C35,C36,C37,C38,C39,C40,C41,C42,C43,C44,C45,C46,C47,C48,C49,C50,C51,C52,C53,C54,C55,C56,C57,C58,C59,C60,C61,C62,C63,C64,C65,C66,C67) -> 2477385.6 | D69: =SUM(D11,D12,D13,D14,D15,D16,D17,D18,D19,D20,D21,D22,D23,D24,D25,D26,D27,D28,D29,D30,D31,D32,D33,D34,D35,D36,D37,D38,D39,D40,D41,D42,D43,D44,D45,D46,D47,D48,D49,D50,D51,D52,D53,D54,D55,D56,D57,D58,D59,D60,D61,D62,D63,D64,D65,D66,D67) -> 2061642.5 | E69: =SUM(E11,E12,E13,E14,E15,E16,E17,E18,E19,E20,E21,E22,E23,E24,E25,E26,E27,E28,E29,E30,E31,E32,E33,E34,E35,E36,E37,E38,E39,E40,E41,E42,E43,E44,E45,E46,E47,E48,E49,E50,E51,E52,E53,E54,E55,E56,E57,E58,E59,E60,E61,E62,E63,E64,E65,E66,E67) -> 2209911.3 | F69: =SUM(F11,F12,F13,F14,F15,F16,F17,F18,F19,F20,F21,F22,F23,F24,F25,F26,F27,F28,F29,F30,F31,F32,F33,F34,F35,F36,F37,F38,F39,F40,F41,F42,F43,F44,F45,F46,F47,F48,F49,F50,F51,F52,F53,F54,F55,F56,F57,F58,F59,F60,F61,F62,F63,F64,F65,F66,F67) -> 2503939.6 | G69: =SUM(G11,G12,G13,G14,G15,G16,G17,G18,G19,G20,G21,G22,G23,G24,G25,G26,G27,G28,G29,G30,G31,G32,G33,G34,G35,G36,G37,G38,G39,G40,G41,G42,G43,G44,G45,G46,G47,G48,G49,G50,G51,G52,G53,G54,G55,G56,G57,G58,G59,G60,G61,G62,G63,G64,G65,G66,G67) -> 3003204.9 | H69: =SUM(H11,H12,H13,H14,H15,H16,H17,H18,H19,H20,H21,H22,H23,H24,H25,H26,H27,H28,H29,H30,H31,H32,H33,H34,H35,H36,H37,H38,H39,H40,H41,H42,H43,H44,H45,H46,H47,H48,H49,H50,H51,H52,H53,H54,H55,H56,H57,H58,H59,H60,H61,H62,H63,H64,H65,H66,H67) -> 3113442.5 | I69: =SUM(C69:H69) -> 15369526
B70: TOTAL | C70: =C68+C69 -> 4105835.7 | D70: =D68+D69 -> 3106184.2 | E70: =E68+E69 -> 3416121.1 | F70: =F68+F69 -> 3732095.9 | G70: =G68+G69 -> 4315116.7 | H70: =H68+H69 -> 4586416.2 | I70: =SUM(C70:H70) -> 23261770
B71: Gerencial — custo (P&L oficial) | C71: 1021126.4 | D71: 1037755.6 | E71: 1158496.6 | F71: 1231075.9 | G71: 1323802.1 | H71: 1473722.3 | I71: =SUM(C71:H71) -> 7245978.9
B72: Gerencial — despesa (P&L oficial) | C72: 2029394.9 | D72: 1891722.3 | E72: 2172723.6 | F72: 2485367.1 | G72: 3050632.3 | H72: 3065504.4 | I72: =SUM(C72:H72) -> 14695345
B73: Diferença — custo (antes das notas explicativas) | C73: =C68-C71 -> 607323.67 | D73: =D68-D71 -> 6786.07 | E73: =E68-E71 -> 47713.17 | F73: =F68-F71 -> -2919.55 | G73: =G68-G71 -> -11890.33 | H73: =H68-H71 -> -748.67 | I73: =SUM(C73:H73) -> 646264.36
B74: Diferença — despesa (antes das notas explicativas) | C74: =C69-C72 -> 447990.77 | D74: =D69-D72 -> 169920.18 | E74: =E69-E72 -> 37187.68 | F74: =F69-F72 -> 18572.51 | G74: =G69-G72 -> -47427.37 | H74: =H69-H72 -> 47938.15 | I74: =SUM(C74:H74) -> 674181.92
A76: AJUSTE DESTA REVISÃO (soma dos lançamentos por conta)
A77: Conta | B77: Descrição | C77: Jan | D77: Fev | E77: Mar | F77: Abr | G77: Mai | H77: Jun | I77: Total
A78: 6.2.1.01.001 | B78: Custos com Serviços de Terceiros - Internos | C78: ='Jan'!E5 -> -7963 | D78: ='Fev'!E5 -> 139118.28 | E78: ='Mar'!E5 -> 99280 | F78: ='Abr'!E5 -> 144000 | G78: ='Mai'!E5 -> 93476.06 | H78: ='Jun'!E5 -> 134097.74 | I78: =SUM(C78:H78) -> 602009.08
A79: 6.2.1.01.003 | B79: Custos com Transações | C79: ='Jan'!E37 -> 60195.75 | D79: ='Fev'!E34 -> 55287.77 | E79: ='Mar'!E36 -> 65259.88 | F79: ='Abr'!E35 -> 64434.06 | G79: ='Mai'!E41 -> 59487.01 | H79: ='Jun'!E42 -> 57078.91 | I79: =SUM(C79:H79) -> 361743.38
A80: 6.2.1.03.001 | B80: Custo de Hospedagem e Infraestrutura (Cloud) | C80: ='Jan'!E39 -> 98168.68 | D80: ='Fev'!E36 -> -7281.44 | E80: ='Mar'!E38 -> 19109.2 | F80: ='Abr'!E37 -> -1303.57 | G80: ='Mai'!E43 -> 9412.35 | H80: ='Jun'!E44 -> 38558.37 | I80: =SUM(C80:H80) -> 156663.59
A81: 6.2.1.03.002 | B81: Custo de Licença de Sofware e Sistemas | C81: ='Jan'!E45 -> 0 | D81: ='Fev'!E41 -> 0 | E81: ='Mar'!E43 -> 4782.25 | F81: ='Abr'!E41 -> 0 | G81: ='Mai'!E50 -> -4782.25 | H81: ='Jun'!E53 -> 0 | I81: =SUM(C81:H81) -> 0
A82: 6.2.1.03.003 | B82: Custo de APIs de Terceiros | C82: ='Jan'!E71 -> 0 | D82: ='Fev'!E60 -> 55567.78 | E82: ='Mar'!E62 -> 98413.21 | F82: ='Abr'!E65 -> -36121.05 | G82: ='Mai'!E72 -> 375211.11 | H82: ='Jun'!E78 -> 3905.02 | I82: =SUM(C82:H82) -> 496976.07
A83: 4.1.2.01.003 | B83: Licença de Sofware e Sistemas (SaaS) | C83: ='Jan'!E94 -> 38961.8 | D83: ='Fev'!E79 -> 10001 | E83: ='Mar'!E83 -> -3118.84 | F83: ='Abr'!E85 -> 0 | G83: ='Mai'!E100 -> -171559.53 | H83: ='Jun'!E103 -> 57416.63 | I83: =SUM(C83:H83) -> -68298.94
A84: 4.1.2.04.001 | B84: Passagens Aereas e Rodoviárias | C84: ='Jan'!E136 -> 0 | D84: ='Fev'!E116 -> 3658.58 | E84: ='Mar'!E118 -> 0 | F84: ='Abr'!E128 -> -3658.58 | G84: ='Mai'!E152 -> 0 | H84: ='Jun'!E142 -> 0 | I84: =SUM(C84:H84) -> 0
A85: 4.1.2.05.011 | B85: Mera importação | C85: 0 | D85: ='Fev'!E170 -> -144317.28 | E85: 0 | F85: 0 | G85: ='Mai'!E194 -> 0 | H85: 0 | I85: =SUM(C85:H85) -> -144317.28
A86: 4.1.3.01.005 | B86: Influenciadores | C86: ='Jan'!E188 -> -6285.36 | D86: ='Fev'!E219 -> -45000 | E86: ='Mar'!E169 -> -1600 | F86: ='Abr'!E185 -> 0 | G86: ='Mai'!E207 -> 0 | H86: ='Jun'!E197 -> 0 | I86: =SUM(C86:H86) -> -52885.36
A87: 4.1.3.01.006 | B87: Microsoft Ads | C87: ='Jan'!E199 -> 0 | D87: 0 | E87: ='Mar'!E182 -> 49131.91 | F87: 0 | G87: 0 | H87: 0 | I87: =SUM(C87:H87) -> 49131.91
A88: 4.1.6.01.002 | B88: Serviços de Consultoria | C88: ='Jan'!E207 -> 0 | D88: ='Fev'!E237 -> -20368.78 | E88: ='Mar'!E194 -> -22501.95 | F88: ='Abr'!E209 -> -39790.21 | G88: ='Mai'!E229 -> 0 | H88: 0 | I88: =SUM(C88:H88) -> -82660.94
A89: 4.1.6.01.003 | B89: Serviços Jurídicos | C89: ='Jan'!E211 -> 0 | D89: ='Fev'!E240 -> 0 | E89: ='Mar'!E197 -> 0 | F89: ='Abr'!E213 -> 0 | G89: ='Mai'!E232 -> -573.4 | H89: ='Jun'!E216 -> 0 | I89: =SUM(C89:H89) -> -573.4
A90: 4.1.6.01.007 | B90: Serviços de Terceiros - Internos | C90: ='Jan'!E217 -> -8000 | D90: ='Fev'!E248 -> -30000 | E90: ='Mar'!E206 -> -60804.94 | F90: ='Abr'!E219 -> -192722 | G90: ='Mai'!E237 -> -80267.21 | H90: ='Jun'!E222 -> -107130 | I90: =SUM(C90:H90) -> -478924.15
A91: 4.1.6.02.002 | B91: Auxílio Ifood | C91: ='Jan'!E287 -> 0 | D91: ='Fev'!E297 -> 23711.09 | E91: ='Mar'!E280 -> 0 | F91: ='Abr'!E281 -> 0 | G91: ='Mai'!E317 -> 0 | H91: ='Jun'!E289 -> 0 | I91: =SUM(C91:H91) -> 23711.09
A92: 4.1.6.02.004 | B92: Bônus - Internos | C92: 0 | D92: 0 | E92: 0 | F92: ='Abr'!E283 -> 0 | G92: 0 | H92: ='Jun'!E294 -> 40686.62 | I92: =SUM(C92:H92) -> 40686.62
A93: 4.1.6.02.006 | B93: Beneficio Psicológico | C93: ='Jan'!E289 -> 0 | D93: 0 | E93: ='Mar'!E282 -> -1797 | F93: 0 | G93: 0 | H93: ='Jun'!E296 -> 0 | I93: =SUM(C93:H93) -> -1797
A94: 4.1.8.09.001 | B94: Brindes | C94: ='Jan'!E292 -> 0 | D94: ='Fev'!E301 -> -1467.02 | E94: ='Mar'!E284 -> 0 | F94: ='Abr'!E285 -> 0 | G94: ='Mai'!E322 -> 0 | H94: ='Jun'!E298 -> 0 | I94: =SUM(C94:H94) -> -1467.02
A95: 4.1.8.09.002 | B95: Confraternização | C95: ='Jan'!E296 -> -267 | D95: ='Fev'!E304 -> -40000 | E95: ='Mar'!E287 -> 0 | F95: ='Abr'!E287 -> 0 | G95: ='Mai'!E325 -> 0 | H95: ='Jun'!E307 -> 0 | I95: =SUM(C95:H95) -> -40267
A96: 4.1.8.09.004 | B96: Despesa com Contingências | C96: 0 | D96: ='Fev'!E310 -> 0 | E96: ='Mar'!E289 -> 0 | F96: 0 | G96: ='Mai'!E331 -> -336.78 | H96: 0 | I96: =SUM(C96:H96) -> -336.78
A97: 4.1.8.09.005 | B97: Despesa com Contingências | C97: 0 | D97: 0 | E97: 0 | F97: 0 | G97: ='Mai'!E333 -> -17434.34 | H97: 0 | I97: =SUM(C97:H97) -> -17434.34
B98: TOTAL CUSTO (6.2) | C98: =SUM(C78,C79,C80,C81,C82) -> 150401.43 | D98: =SUM(D78,D79,D80,D81,D82) -> 242692.39 | E98: =SUM(E78,E79,E80,E81,E82) -> 286844.54 | F98: =SUM(F78,F79,F80,F81,F82) -> 171009.44 | G98: =SUM(G78,G79,G80,G81,G82) -> 532804.28 | H98: =SUM(H78,H79,H80,H81,H82) -> 233640.04 | I98: =SUM(C98:H98) -> 1617392.1
B99: TOTAL DESPESA (4.1) | C99: =SUM(C83,C84,C85,C86,C87,C88,C89,C90,C91,C92,C93,C94,C95,C96,C97) -> 24409.44 | D99: =SUM(D83,D84,D85,D86,D87,D88,D89,D90,D91,D92,D93,D94,D95,D96,D97) -> -243782.41 | E99: =SUM(E83,E84,E85,E86,E87,E88,E89,E90,E91,E92,E93,E94,E95,E96,E97) -> -40690.82 | F99: =SUM(F83,F84,F85,F86,F87,F88,F89,F90,F91,F92,F93,F94,F95,F96,F97) -> -236170.79 | G99: =SUM(G83,G84,G85,G86,G87,G88,G89,G90,G91,G92,G93,G94,G95,G96,G97) -> -270171.26 | H99: =SUM(H83,H84,H85,H86,H87,H88,H89,H90,H91,H92,H93,H94,H95,H96,H97) -> -9026.75 | I99: =SUM(C99:H99) -> -775432.59
B100: TOTAL | C100: =C98+C99 -> 174810.87 | D100: =D98+D99 -> -1090.02 | E100: =E98+E99 -> 246153.72 | F100: =F98+F99 -> -65161.35 | G100: =G98+G99 -> 262633.02 | H100: =H98+H99 -> 224613.29 | I100: =SUM(C100:H100) -> 841959.53

Sheet Jan
A1: Janeiro/2026 — DRE contábil aberto por conta e fornecedor
A2: Cada conta do DRE com os fornecedores do razão (nome como está no livro da Syhus). "Como está" = razão de hoje. "Ajuste" = os lançamentos da aba O QUE FAZER (nº na coluna G). "Como deve ficar" = como a conta fica depois. Os subtotais e totais são fórmulas.
A4: Conta | B4: Descrição | C4: Fornecedor (razão) | D4: Como está | E4: Ajuste | F4: Como deve ficar | G4: Lançamento nº | H4: Observação
A5: 6.2.1.01.001 | B5: Custos com Serviços de Terceiros - Internos | C5: TOTAL DA CONTA | D5: =SUM(D6:D36) -> 647583.29 | E5: =SUM(E6:E36) -> -7963 | F5: =SUM(F6:F36) -> 639620.29
C6: LUCAS ARAUJO SANTOS CONSULTORIA E DESENVOLVIMENTO EM TECNOLOGIA DA INFORMAC | D6: 98591.7 | E6: -49296 | F6: =D6+E6 -> 49295.7 | G6: 2
C7: BEYAUT LTDA | D7: 0 | E7: 33333.33 | F7: =D7+E7 -> 33333.33 | G7: 12
C8: ALEXANDER MAX YOKOGAWA CONSULTORIA EM TECNOLOGIA DA INFORMACAO LTDA | D8: 63333.67 | E8: -31667 | F8: =D8+E8 -> 31666.67 | G8: 3 | H8: Tem R$ 12.667 de competência 2025: fica em 2026 (exercício encerrado), é nota explicativa.
C9: BLUE ENGENHARIA EM SOFTWARE LTDA | D9: 0 | E9: 22166.67 | F9: =D9+E9 -> 22166.67 | G9: 13
C10: IVAN P. DOS SANTOS LTDA | D10: 0 | E10: 17500 | F10: =D10+E10 -> 17500 | G10: 14
C11: CORE PRODUCT LTDA | D11: 49350 | E11: 0 | F11: =D11+E11 -> 49350
C12: LACERDA GUILHERME CONSULTORIA EM TECNOLOGIA DA INFORMACAO LTDA | D12: 33250 | E12: 0 | F12: =D12+E12 -> 33250
C13: DOUGLAS LIMA MACHADO 02831827094 | D13: 29851 | E13: 0 | F13: =D13+E13 -> 29851
C14: POLYANA CHAMAS FALCAO LTDA | D14: 28500 | E14: 0 | F14: =D14+E14 -> 28500 | H14: Tem R$ 9.500 de competência 2025: fica em 2026 (exercício encerrado), é nota explicativa.
C15: LEONARDO PIECHA CALDEIRA LTDA | D15: 26916.67 | E15: 0 | F15: =D15+E15 -> 26916.67 | H15: Tem R$ 9.917 de competência 2025: fica em 2026 (exercício encerrado), é nota explicativa.
C16: 36.256.578 CHRISTIAN RODRIGO CORRALES | D16: 26809.13 | E16: 0 | F16: =D16+E16 -> 26809.13 | H16: Tem R$ 13.125 de competência 2025: fica em 2026 (exercício encerrado), é nota explicativa.
C17: HIGOR SANTOS DE JESUS LTDA | D17: 25333.33 | E17: 0 | F17: =D17+E17 -> 25333.33 | H17: Tem R$ 9.333 de competência 2025: fica em 2026 (exercício encerrado), é nota explicativa.
C18: 50.202.927 FELIPE ALVES DA SILVA | D18: 23592.03 | E18: 0 | F18: =D18+E18 -> 23592.03 | H18: Tem R$ 11.550 de competência 2025: fica em 2026 (exercício encerrado), é nota explicativa.
C19: 54.652.017 JOAO VITOR DE MORAIS ROCHA | D19: 22500 | E19: 0 | F19: =D19+E19 -> 22500 | H19: Tem R$ 9.000 de competência 2025: fica em 2026 (exercício encerrado), é nota explicativa.
C20: BAS DIGITAL LTDA | D20: 21000 | E20: 0 | F20: =D20+E20 -> 21000 | H20: Tem R$ 7.000 de competência 2025: fica em 2026 (exercício encerrado), é nota explicativa.
C21: MARCOS THIAGO SILVESTRE DE MORAES CONSULTORIA EM TECNOLOGIA DA INFORMACAO LTDA | D21: 20000 | E21: 0 | F21: =D21+E21 -> 20000
C22: 61.806.165 MARILIA MARAGNO PEGORARO | D22: 19724.48 | E22: 0 | F22: =D22+E22 -> 19724.48
C23: THIAGO AUGUSTO DE OLIVEIRA TECNOLOGIA DA INFORMACAO LTDA | D23: 17500 | E23: 0 | F23: =D23+E23 -> 17500
C24: DANIEL GERONIMO DO AMARAL 02303012236 | D24: 14106.2 | E24: 0 | F24: =D24+E24 -> 14106.2 | H24: Tem R$ 6.906 de competência 2025: fica em 2026 (exercício encerrado), é nota explicativa.
C25: 4TECH DESENVOLVIMENTO DE SOFTWARES LTDA | D25: 14106.2 | E25: 0 | F25: =D25+E25 -> 14106.2 | H25: Tem R$ 6.906 de competência 2025: fica em 2026 (exercício encerrado), é nota explicativa.
C26: MARIA DE FATIMA BARBOSA CARDOSO DESENVOLVIMENTO DE SOFTWARE LTDA | D26: 13750 | E26: 0 | F26: =D26+E26 -> 13750 | H26: Tem R$ 2.750 de competência 2025: fica em 2026 (exercício encerrado), é nota explicativa.
C27: MARCELINO RAMOS DE AVELAR DESENVOLVIMENTO DE SOFTWARES LTDA | D27: 13064.52 | E27: 0 | F27: =D27+E27 -> 13064.52
C28: GUSTAVO HENRIQUE SILVA CONSULTORIA EM TECNOLOGIA DA INFORMACAO LTDA | D28: 13000 | E28: 0 | F28: =D28+E28 -> 13000
C29: JOSE RICARDO ALVES FIGUEIROA DESENVOLVIMENTO DE SOFTWARE LTDA | D29: 12500 | E29: 0 | F29: =D29+E29 -> 12500
C30: NORTHON VINICIOS CARDOSO SOARES LTDA | D30: 12000 | E30: 0 | F30: =D30+E30 -> 12000 | H30: Tem R$ 3.000 de competência 2025: fica em 2026 (exercício encerrado), é nota explicativa.
C31: Ivan Pedroso dos Santos - 46 | D31: 11666.67 | E31: 0 | F31: =D31+E31 -> 11666.67 | H31: Tem R$ 11.667 de competência 2025: fica em 2026 (exercício encerrado), é nota explicativa.
C32: MEANI DOS SANTOS FREITAS LTDA | D32: 11333.33 | E32: 0 | F32: =D32+E32 -> 11333.33 | H32: Tem R$ 2.833 de competência 2025: fica em 2026 (exercício encerrado), é nota explicativa.
C33: SAMUELSON DE BRITO MESQUITA 02197364219 | D33: 9000 | E33: 0 | F33: =D33+E33 -> 9000
C34: 50.836.277 DIEGO ALVES FERREIRA | D34: 7721.03 | E34: 0 | F34: =D34+E34 -> 7721.03 | H34: Tem R$ 3.780 de competência 2025: fica em 2026 (exercício encerrado), é nota explicativa.
C35: 62.516.834 DAVI GRACIANO NASCIMENTO COSTA | D35: 5333.33 | E35: 0 | F35: =D35+E35 -> 5333.33 | H35: Tem R$ 1.333 de competência 2025: fica em 2026 (exercício encerrado), é nota explicativa.
C36: LUIS EMANUEL RIGON ALDERETE DESENVOLVIMENTO DE SOFTWARE LTDA | D36: 3750 | E36: 0 | F36: =D36+E36 -> 3750 | H36: Tem R$ 1.250 de competência 2025: fica em 2026 (exercício encerrado), é nota explicativa.
A37: 6.2.1.01.003 | B37: Custos com Transações | C37: TOTAL DA CONTA | D37: =SUM(D38:D38) -> 22660.18 | E37: =SUM(E38:E38) -> 60195.75 | F37: =SUM(F38:F38) -> 82855.93
C38: PAGAR.ME INSTITUICAO DE PAGAMENTO S.A | D38: 22660.18 | E38: 60195.75 | F38: =D38+E38 -> 82855.93 | G38: 24
A39: 6.2.1.03.001 | B39: Custo de Hospedagem e Infraestrutura (Cloud) | C39: TOTAL DA CONTA | D39: =SUM(D40:D44) -> 123490.2 | E39: =SUM(E40:E44) -> 98168.68 | F39: =SUM(F40:F44) -> 221658.88
C40: AMAZON AWS SERVICOS BRASIL LTDA | D40: 107263.42 | E40: 95555.68 | F40: =D40+E40 -> 202819.1 | G40: 15 | H40: Tem R$ 107.263 de competência 2025: fica em 2026 (exercício encerrado), é nota explicativa.
C41: NT - 001/001 - GODADDY BRASIL | D41: 0 | E41: 2613 | F41: =D41+E41 -> 2613 | G41: 23
C42: GOOGLE CLOUD BRASIL COMPUTACAO E SERVICOS DE DADOS LTDA. | D42: 8933.75 | E42: 0 | F42: =D42+E42 -> 8933.75
C43: WEBSHARE* PROXY PLN YF | D43: 4286.73 | E43: 0 | F43: =D43+E43 -> 4286.73
C44: PADDLE | D44: 3006.3 | E44: 0 | F44: =D44+E44 -> 3006.3
A45: 6.2.1.03.002 | B45: Custo de Licença de Sofware e Sistemas | C45: TOTAL DA CONTA | D45: =SUM(D46:D70) -> 350882.47 | E45: =SUM(E46:E70) -> 0 | F45: =SUM(F46:F70) -> 350882.47
C46: DIGESTO PESQUISA E BANCO DE DADOS LTDA | D46: 138361.9 | E46: 0 | F46: =D46+E46 -> 138361.9 | H46: Tem R$ 138.362 de competência 2025: fica em 2026 (exercício encerrado), é nota explicativa.
C47: VIR SERVICOS DE INFORMACOES LTDA | D47: 84888.4 | E47: 0 | F47: =D47+E47 -> 84888.4 | H47: Tem R$ 84.888 de competência 2025: fica em 2026 (exercício encerrado), é nota explicativa.
C48: NOVA DD POSITIVO REPRESENTACOES LTDA. | D48: 39535.74 | E48: 0 | F48: =D48+E48 -> 39535.74 | H48: Tem R$ 39.536 de competência 2025: fica em 2026 (exercício encerrado), é nota explicativa.
C49: JUDIT TECNOLOGIA DA INFORMACAO LTDA | D49: 28491 | E49: 0 | F49: =D49+E49 -> 28491 | H49: Tem R$ 28.491 de competência 2025: fica em 2026 (exercício encerrado), é nota explicativa.
C50: APPCUES | D50: 20036.07 | E50: 0 | F50: =D50+E50 -> 20036.07 | H50: Tem R$ 20.036 de competência 2025: fica em 2026 (exercício encerrado), é nota explicativa.
C51: POTELO SISTEMAS DE INFORMACAO LTDA | D51: 10000 | E51: 0 | F51: =D51+E51 -> 10000
C52: METABASE INC | D52: 6897.5 | E52: 0 | F52: =D52+E52 -> 6897.5
C53: BAGOLIN E BASTIANELLO CONSULTORIA LTDA | D53: 6000 | E53: 0 | F53: =D53+E53 -> 6000 | H53: Tem R$ 3.000 de competência 2025: fica em 2026 (exercício encerrado), é nota explicativa.
C54: ATLASSIAN JIRA | D54: 4845.03 | E54: 0 | F54: =D54+E54 -> 4845.03
C55: TWILIO SEGMENT | D55: 2768.35 | E55: 0 | F55: =D55+E55 -> 2768.35
C56: OPENAI CHATGPT | D56: 1942.41 | E56: 0 | F56: =D56+E56 -> 1942.41
C57: FIGMA | D57: 1812.23 | E57: 0 | F57: =D57+E57 -> 1812.23
C58: GITHUB, INC. | D58: 1484.9 | E58: 0 | F58: =D58+E58 -> 1484.9 | H58: Tem R$ 1.426 de competência 2025: fica em 2026 (exercício encerrado), é nota explicativa.
C59: SELKI TECNOLOGIA LTDA | D59: 1141 | E59: 0 | F59: =D59+E59 -> 1141
C60: CARBIGDATA TECNOLOGIA E INTELIGENCIA S/A | D60: 720 | E60: 0 | F60: =D60+E60 -> 720
C61: NEW RELIC | D61: 617.69 | E61: 0 | F61: =D61+E61 -> 617.69
C62: SENTRY | D62: 476.1 | E62: 0 | F62: =D62+E62 -> 476.1
C63: DISCOURSE.ORG Parcela | D63: 158.97 | E63: 0 | F63: =D63+E63 -> 158.97
C64: LOVABLE | D64: 142.34 | E64: 0 | F64: =D64+E64 -> 142.34
C65: HOSTINGER Parcela | D65: 139.99 | E65: 0 | F65: =D65+E65 -> 139.99
C66: GROUPMAP *TEAMRETRO | D66: 138.42 | E66: 0 | F66: =D66+E66 -> 138.42
C67: ELEVENLABS | D67: 125.4 | E67: 0 | F67: =D67+E67 -> 125.4
C68: PLUGA | D68: 89 | E68: 0 | F68: =D68+E68 -> 89 | H68: Tem R$ 89 de competência 2025: fica em 2026 (exercício encerrado), é nota explicativa.
C69: CURSOR USAGE AUG | D69: 41.03 | E69: 0 | F69: =D69+E69 -> 41.03
C70: NVOIP PLATAF | D70: 29 | E70: 0 | F70: =D70+E70 -> 29
A71: 6.2.1.03.003 | B71: Custo de APIs de Terceiros | C71: TOTAL DA CONTA | D71: =SUM(D72:D79) -> 333432.53 | E71: =SUM(E72:E79) -> 0 | F71: =SUM(F72:F79) -> 333432.53
C72: DIGESTO PESQUISA E BANCO DE DADOS LTDA | D72: 143199 | E72: 0 | F72: =D72+E72 -> 143199
C73: VIR SERVICOS DE INFORMACOES LTDA | D73: 79732 | E73: 0 | F73: =D73+E73 -> 79732
C74: NOVA DD POSITIVO REPRESENTACOES LTDA. | D74: 42825 | E74: 0 | F74: =D74+E74 -> 42825
C75: JUDIT TECNOLOGIA DA INFORMACAO LTDA | D75: 35199 | E75: 0 | F75: =D75+E75 -> 35199
C76: BIG DATA SOLUCOES EM TECNOLOGIA DE INFORMATICA S.A. | D76: 20369 | E76: 0 | F76: =D76+E76 -> 20369
C77: DOCSALES Parcela | D77: 6228.43 | E77: 0 | F77: =D77+E77 -> 6228.43
C78: PAYPAL *PAYPROGLOBA | D78: 2976.42 | E78: 0 | F78: =D78+E78 -> 2976.42
C79: CODERABBIT | D79: 2903.68 | E79: 0 | F79: =D79+E79 -> 2903.68
A80: 4.1.1.01.001 | B80: Salários | C80: TOTAL DA CONTA | D80: =SUM(D81:D82) -> 5575.24 | E80: =SUM(E81:E82) -> 0 | F80: =SUM(F81:F82) -> 5575.24
C81: FRANCIELLE FERNANDA DA SILVA LAUDINO - 28 | D81: 5500 | E81: 0 | F81: =D81+E81 -> 5500 | H81: Tem R$ 5.500 de competência 2025: fica em 2026 (exercício encerrado), é nota explicativa.
C82: GIOVANA BASEGGIO DE AZAMBUJA - #9428319 | D82: 75.24 | E82: 0 | F82: =D82+E82 -> 75.24 | H82: Tem R$ 75 de competência 2025: fica em 2026 (exercício encerrado), é nota explicativa.
A83: 4.1.1.01.003 | B83: Bolsa Estágio | C83: TOTAL DA CONTA | D83: =SUM(D84:D84) -> 1300 | E83: =SUM(E84:E84) -> 0 | F83: =SUM(F84:F84) -> 1300
C84: Fopag: DIAS BOLSA AUXILIO 01/2026: - Rúbrica 8797 | D84: 1300 | E84: 0 | F84: =D84+E84 -> 1300
A85: 4.1.1.01.005 | B85: Férias | C85: TOTAL DA CONTA | D85: =SUM(D86:D86) -> 125 | E85: =SUM(E86:E86) -> 0 | F85: =SUM(F86:F86) -> 125
C86: Fopag: Valor da Provisão 01/2026: - Rúbrica 1 | D86: 125 | E86: 0 | F86: =D86+E86 -> 125
A87: 4.1.2.01.001 | B87: Telefonia e Internet | C87: TOTAL DA CONTA | D87: =SUM(D88:D93) -> 2897.76 | E87: =SUM(E88:E93) -> 0 | F87: =SUM(F88:F93) -> 2897.76
C88: Sim Digital - RVT - 9169271-3 | D88: 1099 | E88: 0 | F88: =D88+E88 -> 1099
C89: Avato - 173,453417,171 | D89: 995 | E89: 0 | F89: =D89+E89 -> 995
C90: BRASIL GESTORA DE OPERACOES S/A | D90: 379.24 | E90: 0 | F90: =D90+E90 -> 379.24
C91: STARLINK BRAZIL SERVICOS DE INTERNET LTDA. | D91: 235.52 | E91: 0 | F91: =D91+E91 -> 235.52
C92: Avato - 084133 | D92: 169 | E92: 0 | F92: =D92+E92 -> 169
C93: Avato - 0453416 | D93: 20 | E93: 0 | F93: =D93+E93 -> 20
A94: 4.1.2.01.003 | B94: Licença de Sofware e Sistemas (SaaS) | C94: TOTAL DA CONTA | D94: =SUM(D95:D126) -> 211153.86 | E94: =SUM(E95:E126) -> 38961.8 | F94: =SUM(F95:F126) -> 250115.66
C95: PPRO MICROSOFT | D95: 200.18 | E95: 19757.12 | F95: =D95+E95 -> 19957.3 | G95: 19
C96: WINGIFY | D96: 0 | E96: 13066.49 | F96: =D96+E96 -> 13066.49 | G96: 20
C97: NOTION LABS, INC. | D97: 0 | E97: 3314 | F97: =D97+E97 -> 3314 | G97: 21
C98: OMIEXPERIENCE LTDA. | D98: 3209.81 | E98: 2824.19 | F98: =D98+E98 -> 6034 | G98: 22
C99: HUBSPOT INC. | D99: 64323.22 | E99: 0 | F99: =D99+E99 -> 64323.22
C100: TREBLE.AI DO BRASIL SERVICOS DIGITAIS LTDA. | D100: 39421 | E100: 0 | F100: =D100+E100 -> 39421
C101: ZOHO CORPORATION BRASIL TECNOLOGIA LTDA. | D101: 25781.45 | E101: 0 | F101: =D101+E101 -> 25781.45
...

Sheet Fev
A1: Fevereiro/2026 — DRE contábil aberto por conta e fornecedor
A2: Cada conta do DRE com os fornecedores do razão (nome como está no livro da Syhus). "Como está" = razão de hoje. "Ajuste" = os lançamentos da aba O QUE FAZER (nº na coluna G). "Como deve ficar" = como a conta fica depois. Os subtotais e totais são fórmulas.
A4: Conta | B4: Descrição | C4: Fornecedor (razão) | D4: Como está | E4: Ajuste | F4: Como deve ficar | G4: Lançamento nº | H4: Observação
A5: 6.2.1.01.001 | B5: Custos com Serviços de Terceiros - Internos | C5: TOTAL DA CONTA | D5: =SUM(D6:D33) -> 331117.39 | E5: =SUM(E6:E33) -> 139118.28 | F5: =SUM(F6:F33) -> 470235.67
C6: L. A. B. CAMPOS LTDA | D6: 0 | E6: 30000 | F6: =D6+E6 -> 30000 | G6: 30
C7: DKSWEB DESENVOLVIMENTO DE SOFTWARE LTDA | D7: 0 | E7: 26000 | F7: =D7+E7 -> 26000 | G7: 31
C8: BEYAUT LTDA | D8: 0 | E8: 20000 | F8: =D8+E8 -> 20000 | G8: 33
C9: LACERDA GUILHERME CONSULTORIA EM TECNOLOGIA DA INFORMACAO LTDA | D9: 0 | E9: 19000 | F9: =D9+E9 -> 19000 | G9: 34
C10: ALEXANDER MAX YOKOGAWA CONSULTORIA EM TECNOLOGIA DA INFORMACAO LTDA | D10: 0 | E10: 19000 | F10: =D10+E10 -> 19000 | G10: 35
C11: THIAGO AUGUSTO DE OLIVEIRA TECNOLOGIA DA INFORMACAO LTDA | D11: 0 | E11: 17500 | F11: =D11+E11 -> 17500 | G11: 36
C12: DOUGLAS LIMA MACHADO 02831827094 | D12: 0 | E12: 7618.28 | F12: =D12+E12 -> 7618.28 | G12: 37
C13: Renato Sacramento Horta Moreira | D13: 50000 | E13: 0 | F13: =D13+E13 -> 50000
C14: CORE PRODUCT LTDA | D14: 50000 | E14: 0 | F14: =D14+E14 -> 50000
C15: POLYANA CHAMAS FALCAO LTDA | D15: 34607.14 | E15: 0 | F15: =D15+E15 -> 34607.14
C16: MARCOS THIAGO SILVESTRE DE MORAES CONSULTORIA EM TECNOLOGIA DA INFORMACAO LTDA | D16: 20000 | E16: 0 | F16: =D16+E16 -> 20000
C17: LEONARDO PIECHA CALDEIRA LTDA | D17: 17000 | E17: 0 | F17: =D17+E17 -> 17000
C18: HIGOR SANTOS DE JESUS LTDA | D18: 16000 | E18: 0 | F18: =D18+E18 -> 16000
C19: BAS DIGITAL LTDA | D19: 14000 | E19: 0 | F19: =D19+E19 -> 14000
C20: 36.256.578 CHRISTIAN RODRIGO CORRALES | D20: 13684.13 | E20: 0 | F20: =D20+E20 -> 13684.13
C21: 54.652.017 JOAO VITOR DE MORAIS ROCHA | D21: 13500 | E21: 0 | F21: =D21+E21 -> 13500
C22: GUSTAVO HENRIQUE SILVA CONSULTORIA EM TECNOLOGIA DA INFORMACAO LTDA | D22: 13000 | E22: 0 | F22: =D22+E22 -> 13000
C23: JOSE RICARDO ALVES FIGUEIROA DESENVOLVIMENTO DE SOFTWARE LTDA | D23: 12500 | E23: 0 | F23: =D23+E23 -> 12500
C24: 50.202.927 FELIPE ALVES DA SILVA | D24: 12042.03 | E24: 0 | F24: =D24+E24 -> 12042.03
... C33: LUIS EMANUEL RIGON ALDERETE DESENVOLVIMENTO DE SOFTWARE LTDA | D33: 2500 | E33: 0 | F33: =D33+E33 -> 2500
A34: 6.2.1.01.003 | B34: Custos com Transações | C34: TOTAL DA CONTA | D34: =SUM(D35:D35) -> 22010 | E34: =SUM(E35:E35) -> 55287.77 | F34: =SUM(F35:F35) -> 77297.77
C35: PAGAR.ME INSTITUICAO DE PAGAMENTO S.A | D35: 22010 | E35: 55287.77 | F35: =D35+E35 -> 77297.77 | G35: 44
A36: 6.2.1.03.001 | B36: Custo de Hospedagem e Infraestrutura (Cloud) | C36: TOTAL DA CONTA | D36: =SUM(D37:D40) -> 111623.7 | E36: =SUM(E37:E40) -> -7281.44 | F36: =SUM(F37:F40) -> 104342.26
C37: AMAZON AWS SERVICOS BRASIL LTDA | D37: 95555.68 | E37: -7281.44 | F37: =D37+E37 -> 88274.24 | G37: 38, 39
C38: GOOGLE CLOUD BRASIL COMPUTACAO E SERVICOS DE DADOS LTDA. | D38: 8759.48 | E38: 0 | F38: =D38+E38 -> 8759.48
C39: WEBSHARE* PROXY PLN YF | D39: 4047.69 | E39: 0 | F39: =D39+E39 -> 4047.69
C40: PADDLE | D40: 3260.85 | E40: 0 | F40: =D40+E40 -> 3260.85
A41: 6.2.1.03.002 | B41: Custo de Licença de Sofware e Sistemas | C41: TOTAL DA CONTA | D41: =SUM(D42:D59) -> 159560.04 | E41: =SUM(E42:E59) -> 0 | F41: =SUM(F42:F59) -> 159560.04
C42: VIR SERVICOS DE INFORMACOES LTDA | D42: 79731.8 | E42: 0 | F42: =D42+E42 -> 79731.8
C43: NOVA DD POSITIVO REPRESENTACOES LTDA. | D43: 44079.32 | E43: 0 | F43: =D43+E43 -> 44079.32
C44: POTELO SISTEMAS DE INFORMACAO LTDA | D44: 10000 | E44: 0 | F44: =D44+E44 -> 10000
C45: TWILIO SEGMENT | D45: 4789.62 | E45: 0 | F45: =D45+E45 -> 4789.62
C46: ATLASSIAN JIRA | D46: 4462.85 | E46: 0 | F46: =D46+E46 -> 4462.85
C47: METABASE INC | D47: 3400.62 | E47: 0 | F47: =D47+E47 -> 3400.62
C48: BAGOLIN E BASTIANELLO CONSULTORIA LTDA | D48: 3000 | E48: 0 | F48: =D48+E48 -> 3000
C49: OPENAI CHATGPT | D49: 2094.05 | E49: 0 | F49: =D49+E49 -> 2094.05
C50: FIGMA | D50: 1844.59 | E50: 0 | F50: =D50+E50 -> 1844.59
C51: DISCOURSE.ORG | D51: 1708.32 | E51: 0 | F51: =D51+E51 -> 1708.32
C52: GITHUB, INC. | D52: 1421.53 | E52: 0 | F52: =D52+E52 -> 1421.53
C53: Cleverbridge | D53: 1128.64 | E53: 0 | F53: =D53+E53 -> 1128.64
... C59: NVOIP PLATAF | D59: 29 | E59: 0 | F59: =D59+E59 -> 29
A60: 6.2.1.03.003 | B60: Custo de APIs de Terceiros | C60: TOTAL DA CONTA | D60: =SUM(D61:D69) -> 177538.15 | E60: =SUM(E61:E69) -> 55567.78 | F60: =SUM(F61:F69) -> 233105.93
C61: JUDIT TECNOLOGIA DA INFORMACAO LTDA | D61: -2343 | E61: 35199 | F61: =D61+E61 -> 32856 | G61: 29
C62: BIG DATA SOLUCOES EM TECNOLOGIA DE INFORMATICA S.A. | D62: 2133 | E62: 20368.78 | F62: =D62+E62 -> 22501.78 | G62: 32
C63: DIGESTO PESQUISA E BANCO DE DADOS LTDA | D63: 139999.9 | E63: 0 | F63: =D63+E63 -> 139999.9
C64: VIR SERVICOS DE INFORMACOES LTDA | D64: 10775 | E64: 0 | F64: =D64+E64 -> 10775
C65: DIGESTO - defasagem de 1 mês (padrão recorrente, ct 143.199 vs ger 151.942) | D65: 8743 | E65: 0 | F65: =D65+E65 -> 8743
C66: DOCSALES | D66: 6234.25 | E66: 0 | F66: =D66+E66 -> 6234.25
C67: PAYPAL *PAYPROGLOBA | D67: 5135.94 | E67: 0 | F67: =D67+E67 -> 5135.94
C68: NOVA DD POSITIVO REPRESENTACOES LTDA. | D68: 4042 | E68: 0 | F68: =D68+E68 -> 4042
C69: CODERABBIT | D69: 2818.06 | E69: 0 | F69: =D69+E69 -> 2818.06
A70: 4.1.1.01.003 | B70: Bolsa Estágio | C70: TOTAL DA CONTA | D70: =SUM(D71:D71) -> 1500 | E70: =SUM(E71:E71) -> 0 | F70: =SUM(F71:F71) -> 1500
C71: Fopag: DIAS BOLSA AUXILIO 02/2026: - Rúbrica 8797 | D71: 1500 | E71: 0 | F71: =D71+E71 -> 1500
A72: 4.1.1.01.005 | B72: Férias | C72: TOTAL DA CONTA | D72: =SUM(D73:D73) -> 125 | E72: =SUM(E73:E73) -> 0 | F72: =SUM(F73:F73) -> 125
C73: Fopag: Valor da Provisão 02/2026: - Rúbrica 1 | D73: 125 | E73: 0 | F73: =D73+E73 -> 125
A74: 4.1.2.01.001 | B74: Telefonia e Internet | C74: TOTAL DA CONTA | D74: =SUM(D75:D78) -> 2576.51 | E74: =SUM(E75:E78) -> 0 | F74: =SUM(F75:F78) -> 2576.51
C75: Avato | D75: 1184 | E75: 0 | F75: =D75+E75 -> 1184
C76: Sim Digital - RVT | D76: 1099 | E76: 0 | F76: =D76+E76 -> 1099
C77: STARLINK BRAZIL SERVICOS DE INTERNET LTDA. | D77: 235.52 | E77: 0 | F77: =D77+E77 -> 235.52
C78: BIANCA DA SILVEIRA LESSA PF | D78: 57.99 | E78: 0 | F78: =D78+E78 -> 57.99
A79: 4.1.2.01.003 | B79: Licença de Sofware e Sistemas (SaaS) | C79: TOTAL DA CONTA | D79: =SUM(D80:D105) -> 73488.94 | E79: =SUM(E80:E105) -> 10001 | F79: =SUM(F80:F105) -> 83489.94
C80: JOINVIXBRASIL SERVICOS DE INTERNET LTDA | D80: 5000 | E80: 10001 | F80: =D80+E80 -> 15001 | G80: 41
C81: MICROSOFT DO BRASIL IMPORTACAO E COMERCIO DE SOFTWARE E VIDEO GAMES LTDA | D81: 30000 | E81: 0 | F81: =D81+E81 -> 30000
C82: ZOHO CORPORATION BRASIL TECNOLOGIA LTDA. | D82: -21759.56 | E82: 0 | F82: =D82+E82 -> -21759.56
C83: WINGIFY | D83: 13226.53 | E83: 0 | F83: =D83+E83 -> 13226.53
C84: TESTES JUSFY | D84: 9074.28 | E84: 0 | F84: =D84+E84 -> 9074.28
C85: KAMINO INSTITUICAO DE PAGAMENTO LTDA | D85: 7920.24 | E85: 0 | F85: =D85+E85 -> 7920.24
C86: IPROYAL | D86: 5781.88 | E86: 0 | F86: =D86+E86 -> 5781.88
C87: LINKEDIN | D87: 5678.52 | E87: 0 | F87: =D87+E87 -> 5678.52
C88: CLOUD HUMANS TECNOLOGIA LTDA. | D88: 4855 | E88: 0 | F88: =D88+E88 -> 4855
C89: AUGMENT CODE | D89: 4416.94 | E89: 0 | F89: =D89+E89 -> 4416.94
C90: OMIEXPERIENCE LTDA. | D90: 3192.25 | E90: 0 | F90: =D90+E90 -> 3192.25
C91: SLACK | D91: 2384.54 | E91: 0 | F91: =D91+E91 -> 2384.54
C92: OBVIO BRASIL SOFTWARE E SERVICOS S.A. | D92: 1304 | E92: 0 | F92: =D92+E92 -> 1304
... C105: X CORP PAID FEATURES BASTROP TX | D105: 28.98 | E105: 0 | F105: =D105+E105 -> 28.98
A106: 4.1.2.02.001 | B106: Aluguel | C106: TOTAL DA CONTA | D106: =SUM(D107:D109) -> 9105.76 | E106: =SUM(E107:E109) -> 0 | F106: =SUM(F107:F109) -> 9105.76
C107: CAMARA DE DIRIGENTES LOJISTAS DE SANTA MARIA | D107: 4272.44 | E107: 0 | F107: =D107+E107 -> 4272.44
C108: TIMEWORK SERVICOS DE ESCRITORIO LTDA | D108: 2833.32 | E108: 0 | F108: =D108+E108 -> 2833.32
C109: CASTELBRAS DESIGN, COMUNICACAO E TECNOLOGIA DA INFORMACAO LTDA | D109: 2000 | E109: 0 | F109: =D109+E109 -> 2000
A110: 4.1.2.02.002 | B110: Energia Elétrica | C110: TOTAL DA CONTA | D110: =SUM(D111:D112) -> 3002.34 | E110: =SUM(E111:E112) -> 0 | F110: =SUM(F111:F112) -> 3002.34
C111: Celesc Distribuição | D111: 1813.05 | E111: 0 | F111: =D111+E111 -> 1813.05
C112: RGE ENERGIA ELETRICA Energia Elétrica 147058223 | D112: 1189.29 | E112: 0 | F112: =D112+E112 -> 1189.29
A113: 4.1.2.02.005 | B113: Manutenções Prediais | C113: TOTAL DA CONTA | D113: =SUM(D114:D115) -> 2769 | E113: =SUM(E114:E115) -> 0 | F113: =SUM(F114:F115) -> 2769
C114: CASA DAS PERSIANAS TRILHO SUISSO TELAS MOSQUITEIRAS | D114: 2200 | E114: 0 | F114: =D114+E114 -> 2200
C115: K. H. S. COMERCIO DE TECNOLOGIA LTDA | D115: 569 | E115: 0 | F115: =D115+E115 -> 569
A116: 4.1.2.04.001 | B116: Passagens Aereas e Rodoviárias | C116: TOTAL DA CONTA | D116: =SUM(D117:D126) -> 54701.12 | E116: =SUM(E117:E126) -> 3658.58 | F116: =SUM(F117:F126) -> 58359.7
C117: GOL LINHAS AEREAS INTELIGENTES S.A. | D117: 3049.5 | E117: 3049.5 | F117: =D117+E117 -> 6099 | G117: 42
C118: GOL LINHAS AEREAS | D118: 609.08 | E118: 609.08 | F118: =D118+E118 -> 1218.16 | G118: 43
C119: LATAM AIRLINES BRASIL | D119: 40374.94 | E119: 0 | F119: =D119+E119 -> 40374.94
C120: RENATO SACRAMENTO HORTA MOREIRA PF - #9424806 | D120: 5254.01 | E120: 0 | F120: =D120+E120 -> 5254.01
C121: RENATO SACRAMENTO HORTA MOREIRA PF - #9371125 | D121: 3982.98 | E121: 0 | F121: =D121+E121 -> 3982.98
C122: LUAN ANDREY VIEIRA PF - #9385569 | D122: 491.7 | E122: 0 | F122: =D122+E122 -> 491.7
C123: KAUAN SOUZA PORTELA PF | D123: 442.55 | E123: 0 | F123: =D123+E123 -> 442.55
C124: AZUL LINHAS AEREAS BRASILEIRAS S.A. | D124: 309.35 | E124: 0 | F124: =D124+E124 -> 309.35
C125: KAIO MARTINS DA SILVA PF | D125: 98.61 | E125: 0 | F125: =D125+E125 -> 98.61
C126: ELIZANGELA FERNANDES BORGES | D126: 88.4 | E126: 0 | F126: =D126+E126 -> 88.4
...

Sheet Mar
A1: Março/2026 — DRE contábil aberto por conta e fornecedor
A2: Cada conta do DRE com os fornecedores do razão (nome como está no livro da Syhus). "Como está" = razão de hoje. "Ajuste" = os lançamentos da aba O QUE FAZER (nº na coluna G). "Como deve ficar" = como a conta fica depois. Os subtotais e totais são fórmulas.
A4: Conta | B4: Descrição | C4: Fornecedor (razão) | D4: Como está | E4: Ajuste | F4: Como deve ficar | G4: Lançamento nº | H4: Observação
A5: 6.2.1.01.001 | B5: Custos com Serviços de Terceiros - Internos | C5: TOTAL DA CONTA | D5: =SUM(D6:D35) -> 380723.21 | E5: =SUM(E6:E35) -> 99280 | F5: =SUM(F6:F35) -> 480003.21
C6: L. A. B. CAMPOS LTDA | D6: 0 | E6: 30000 | F6: =D6+E6 -> 30000 | G6: 50
C7: DKSWEB DESENVOLVIMENTO DE SOFTWARE LTDA | D7: 0 | E7: 26000 | F7: =D7+E7 -> 26000 | G7: 51
C8: BEYAUT LTDA | D8: 0 | E8: 22000 | F8: =D8+E8 -> 22000 | G8: 53
C9: LACERDA GUILHERME CONSULTORIA EM TECNOLOGIA DA INFORMACAO LTDA | D9: 0 | E9: 21280 | F9: =D9+E9 -> 21280 | G9: 54
C10: CORE PRODUCT LTDA | D10: 50000 | E10: 0 | F10: =D10+E10 -> 50000
C11: LUCAS ROBERTO FRANZON PASSELI 43946514847 | D11: 38766.06 | E11: 0 | F11: =D11+E11 -> 38766.06 | H11: Tem R$ 7.560 de competência 2025: fica em 2026 (exercício encerrado), é nota explicativa.
C12: MARCOS THIAGO SILVESTRE DE MORAES CONSULTORIA EM TECNOLOGIA DA INFORMACAO LTDA | D12: 20000 | E12: 0 | F12: =D12+E12 -> 20000
C13: ALEXANDER MAX YOKOGAWA CONSULTORIA EM TECNOLOGIA DA INFORMACAO LTDA | D13: 19000 | E13: 0 | F13: =D13+E13 -> 19000
C14: LEONARDO PIECHA CALDEIRA LTDA | D14: 18700 | E14: 0 | F14: =D14+E14 -> 18700
C15: IVAN P. DOS SANTOS LTDA | D15: 17500 | E15: 0 | F15: =D15+E15 -> 17500
C16: THIAGO AUGUSTO DE OLIVEIRA TECNOLOGIA DA INFORMACAO LTDA | D16: 17500 | E16: 0 | F16: =D16+E16 -> 17500
C17: HIGOR SANTOS DE JESUS LTDA | D17: 16000 | E17: 0 | F17: =D17+E17 -> 16000
C18: 36.256.578 CHRISTIAN RODRIGO CORRALES | D18: 15736.75 | E18: 0 | F18: =D18+E18 -> 15736.75
C19: BAS DIGITAL LTDA | D19: 14000 | E19: 0 | F19: =D19+E19 -> 14000
C20: 54.652.017 JOAO VITOR DE MORAIS ROCHA | D20: 13500 | E20: 0 | F20: =D20+E20 -> 13500
C21: 65.279.421 JULIA THIESEN SCHERER | D21: 13000 | E21: 0 | F21: =D21+E21 -> 13000
C22: GUSTAVO HENRIQUE SILVA CONSULTORIA EM TECNOLOGIA DA INFORMACAO LTDA | D22: 13000 | E22: 0 | F22: =D22+E22 -> 13000
C23: JOSE RICARDO ALVES FIGUEIROA DESENVOLVIMENTO DE SOFTWARE LTDA | D23: 12500 | E23: 0 | F23: =D23+E23 -> 12500
... C35: 62.516.834 DAVI GRACIANO NASCIMENTO COSTA | D35: 4000 | E35: 0 | F35: =D35+E35 -> 4000
A36: 6.2.1.01.003 | B36: Custos com Transações | C36: TOTAL DA CONTA | D36: =SUM(D37:D37) -> 25001.26 | E36: =SUM(E37:E37) -> 65259.88 | F36: =SUM(F37:F37) -> 90261.14
C37: PAGAR.ME INSTITUICAO DE PAGAMENTO S.A | D37: 25001.26 | E37: 65259.88 | F37: =D37+E37 -> 90261.14 | G37: 62
A38: 6.2.1.03.001 | B38: Custo de Hospedagem e Infraestrutura (Cloud) | C38: TOTAL DA CONTA | D38: =SUM(D39:D42) -> 121274.58 | E38: =SUM(E39:E42) -> 19109.2 | F38: =SUM(F39:F42) -> 140383.78
C39: AMAZON AWS SERVICOS BRASIL LTDA | D39: 88274.24 | E39: 19109.2 | F39: =D39+E39 -> 107383.44 | G39: 55, 56
C40: GOOGLE CLOUD BRASIL COMPUTACAO E SERVICOS DE DADOS LTDA. | D40: 26860.75 | E40: 0 | F40: =D40+E40 -> 26860.75
C41: WEBSHARE RNW PROXY 42 | D41: 4002.91 | E41: 0 | F41: =D41+E41 -> 4002.91
C42: PADDLE | D42: 2136.68 | E42: 0 | F42: =D42+E42 -> 2136.68
A43: 6.2.1.03.002 | B43: Custo de Licença de Sofware e Sistemas | C43: TOTAL DA CONTA | D43: =SUM(D44:D61) -> 388452.89 | E43: =SUM(E44:E61) -> 4782.25 | F43: =SUM(F44:F61) -> 393235.14
C44: TWILIO SEGMENT | D44: 0 | E44: 4782.25 | F44: =D44+E44 -> 4782.25 | G44: 60
C45: DIGESTO PESQUISA E BANCO DE DADOS LTDA | D45: 151942.35 | E45: 0 | F45: =D45+E45 -> 151942.35
C46: VIR SERVICOS DE INFORMACOES LTDA | D46: 94428 | E46: 0 | F46: =D46+E46 -> 94428
C47: NOVA DD POSITIVO REPRESENTACOES LTDA. | D47: 47580.42 | E47: 0 | F47: =D47+E47 -> 47580.42
C48: JUDIT TECNOLOGIA DA INFORMACAO LTDA | D48: 37176.35 | E48: 0 | F48: =D48+E48 -> 37176.35
C49: CARBIGDATA TECNOLOGIA E INTELIGENCIA S/A | D49: 24060 | E49: 0 | F49: =D49+E49 -> 24060
C50: APPCUES | D50: 18827 | E50: 0 | F50: =D50+E50 -> 18827
C51: POTELO SISTEMAS DE INFORMACAO LTDA | D51: 10000 | E51: 0 | F51: =D51+E51 -> 10000
C52: BAGOLIN E BASTIANELLO CONSULTORIA LTDA | D52: 3000 | E52: 0 | F52: =D52+E52 -> 3000
C53: NRI*NEW RELIC | D53: 578.07 | E53: 0 | F53: =D53+E53 -> 578.07
C54: DIGITALOCEAN.COM | D54: 154.85 | E54: 0 | F54: =D54+E54 -> 154.85
C55: HOSTINGER | D55: 139.99 | E55: 0 | F55: =D55+E55 -> 139.99
C56: LOVABLE | D56: 134.55 | E56: 0 | F56: =D56+E56 -> 134.55
... C61: NF FATURA DIGITALOCEAN.COM | D61: 21.01 | E61: 0 | F61: =D61+E61 -> 21.01
A62: 6.2.1.03.003 | B62: Custo de APIs de Terceiros | C62: TOTAL DA CONTA | D62: =SUM(D63:D71) -> 3913.31 | E62: =SUM(E63:E71) -> 98413.21 | F62: =SUM(F63:F71) -> 102326.52
C63: NOVA DD POSITIVO REPRESENTACOES LTDA. | D63: -46867 | E63: 75911.26 | F63: =D63+E63 -> 29044.26 | G63: 57
C64: BIG DATA SOLUCOES EM TECNOLOGIA DE INFORMATICA S.A. | D64: 5585 | E64: 22501.95 | F64: =D64+E64 -> 28086.95 | G64: 52
C65: VIR SERVICOS DE INFORMACOES LTDA | D65: 12408 | E65: 0 | F65: =D65+E65 -> 12408
C66: DIGESTO PESQUISA E BANCO DE DADOS LTDA | D66: 10000 | E66: 0 | F66: =D66+E66 -> 10000
C67: JUDIT TECNOLOGIA DA INFORMACAO LTDA | D67: 9135 | E67: 0 | F67: =D67+E67 -> 9135
C68: DOCSALES | D68: 6273.23 | E68: 0 | F68: =D68+E68 -> 6273.23
C69: SELKI TECNOLOGIA LTDA | D69: 2948 | E69: 0 | F69: =D69+E69 -> 2948
C70: CODERABBIT | D70: 2744.72 | E70: 0 | F70: =D70+E70 -> 2744.72
C71: PAYPAL *PAYPROGLOBA | D71: 1686.36 | E71: 0 | F71: =D71+E71 -> 1686.36
A72: 4.1.1.01.003 | B72: Bolsa Estágio | C72: TOTAL DA CONTA | D72: =SUM(D73:D73) -> 1500 | E72: =SUM(E73:E73) -> 0 | F72: =SUM(F73:F73) -> 1500
C73: Fopag: DIAS BOLSA AUXILIO 03/2026: - Rúbrica 8797 | D73: 1500 | E73: 0 | F73: =D73+E73 -> 1500
A74: 4.1.1.01.005 | B74: Férias | C74: TOTAL DA CONTA | D74: =SUM(D75:D75) -> 125 | E74: =SUM(E75:E75) -> 0 | F74: =SUM(F75:F75) -> 125
C75: Fopag: Valor da Provisão 03/2026: - Rúbrica 1 | D75: 125 | E75: 0 | F75: =D75+E75 -> 125
A76: 4.1.2.01.001 | B76: Telefonia e Internet | C76: TOTAL DA CONTA | D76: =SUM(D77:D77) -> 235.52 | E76: =SUM(E77:E77) -> 0 | F76: =SUM(F77:F77) -> 235.52
C77: STARLINK BRAZIL SERVICOS DE INTERNET LTDA. | D77: 235.52 | E77: 0 | F77: =D77+E77 -> 235.52
A78: 4.1.2.01.002 | B78: Serviços e Equipamentos de TI | C78: TOTAL DA CONTA | D78: =SUM(D79:D82) -> 13957.29 | E78: =SUM(E79:E82) -> 0 | F78: =SUM(F79:F82) -> 13957.29
C79: ALIEXPRESS | D79: 11942.06 | E79: 0 | F79: =D79+E79 -> 11942.06
C80: DELL COMPUTADORES DO BRASIL LTDA | D80: 1604.39 | E80: 0 | F80: =D80+E80 -> 1604.39
C81: NF FATURA KABUM S.A. | D81: 220.87 | E81: 0 | F81: =D81+E81 -> 220.87
C82: NF FORNECEDOR SEM | D82: 189.97 | E82: 0 | F82: =D82+E82 -> 189.97
A83: 4.1.2.01.003 | B83: Licença de Sofware e Sistemas (SaaS) | C83: TOTAL DA CONTA | D83: =SUM(D84:D108) -> 132458.76 | E83: =SUM(E84:E108) -> -3118.84 | F83: =SUM(F84:F108) -> 129339.92
C84: CLOUD HUMANS TECNOLOGIA LTDA. | D84: 19170 | E84: -5400 | F84: =D84+E84 -> 13770 | G84: 46
C85: SLACK | D85: 0 | E85: 2281.16 | F85: =D85+E85 -> 2281.16 | G85: 61
C86: TREBLE.AI | D86: 39421.2 | E86: 0 | F86: =D86+E86 -> 39421.2
C87: TREBLE.AI DO BRASIL SERVICOS DIGITAIS LTDA. | D87: 17996 | E87: 0 | F87: =D87+E87 -> 17996
C88: MICROSOFT DO BRASIL IMPORTACAO E COMERCIO DE SOFTWARE E VIDEO GAMES LTDA | D88: 17490.06 | E88: 0 | F88: =D88+E88 -> 17490.06
C89: ZOHO CORPORATION BRASIL TECNOLOGIA LTDA. | D89: 9898.14 | E89: 0 | F89: =D89+E89 -> 9898.14
C90: KAMINO INSTITUICAO DE PAGAMENTO LTDA | D90: 7920.24 | E90: 0 | F90: =D90+E90 -> 7920.24
C91: JOINVIXBRASIL SERVICOS DE INTERNET LTDA | D91: 5000 | E91: 0 | F91: =D91+E91 -> 5000
C92: OMIEXPERIENCE LTDA. | D92: 4092.2 | E92: 0 | F92: =D92+E92 -> 4092.2
C93: AUGMENT CODE | D93: 2674.65 | E93: 0 | F93: =D93+E93 -> 2674.65
C94: TESTES JUSFY | D94: 2046.77 | E94: 0 | F94: =D94+E94 -> 2046.77
C95: DISCOURSE.ORG | D95: 1613.04 | E95: 0 | F95: =D95+E95 -> 1613.04
C96: OBVIO BRASIL SOFTWARE E SERVICOS S.A. | D96: 1304 | E96: 0 | F96: =D96+E96 -> 1304
C97: SPEED IO - SERVICOS ESPECIALIZADOS LTDA - | D97: 990 | E97: 0 | F97: =D97+E97 -> 990
... C108: SUPABASE INC | D108: 23.79 | E108: 0 | F108: =D108+E108 -> 23.79
A109: 4.1.2.02.001 | B109: Aluguel | C109: TOTAL DA CONTA | D109: =SUM(D110:D112) -> 17762.35 | E109: =SUM(E110:E112) -> 0 | F109: =SUM(F110:F112) -> 17762.35
C110: WEWORK SERVICOS DE ESCRITORIO LTDA. | D110: 11699.35 | E110: 0 | F110: =D110+E110 -> 11699.35
C111: CAMARA DE DIRIGENTES LOJISTAS DE SANTA MARIA | D111: 4063 | E111: 0 | F111: =D111+E111 -> 4063
C112: CASTELBRAS DESIGN, COMUNICACAO E TECNOLOGIA DA INFORMACAO LTDA | D112: 2000 | E112: 0 | F112: =D112+E112 -> 2000
A113: 4.1.2.02.002 | B113: Energia Elétrica | C113: TOTAL DA CONTA | D113: =SUM(D114:D115) -> 2883.64 | E113: =SUM(E114:E115) -> 0 | F113: =SUM(F114:F115) -> 2883.64
C114: CELESC DISTRIBUICAO S.A. | D114: 1856.71 | E114: 0 | F114: =D114+E114 -> 1856.71
C115: RGE SUL DISTRIBUIDORA DE ENERGIA S.A. | D115: 1026.93 | E115: 0 | F115: =D115+E115 -> 1026.93
A116: 4.1.2.02.004 | B116: Serviços de Limpeza | C116: TOTAL DA CONTA | D116: =SUM(D117:D117) -> 2000 | E116: =SUM(E117:E117) -> 0 | F116: =SUM(F117:F117) -> 2000
C117: ELISABETE DA SILVA PULHESE | D117: 2000 | E117: 0 | F117: =D117+E117 -> 2000
A118: 4.1.2.04.001 | B118: Passagens Aereas e Rodoviárias | C118: TOTAL DA CONTA | D118: =SUM(D119:D121) -> 11862.57 | E118: =SUM(E119:E121) -> 0 | F118: =SUM(F119:F121) -> 11862.57
C119: TAM LINHAS AEREAS S/A. | D119: 8376.58 | E119: 0 | F119: =D119+E119 -> 8376.58
C120: GOL LINHAS AEREAS INTELIGENTES S.A. | D120: 2876.91 | E120: 0 | F120: =D120+E120 -> 2876.91
C121: GOL LINHAS AEREAS S.A. | D121: 609.08 | E121: 0 | F121: =D121+E121 -> 609.08
A122: 4.1.2.04.002 | B122: Lanches e Refeições | C122: TOTAL DA CONTA | D122: =SUM(D123:D131) -> 1131.89 | E122: =SUM(E123:E131) -> 0 | F122: =SUM(F123:F131) -> 1131.89
C123: NF 000454488 STANGHERLIN SUPERMERCADOS LTDA | D123: 264.08 | E123: 0 | F123: =D123+E123 -> 264.08
C124: NF RECIBO ESTACAO RODOVIARIA SANTA MARIA LTDA | D124: 242.8 | E124: 0 | F124: =D124+E124 -> 242.8
C125: NF 000467365 STANGHERLIN SUPERMERCADOS LTDA | D125: 189.74 | E125: 0 | F125: =D125+E125 -> 189.74
C126: NF 000308268 STANGHERLIN SUPERMERCADOS LTDA | D126: 149.44 | E126: 0 | F126: =D126+E126 -> 149.44
...

Sheet Abr
A1: Abril/2026 — DRE contábil aberto por conta e fornecedor
A2: Cada conta do DRE com os fornecedores do razão (nome como está no livro da Syhus). "Como está" = razão de hoje. "Ajuste" = os lançamentos da aba O QUE FAZER (nº na coluna G). "Como deve ficar" = como a conta fica depois. Os subtotais e totais são fórmulas.
A4: Conta | B4: Descrição | C4: Fornecedor (razão) | D4: Como está | E4: Ajuste | F4: Como deve ficar | G4: Lançamento nº | H4: Observação
A5: 6.2.1.01.001 | B5: Custos com Serviços de Terceiros - Internos | C5: TOTAL DA CONTA | D5: =SUM(D6:D34) -> 265310.42 | E5: =SUM(E6:E34) -> 144000 | F5: =SUM(F6:F34) -> 409310.42
C6: GABRIELA BORCA SERVICOS DE APOIO ADMINISTRATIVO LTDA | D6: -35000 | E6: 35000 | F6: =D6+E6 -> 0 | G6: 63
C7: L. A. B. CAMPOS LTDA | D7: 0 | E7: 30000 | F7: =D7+E7 -> 30000 | G7: 64
C8: DKSWEB DESENVOLVIMENTO DE SOFTWARE LTDA | D8: 0 | E8: 26000 | F8: =D8+E8 -> 26000 | G8: 66
C9: BEYAUT LTDA | D9: 0 | E9: 22000 | F9: =D9+E9 -> 22000 | G9: 67
C10: IVAN P. DOS SANTOS LTDA | D10: 0 | E10: 17500 | F10: =D10+E10 -> 17500 | G10: 68
C11: BATISTA SOLUCOES EM TECNOLOGIA LTDA | D11: 0 | E11: 13500 | F11: =D11+E11 -> 13500 | G11: 69
C12: CORE PRODUCT LTDA | D12: 50000 | E12: 0 | F12: =D12+E12 -> 50000
C13: MARCOS THIAGO SILVESTRE DE MORAES CONSULTORIA EM TECNOLOGIA DA INFORMACAO LTDA | D13: 20000 | E13: 0 | F13: =D13+E13 -> 20000
C14: ALEXANDER MAX YOKOGAWA CONSULTORIA EM TECNOLOGIA DA INFORMACAO LTDA | D14: 19000 | E14: 0 | F14: =D14+E14 -> 19000
C15: LEONARDO PIECHA CALDEIRA LTDA | D15: 18700 | E15: 0 | F15: =D15+E15 -> 18700
C16: THIAGO AUGUSTO DE OLIVEIRA TECNOLOGIA DA INFORMACAO LTDA | D16: 17500 | E16: 0 | F16: =D16+E16 -> 17500
C17: HIGOR SANTOS DE JESUS LTDA | D17: 16000 | E17: 0 | F17: =D17+E17 -> 16000
C18: 36.256.578 CHRISTIAN RODRIGO CORRALES | D18: 15736.75 | E18: 0 | F18: =D18+E18 -> 15736.75
C19: 50.202.927 FELIPE ALVES DA SILVA | D19: 15253.24 | E19: 0 | F19: =D19+E19 -> 15253.24
C20: BAS DIGITAL LTDA | D20: 14000 | E20: 0 | F20: =D20+E20 -> 14000
C21: 54.652.017 JOAO VITOR DE MORAIS ROCHA | D21: 13500 | E21: 0 | F21: =D21+E21 -> 13500
C22: GUSTAVO HENRIQUE SILVA CONSULTORIA EM TECNOLOGIA DA INFORMACAO LTDA | D22: 13000 | E22: 0 | F22: =D22+E22 -> 13000
C23: JOSE RICARDO ALVES FIGUEIROA DESENVOLVIMENTO DE SOFTWARE LTDA | D23: 12500 | E23: 0 | F23: =D23+E23 -> 12500
... C34: SWILE DO BRASIL S.A. | D34: 2102.31 | E34: 0 | F34: =D34+E34 -> 2102.31
A35: 6.2.1.01.003 | B35: Custos com Transações | C35: TOTAL DA CONTA | D35: =SUM(D36:D36) -> 23802.94 | E35: =SUM(E36:E36) -> 64434.06 | F35: =SUM(F36:F36) -> 88237
C36: PAGAR.ME INSTITUICAO DE PAGAMENTO S.A | D36: 23802.94 | E36: 64434.06 | F36: =D36+E36 -> 88237 | G36: 79
A37: 6.2.1.03.001 | B37: Custo de Hospedagem e Infraestrutura (Cloud) | C37: TOTAL DA CONTA | D37: =SUM(D38:D40) -> 271058.44 | E37: =SUM(E38:E40) -> -1303.57 | F37: =SUM(F38:F40) -> 269754.87
C38: AMAZON AWS SERVICOS BRASIL LTDA | D38: 107383.44 | E38: -1303.57 | F38: =D38+E38 -> 106079.87 | G38: 71, 77
C39: GOOGLE CLOUD BRASIL COMPUTACAO E SERVICOS DE DADOS LTDA. | D39: 161612.46 | E39: 0 | F39: =D39+E39 -> 161612.46
C40: PADDLE | D40: 2062.54 | E40: 0 | F40: =D40+E40 -> 2062.54
A41: 6.2.1.03.002 | B41: Custo de Licença de Sofware e Sistemas | C41: TOTAL DA CONTA | D41: =SUM(D42:D64) -> 385424.66 | E41: =SUM(E42:E64) -> 0 | F41: =SUM(F42:F64) -> 385424.66
C42: DIGESTO PESQUISA E BANCO DE DADOS LTDA | D42: 161483.1 | E42: 0 | F42: =D42+E42 -> 161483.1
C43: VIR SERVICOS DE INFORMACOES LTDA | D43: 102915 | E43: 0 | F43: =D43+E43 -> 102915
C44: CARBIGDATA TECNOLOGIA E INTELIGENCIA S/A | D44: 42504 | E44: 0 | F44: =D44+E44 -> 42504
C45: JUDIT TECNOLOGIA DA INFORMACAO LTDA | D45: 41990.75 | E45: 0 | F45: =D45+E45 -> 41990.75
C46: POTELO SISTEMAS DE INFORMACAO LTDA | D46: 10000 | E46: 0 | F46: =D46+E46 -> 10000
C47: TWILIO SEGMENT | D47: 4578.7 | E47: 0 | F47: =D47+E47 -> 4578.7
C48: OPENAI CHATGPT | D48: 4082.46 | E48: 0 | F48: =D48+E48 -> 4082.46
C49: ATLASSIAN | D49: 4010.81 | E49: 0 | F49: =D49+E49 -> 4010.81
C50: METABASE INC | D50: 3355.87 | E50: 0 | F50: =D50+E50 -> 3355.87
C51: BAGOLIN E BASTIANELLO CONSULTORIA LTDA | D51: 3000 | E51: 0 | F51: =D51+E51 -> 3000
C52: SELKI TECNOLOGIA LTDA | D52: 2948 | E52: 0 | F52: =D52+E52 -> 2948
C53: FIGMA | D53: 1804.54 | E53: 0 | F53: =D53+E53 -> 1804.54
... C64: APPCUES | D64: 0.03 | E64: 0 | F64: =D64+E64 -> 0.03
A65: 6.2.1.03.003 | B65: Custo de APIs de Terceiros | C65: TOTAL DA CONTA | D65: =SUM(D66:D74) -> 111550.43 | E65: =SUM(E66:E74) -> -36121.05 | F65: =SUM(F66:F74) -> 75429.38
C66: NOVA DD POSITIVO REPRESENTACOES LTDA. | D66: 120785.2 | E66: -75911.26 | F66: =D66+E66 -> 44873.94 | G66: 72
C67: BIG DATA SOLUCOES EM TECNOLOGIA DE INFORMATICA S.A. | D67: -8404 | E67: 28087.17 | F67: =D67+E67 -> 19683.17 | G67: 65
C68: DATACUBE SERVICO DE INFORMACAO VIA WEB LTDA | D68: 0 | E68: 11703.04 | F68: =D68+E68 -> 11703.04 | G68: 70
C69: VIR SERVICOS DE INFORMACOES LTDA | D69: -19241 | E69: 0 | F69: =D69+E69 -> -19241
C70: DIGESTO PESQUISA E BANCO DE DADOS LTDA | D70: 11483 | E70: 0 | F70: =D70+E70 -> 11483
C71: JUDIT TECNOLOGIA DA INFORMACAO LTDA | D71: -7005 | E71: 0 | F71: =D71+E71 -> -7005
C72: DOCSALES | D72: 6226.92 | E72: 0 | F72: =D72+E72 -> 6226.92
C73: PAYPAL *PAYPROGLOBA | D73: 4859.4 | E73: 0 | F73: =D73+E73 -> 4859.4
C74: CODERABBIT | D74: 2845.91 | E74: 0 | F74: =D74+E74 -> 2845.91
A75: 4.1.1.01.003 | B75: Bolsa Estágio | C75: TOTAL DA CONTA | D75: =SUM(D76:D76) -> 1500 | E75: =SUM(E76:E76) -> 0 | F75: =SUM(F76:F76) -> 1500
C76: Fopag: DIAS BOLSA AUXILIO 04/2026: - Rúbrica 8797 | D76: 1500 | E76: 0 | F76: =D76+E76 -> 1500
A77: 4.1.1.01.005 | B77: Férias | C77: TOTAL DA CONTA | D77: =SUM(D78:D78) -> 125 | E77: =SUM(E78:E78) -> 0 | F77: =SUM(F78:F78) -> 125
C78: Fopag: Valor da Provisão 04/2026: - Rúbrica 1 | D78: 125 | E78: 0 | F78: =D78+E78 -> 125
A79: 4.1.2.01.001 | B79: Telefonia e Internet | C79: TOTAL DA CONTA | D79: =SUM(D80:D81) -> 345.42 | E79: =SUM(E80:E81) -> 0 | F79: =SUM(F80:F81) -> 345.42
C80: STARLINK BRAZIL SERVICOS DE INTERNET LTDA. | D80: 235.52 | E80: 0 | F80: =D80+E80 -> 235.52
C81: RVT SERVICOS DE TELECOMUNICACOES LTDA | D81: 109.9 | E81: 0 | F81: =D81+E81 -> 109.9
A82: 4.1.2.01.002 | B82: Serviços e Equipamentos de TI | C82: TOTAL DA CONTA | D82: =SUM(D83:D84) -> 1744.29 | E82: =SUM(E83:E84) -> 0 | F82: =SUM(F83:F84) -> 1744.29
C83: DELL COMPUTADORES DO BRASIL LTDA | D83: 1604.39 | E83: 0 | F83: =D83+E83 -> 1604.39
C84: EBAZAR.COM.BR. LTDA | D84: 139.9 | E84: 0 | F84: =D84+E84 -> 139.9
A85: 4.1.2.01.003 | B85: Licença de Sofware e Sistemas (SaaS) | C85: TOTAL DA CONTA | D85: =SUM(D86:D113) -> 258182.39 | E85: =SUM(E86:E113) -> 0 | F85: =SUM(F86:F113) -> 258182.39
C86: MICROSOFT DO BRASIL IMPORTACAO E COMERCIO DE SOFTWARE E VIDEO GAMES LTDA | D86: 68263.43 | E86: 0 | F86: =D86+E86 -> 68263.43
C87: HUBSPOT INC. | D87: 66947.53 | E87: 0 | F87: =D87+E87 -> 66947.53
C88: TREBLE.AI DO BRASIL SERVICOS DIGITAIS LTDA. | D88: 56614 | E88: 0 | F88: =D88+E88 -> 56614
C89: CLOUD HUMANS TECNOLOGIA LTDA. | D89: 18624.96 | E89: 0 | F89: =D89+E89 -> 18624.96
C90: ZOHO CORPORATION BRASIL TECNOLOGIA LTDA. | D90: 10503.42 | E90: 0 | F90: =D90+E90 -> 10503.42
C91: KAMINO INSTITUICAO DE PAGAMENTO LTDA | D91: 8903.4 | E91: 0 | F91: =D91+E91 -> 8903.4
C92: IPROYAL | D92: 5802.46 | E92: 0 | F92: =D92+E92 -> 5802.46
C93: AUGMENT CODE | D93: 5422.7 | E93: 0 | F93: =D93+E93 -> 5422.7
C94: JOINVIXBRASIL SERVICOS DE INTERNET LTDA | D94: 5000 | E94: 0 | F94: =D94+E94 -> 5000
C95: OMIEXPERIENCE LTDA. | D95: 3200.19 | E95: 0 | F95: =D95+E95 -> 3200.19
C96: SLACK | D96: 2213.63 | E96: 0 | F96: =D96+E96 -> 2213.63
C97: DISCOURSE.ORG | D97: 1595.22 | E97: 0 | F97: =D97+E97 -> 1595.22
... C113: TESTES JUSFY | D113: 20.16 | E113: 0 | F113: =D113+E113 -> 20.16
A114: 4.1.2.02.001 | B114: Aluguel | C114: TOTAL DA CONTA | D114: =SUM(D115:D117) -> 19568.98 | E114: =SUM(E115:E117) -> 0 | F114: =SUM(F115:F117) -> 19568.98
C115: WEWORK SERVICOS DE ESCRITORIO LTDA. | D115: 13251.5 | E115: 0 | F115: =D115+E115 -> 13251.5
C116: CAMARA DE DIRIGENTES LOJISTAS DE SANTA MARIA | D116: 4317.48 | E116: 0 | F116: =D116+E116 -> 4317.48
C117: CASTELBRAS DESIGN, COMUNICACAO E TECNOLOGIA DA INFORMACAO LTDA | D117: 2000 | E117: 0 | F117: =D117+E117 -> 2000
A118: 4.1.2.02.002 | B118: Energia Elétrica | C118: TOTAL DA CONTA | D118: =SUM(D119:D120) -> 2882.62 | E118: =SUM(E119:E120) -> 0 | F118: =SUM(F119:F120) -> 2882.62
C119: CELESC DISTRIBUICAO S.A. | D119: 1930.82 | E119: 0 | F119: =D119+E119 -> 1930.82
C120: RGE SUL DISTRIBUIDORA DE ENERGIA S.A. | D120: 951.8 | E120: 0 | F120: =D120+E120 -> 951.8
A121: 4.1.2.02.004 | B121: Serviços de Limpeza | C121: TOTAL DA CONTA | D121: =SUM(D122:D122) -> 2000 | E121: =SUM(E122:E122) -> 0 | F121: =SUM(F122:F122) -> 2000
C122: ELISABETE DA SILVA PULHESE | D122: 2000 | E122: 0 | F122: =D122+E122 -> 2000
A123: 4.1.2.02.005 | B123: Manutenções Prediais | C123: TOTAL DA CONTA | D123: =SUM(D124:D127) -> 1453.58 | E123: =SUM(E124:E127) -> 0 | F123: =SUM(F124:F127) -> 1453.58
C124: K. H. S. COMERCIO DE TECNOLOGIA LTDA | D124: 1138 | E124: 0 | F124: =D124+E124 -> 1138
C125: 36.209.065 ANDREA DA COSTA LEMES | D125: 255 | E125: 0 | F125: =D125+E125 -> 255
C126: CASA ONLINE COMERCIO E VAREJO LTDA | D126: 39.28 | E126: 0 | F126: =D126+E126 -> 39.28
C127: ROSA MATERIAL DE CONSTRUCAO LTDA | D127: 21.3 | E127: 0 | F127: =D127+E127 -> 21.3
A128: 4.1.2.04.001 | B128: Passagens Aereas e Rodoviárias | C128: TOTAL DA CONTA | D128: =SUM(D129:D135) -> 22653.8 | E128: =SUM(E129:E135) -> -3658.58 | F128: =SUM(F129:F135) -> 18995.22
C129: GOL LINHAS AEREAS INTELIGENTES S.A. | D129: 3049.5 | E129: -3049.5 | F129: =D129+E129 -> 0 | G129: 75
C130: GOL LINHAS AEREAS | D130: 609.08 | E130: -609.08 | F130: =D130+E130 -> 0 | G130: 76
C131: NF FATURA TAM LINHAS AEREAS S/A. | D131: 7645.23 | E131: 0 | F131: =D131+E131 -> 7645.23
C132: TAM LINHAS AEREAS S/A. | D132: 7306.28 | E132: 0 | F132: =D132+E132 -> 7306.28
C133: LATAM AIRLINES BRASIL | D133: 1702.13 | E133: 0 | F133: =D133+E133 -> 1702.13
C134: NF 10157328 22793 CONSULTORIA EM TECNOLOGIA DA INFORMACAO LTDA | D134: 1675.35 | E134: 0 | F134: =D134+E134 -> 1675.35
C135: AZUL LINHAS AEREAS BRASILEIRAS S.A. | D135: 666.23 | E135: 0 | F135: =D135+E135 -> 666.23
A136: 4.1.2.04.002 | B136: Lanches e Refeições | C136: TOTAL DA CONTA | D136: =SUM(D137:D147) -> 793.24 | E136: =SUM(E137:E147) -> 0 | F136: =SUM(F137:F147) -> 793.24
...

Sheet Mai
A1: Maio/2026 — DRE contábil aberto por conta e fornecedor
A2: Cada conta do DRE com os fornecedores do razão (nome como está no livro da Syhus). "Como está" = razão de hoje. "Ajuste" = os lançamentos da aba O QUE FAZER (nº na coluna G). "Como deve ficar" = como a conta fica depois. Os subtotais e totais são fórmulas.
A4: Conta | B4: Descrição | C4: Fornecedor (razão) | D4: Como está | E4: Ajuste | F4: Como deve ficar | G4: Lançamento nº | H4: Observação
A5: 6.2.1.01.001 | B5: Custos com Serviços de Terceiros - Internos | C5: TOTAL DA CONTA | D5: =SUM(D6:D40) -> 273982.74 | E5: =SUM(E6:E40) -> 93476.06 | F5: =SUM(F6:F40) -> 367458.8
C6: LACERDA GUILHERME CONSULTORIA EM TECNOLOGIA DA INFORMACAO LTDA | D6: 0 | E6: 40280 | F6: =D6+E6 -> 40280 | G6: 100
C7: L. A. B. CAMPOS LTDA | D7: 0 | E7: 30000 | F7: =D7+E7 -> 30000 | G7: 101
C8: DKSWEB DESENVOLVIMENTO DE SOFTWARE LTDA | D8: 0 | E8: 26000 | F8: =D8+E8 -> 26000 | G8: 102
C9: LUCAS ROBERTO FRANZON PASSELI 43946514847 | D9: 0 | E9: 7882.06 | F9: =D9+E9 -> 7882.06 | G9: 116
C10: Kauan Portela | D10: 6906 | E10: -6906 | F10: =D10+E10 -> 0 | G10: 84
C11: Diego Alves | D11: 3780 | E11: -3780 | F11: =D11+E11 -> 0 | G11: 88
C12: IVAN P. DOS SANTOS LTDA | D12: 23333.33 | E12: 0 | F12: =D12+E12 -> 23333.33
C13: MARCOS THIAGO SILVESTRE DE MORAES CONSULTORIA EM TECNOLOGIA DA INFORMACAO LTDA | D13: 20000 | E13: 0 | F13: =D13+E13 -> 20000
C14: ALEXANDER MAX YOKOGAWA CONSULTORIA EM TECNOLOGIA DA INFORMACAO LTDA | D14: 19000 | E14: 0 | F14: =D14+E14 -> 19000
C15: LEONARDO PIECHA CALDEIRA LTDA | D15: 18700 | E15: 0 | F15: =D15+E15 -> 18700
C16: THIAGO AUGUSTO DE OLIVEIRA TECNOLOGIA DA INFORMACAO LTDA | D16: 17500 | E16: 0 | F16: =D16+E16 -> 17500
C17: HAGROEX LTDA | D17: 17000 | E17: 0 | F17: =D17+E17 -> 17000
C18: HIGOR SANTOS DE JESUS LTDA | D18: 16000 | E18: 0 | F18: =D18+E18 -> 16000
C19: 36.256.578 CHRISTIAN RODRIGO CORRALES | D19: 15736.75 | E19: 0 | F19: =D19+E19 -> 15736.75
C20: s Mensal- Ramon de Sousa Pereira [Oficial] | D20: -15500 | E20: 0 | F20: =D20+E20 -> -15500 | H20: Tem R$ 15.500 de competência 2025: fica em 2026 (exercício encerrado), é nota explicativa.
C21: Mensal - Ramon - s - Ramon de Sousa Pereira | D21: -15500 | E21: 0 | F21: =D21+E21 -> -15500 | H21: Tem R$ 15.500 de competência 2025: fica em 2026 (exercício encerrado), é nota explicativa.
C22: BAS DIGITAL LTDA | D22: 14000 | E22: 0 | F22: =D22+E22 -> 14000
C23: 54.652.017 JOAO VITOR DE MORAIS ROCHA | D23: 13500 | E23: 0 | F23: =D23+E23 -> 13500
C24: GUSTAVO HENRIQUE SILVA CONSULTORIA EM TECNOLOGIA DA INFORMACAO LTDA | D24: 13000 | E24: 0 | F24: =D24+E24 -> 13000
C25: JOSE RICARDO ALVES FIGUEIROA DESENVOLVIMENTO DE SOFTWARE LTDA | D25: 12500 | E25: 0 | F25: =D25+E25 -> 12500
C26: MARIA DE FATIMA BARBOSA CARDOSO DESENVOLVIMENTO DE SOFTWARE LTDA | D26: 11000 | E26: 0 | F26: =D26+E26 -> 11000
C27: NORTHON VINICIOS CARDOSO SOARES LTDA | D27: 10800 | E27: 0 | F27: =D27+E27 -> 10800
C28: Juan Carlo | D28: 10000 | E28: 0 | F28: =D28+E28 -> 10000
C29: KAYRO DANYELL ALVES CONSULTORIA EM TECNOLOGIA DA INFORMACAO LTDA | D29: 10000 | E29: 0 | F29: =D29+E29 -> 10000
C30: EDUARDO HENRIQUE KATSURAYAMA ABREU CONSULTORIA EM TECNOLOGIA DA INFORMACAO LTDA | D30: 9032.26 | E30: 0 | F30: =D30+E30 -> 9032.26
C31: 4TECH DESENVOLVIMENTO DE SOFTWARES LTDA | D31: 8064.22 | E31: 0 | F31: =D31+E31 -> 8064.22
C32: LUIS EMANUEL RIGON ALDERETE DESENVOLVIMENTO DE SOFTWARE LTDA | D32: 7500 | E32: 0 | F32: =D32+E32 -> 7500
C33: DOUGLAS LIMA MACHADO 02831827094 | D33: 7307 | E33: 0 | F33: =D33+E33 -> 7307 | H33: Tem R$ 7.307 de competência 2025: fica em 2026 (exercício encerrado), é nota explicativa.
C34: DANIEL GERONIMO DO AMARAL 02303012236 | D34: 7200.2 | E34: 0 | F34: =D34+E34 -> 7200.2
C35: 50.836.277 DIEGO ALVES FERREIRA | D35: 4413.95 | E35: 0 | F35: =D35+E35 -> 4413.95
C36: 62.516.834 DAVI GRACIANO NASCIMENTO COSTA | D36: 4000 | E36: 0 | F36: =D36+E36 -> 4000
C37: JMR SOLUCOES DIGITAIS LTDA | D37: 3000 | E37: 0 | F37: =D37+E37 -> 3000
C38: SWILE DO BRASIL S.A. | D38: 2130 | E38: 0 | F38: =D38+E38 -> 2130
C39: Ramon de Sousa Pereira | D39: -1550 | E39: 0 | F39: =D39+E39 -> -1550 | H39: Tem R$ 1.550 de competência 2025: fica em 2026 (exercício encerrado), é nota explicativa.
C40: 55.743.508 JULIANA HELENA VALLE FRASAO | D40: 1129.03 | E40: 0 | F40: =D40+E40 -> 1129.03
A41: 6.2.1.01.003 | B41: Custos com Transações | C41: TOTAL DA CONTA | D41: =SUM(D42:D42) -> 24160.94 | E41: =SUM(E42:E42) -> 59487.01 | F41: =SUM(F42:F42) -> 83647.95
C42: PAGAR.ME INSTITUICAO DE PAGAMENTO S.A | D42: 24160.94 | E42: 59487.01 | F42: =D42+E42 -> 83647.95 | G42: 117
A43: 6.2.1.03.001 | B43: Custo de Hospedagem e Infraestrutura (Cloud) | C43: TOTAL DA CONTA | D43: =SUM(D44:D49) -> 239942.19 | E43: =SUM(E44:E49) -> 9412.35 | F43: =SUM(F44:F49) -> 249354.54
C44: 944279429428 - 005/026 - AMAZON AWS SERVICOS BRASIL LTDA | D44: 0 | E44: 115492.22 | F44: =D44+E44 -> 115492.22 | G44: 108
C45: AMAZON AWS SERVICOS BRASIL LTDA | D45: 106079.87 | E45: -106079.87 | F45: =D45+E45 -> 0 | G45: 104
C46: GOOGLE CLOUD BRASIL COMPUTACAO E SERVICOS DE DADOS LTDA. | D46: 124376.97 | E46: 0 | F46: =D46+E46 -> 124376.97
C47: PADDLE | D47: 4707.83 | E47: 0 | F47: =D47+E47 -> 4707.83
C48: WEBSHARE RNW PROXY 42 | D48: 2777.52 | E48: 0 | F48: =D48+E48 -> 2777.52
C49: CASTELBRAS DESIGN, COMUNICACAO E TECNOLOGIA DA INFORMACAO LTDA | D49: 2000 | E49: 0 | F49: =D49+E49 -> 2000
A50: 6.2.1.03.002 | B50: Custo de Licença de Sofware e Sistemas | C50: TOTAL DA CONTA | D50: =SUM(D51:D71) -> 187488.58 | E50: =SUM(E51:E71) -> -4782.25 | F50: =SUM(F51:F71) -> 182706.33
C51: TWILIO SEGMENT | D51: 24508.03 | E51: -4782.25 | F51: =D51+E51 -> 19725.78 | G51: 105
C52: ZEE FILMS PRODUCOES LTDA | D52: 74800 | E52: 0 | F52: =D52+E52 -> 74800
C53: CARBIGDATA TECNOLOGIA E INTELIGENCIA S/A | D53: 46992 | E53: 0 | F53: =D53+E53 -> 46992
C54: POTELO SISTEMAS DE INFORMACAO LTDA | D54: 10000 | E54: 0 | F54: =D54+E54 -> 10000
C55: ATLASSIAN | D55: 8599.23 | E55: 0 | F55: =D55+E55 -> 8599.23
C56: PAYPAL *PROXMOXSERV | D56: 4612.93 | E56: 0 | F56: =D56+E56 -> 4612.93
C57: FIGMA | D57: 3803.71 | E57: 0 | F57: =D57+E57 -> 3803.71
C58: METABASE INC | D58: 3261.1 | E58: 0 | F58: =D58+E58 -> 3261.1
C59: GITHUB, INC. | D59: 2965.16 | E59: 0 | F59: =D59+E59 -> 2965.16
C60: BRIGHT DATA | D60: 2740.98 | E60: 0 | F60: =D60+E60 -> 2740.98
C61: SELKI TECNOLOGIA LTDA | D61: 1474 | E61: 0 | F61: =D61+E61 -> 1474
C62: NRI*NEW RELIC | D62: 1136.78 | E62: 0 | F62: =D62+E62 -> 1136.78
C63: SENTRY | D63: 789.17 | E63: 0 | F63: =D63+E63 -> 789.17
... C71: NVOIP PLATAF | D71: 87 | E71: 0 | F71: =D71+E71 -> 87
A72: 6.2.1.03.003 | B72: Custo de APIs de Terceiros | C72: TOTAL DA CONTA | D72: =SUM(D73:D85) -> 53533.05 | E72: =SUM(E73:E85) -> 375211.11 | F72: =SUM(F73:F85) -> 428744.16
C73: DIGESTO PESQUISA E BANCO DE DADOS LTDA | D73: 2301.15 | E73: 176091.75 | F73: =D73+E73 -> 178392.9 | G73: 107
C74: VIR SERVICOS DE INFORMACOES LTDA | D74: 0 | E74: 102290 | F74: =D74+E74 -> 102290 | G74: 109
C75: JUDIT TECNOLOGIA DA INFORMACAO LTDA | D75: -0.25 | E75: 38715.35 | F75: =D75+E75 -> 38715.1 | G75: 112
C76: NOVA DD POSITIVO REPRESENTACOES LTDA. | D76: 635.46 | E76: 38314.6 | F76: =D76+E76 -> 38950.06 | G76: 113
C77: BIG DATA SOLUCOES EM TECNOLOGIA DE INFORMATICA S.A. | D77: -0.36 | E77: 19799.41 | F77: =D77+E77 -> 19799.05 | G77: 114
C78: PAYPAL *PAYPROGLOBA | D78: 26083.73 | E78: 0 | F78: =D78+E78 -> 26083.73
C79: DATACUBE SERVICO DE INFORMACAO VIA WEB LTDA | D79: 12564.73 | E79: 0 | F79: =D79+E79 -> 12564.73
C80: DOCSALES | D80: 6241.71 | E80: 0 | F80: =D80+E80 -> 6241.71
C81: CODERABBIT | D81: 2908.23 | E81: 0 | F81: =D81+E81 -> 2908.23
C82: DE LUCA & OLIVEIRA ADVOGADOS ASSOCIADOS. | D82: 1400 | E82: 0 | F82: =D82+E82 -> 1400
C83: PAYPRO-CHARGE | D83: 1119.95 | E83: 0 | F83: =D83+E83 -> 1119.95
C84: DEBITO DIRETO SERVICOS DE PAGAMENTOS S.A. | D84: 284.75 | E84: 0 | F84: =D84+E84 -> 284.75
C85: Juros Pagos | D85: -6.05 | E85: 0 | F85: =D85+E85 -> -6.05
A86: 4.1.1.01.003 | B86: Bolsa Estágio | C86: TOTAL DA CONTA | D86: =SUM(D87:D87) -> 1500 | E86: =SUM(E87:E87) -> 0 | F86: =SUM(F87:F87) -> 1500
C87: Fopag: DIAS BOLSA AUXILIO 05/2026: - Rúbrica 8797 | D87: 1500 | E87: 0 | F87: =D87+E87 -> 1500
A88: 4.1.1.01.005 | B88: Férias | C88: TOTAL DA CONTA | D88: =SUM(D89:D89) -> 125 | E88: =SUM(E89:E89) -> 0 | F88: =SUM(F89:F89) -> 125
C89: Fopag: Valor da Provisão 05/2026: - Rúbrica 1 | D89: 125 | E89: 0 | F89: =D89+E89 -> 125
A90: 4.1.2.01.001 | B90: Telefonia e Internet | C90: TOTAL DA CONTA | D90: =SUM(D91:D92) -> 1158.74 | E90: =SUM(E91:E92) -> 0 | F90: =SUM(F91:F92) -> 1158.74
C91: RVT SERVICOS DE TELECOMUNICACOES LTDA | D91: 969.74 | E91: 0 | F91: =D91+E91 -> 969.74
C92: BRASIL TECPAR SERVICOS DE TELECOMUNICACOES S.A | D92: 189 | E92: 0 | F92: =D92+E92 -> 189
A93: 4.1.2.01.002 | B93: Serviços e Equipamentos de TI | C93: TOTAL DA CONTA | D93: =SUM(D94:D99) -> 30963.37 | E93: =SUM(E94:E99) -> 0 | F93: =SUM(F94:F99) -> 30963.37
C94: CHYPPS COMERCIO E IMPORTACAO DE PRODUTOS DE TECNOLOGIA LTDA | D94: 45099.98 | E94: 0 | F94: =D94+E94 -> 45099.98
C95: RECEBIMENTO ALIEXPRESS NF 8208452988187313 | D95: -23884.13 | E95: 0 | F95: =D95+E95 -> -23884.13
C96: STARK INDUSTRIA E COMERCIO LTDA | D96: 6833.44 | E96: 0 | F96: =D96+E96 -> 6833.44
C97: DELL COMPUTADORES DO BRASIL LTDA | D97: 1604.39 | E97: 0 | F97: =D97+E97 -> 1604.39
C98: KABUM S.A. | D98: 1309.7 | E98: 0 | F98: =D98+E98 -> 1309.7
C99: Juros Pagos | D99: -0.01 | E99: 0 | F99: =D99+E99 -> -0.01
A100: 4.1.2.01.003 | B100: Licença de Sofware e Sistemas (SaaS) | C100: TOTAL DA CONTA | D100: =SUM(D101:D136) -> 322496.05 | E100: =SUM(E101:E136) -> -171559.53 | F100: =SUM(F101:F136) -> 150936.52
C101: TREBLE.AI | D101: 114030.6 | E101: -170081.99 | F101: =D101+E101 -> -56051.39 | G101: 80, 103
C102: SLACK | D102: 4477.1 | E102: -2281.16 | F102: =D102+E102 -> 2195.94 | G102: 106
C103: TREBLE.AI DO BRASIL SERVICOS DIGITAIS LTDA. | D103: 55248.33 | E103: 803.62 | F103: =D103+E103 -> 56051.95 | G103: 81, 110
C104: MICROSOFT DO BRASIL IMPORTACAO E COMERCIO DE SOFTWARE E VIDEO GAMES LTDA | D104: 79231.56 | E104: 0 | F104: =D104+E104 -> 79231.56
C105: WINGIFY | D105: 13226.53 | E105: 0 | F105: =D105+E105 -> 13226.53
C106: IPROYAL | D106: 11114.26 | E106: 0 | F106: =D106+E106 -> 11114.26
C107: LINKEDIN | D107: 11053.86 | E107: 0 | F107: =D107+E107 -> 11053.86
C108: AUGMENT CODE | D108: 10762.65 | E108: 0 | F108: =D108+E108 -> 10762.65
...

Sheet Jun
A1: Junho/2026 — DRE contábil aberto por conta e fornecedor
A2: Cada conta do DRE com os fornecedores do razão (nome como está no livro da Syhus). "Como está" = razão de hoje. "Ajuste" = os lançamentos da aba O QUE FAZER (nº na coluna G). "Como deve ficar" = como a conta fica depois. Os subtotais e totais são fórmulas.
A4: Conta | B4: Descrição | C4: Fornecedor (razão) | D4: Como está | E4: Ajuste | F4: Como deve ficar | G4: Lançamento nº | H4: Observação
A5: 6.2.1.01.001 | B5: Custos com Serviços de Terceiros - Internos | C5: TOTAL DA CONTA | D5: =SUM(D6:D41) -> 390953.79 | E5: =SUM(E6:E41) -> 134097.74 | F5: =SUM(F6:F41) -> 525051.53
C6: DKSWEB DESENVOLVIMENTO DE SOFTWARE LTDA | D6: 0 | E6: 52000 | F6: =D6+E6 -> 52000 | G6: 120, 134
C7: L. A. B. CAMPOS LTDA | D7: 0 | E7: 30000 | F7: =D7+E7 -> 30000 | G7: 119
C8: BEYAUT LTDA | D8: 0 | E8: 22000 | F8: =D8+E8 -> 22000 | G8: 121
C9: LACERDA GUILHERME CONSULTORIA EM TECNOLOGIA DA INFORMACAO LTDA | D9: 0 | E9: 21280 | F9: =D9+E9 -> 21280 | G9: 122
C10: ESPEJOLAB TECNOLOGIA LTDA | D10: 0 | E10: 10000 | F10: =D10+E10 -> 10000 | G10: 137
C11: EDUARDO HENRIQUE KATSURAYAMA ABREU CONSULTORIA EM TECNOLOGIA DA INFORMACAO LTDA | D11: 29032.26 | E11: -9032.26 | F11: =D11+E11 -> 20000 | G11: 118
C12: SAM TECHNOLOGIES LTDA | D12: 0 | E12: 7850 | F12: =D12+E12 -> 7850 | G12: 123
C13: JOAO VICTOR XAVIER DA SILVA 08983862688 | D13: 30933.33 | E13: 0 | F13: =D13+E13 -> 30933.33
C14: THIAGO AUGUSTO DE OLIVEIRA TECNOLOGIA DA INFORMACAO LTDA | D14: 22000 | E14: 0 | F14: =D14+E14 -> 22000
C15: MARCOS THIAGO SILVESTRE DE MORAES CONSULTORIA EM TECNOLOGIA DA INFORMACAO LTDA | D15: 20000 | E15: 0 | F15: =D15+E15 -> 20000
C16: ALEXANDER MAX YOKOGAWA CONSULTORIA EM TECNOLOGIA DA INFORMACAO LTDA | D16: 19000 | E16: 0 | F16: =D16+E16 -> 19000
C17: LEONARDO PIECHA CALDEIRA LTDA | D17: 18700 | E17: 0 | F17: =D17+E17 -> 18700
C18: HIGOR SANTOS DE JESUS LTDA | D18: 16000 | E18: 0 | F18: =D18+E18 -> 16000
C19: 36.256.578 CHRISTIAN RODRIGO CORRALES | D19: 15736.75 | E19: 0 | F19: =D19+E19 -> 15736.75
C20: R R TECNOLOGIA DA INFORMACAO LTDA | D20: 15000 | E20: 0 | F20: =D20+E20 -> 15000
C21: HAGROEX LTDA | D21: 15000 | E21: 0 | F21: =D21+E21 -> 15000
C22: CURRY LABS TECNOLOGIA LTDA | D22: 15000 | E22: 0 | F22: =D22+E22 -> 15000
C23: BAS DIGITAL LTDA | D23: 14000 | E23: 0 | F23: =D23+E23 -> 14000
C24: 54.652.017 JOAO VITOR DE MORAIS ROCHA | D24: 13500 | E24: 0 | F24: =D24+E24 -> 13500
... C41: 02070665 - 005/025 - SWILE DO BRASIL S.A. | D41: 2157.69 | E41: 0 | F41: =D41+E41 -> 2157.69
A42: 6.2.1.01.003 | B42: Custos com Transações | C42: TOTAL DA CONTA | D42: =SUM(D43:D43) -> 24631.6 | E42: =SUM(E43:E43) -> 57078.91 | F42: =SUM(F43:F43) -> 81710.51
C43: PAGAR.ME INSTITUICAO DE PAGAMENTO S.A | D43: 24631.6 | E43: 57078.91 | F43: =D43+E43 -> 81710.51 | G43: 138
A44: 6.2.1.03.001 | B44: Custo de Hospedagem e Infraestrutura (Cloud) | C44: TOTAL DA CONTA | D44: =SUM(D45:D52) -> 281755.1 | E44: =SUM(E45:E52) -> 38558.37 | F44: =SUM(F45:F52) -> 320313.47
C45: AMAZON AWS SERVICOS BRASIL LTDA | D45: 0 | E45: 126682 | F45: =D45+E45 -> 126682 | G45: 129
C46: 944279429428 - 005/026 - AMAZON AWS SERVICOS BRASIL LTDA | D46: 115492.22 | E46: -115492.22 | F46: =D46+E46 -> 0 | G46: 125
C47: GOOGLE CLOUD BRASIL COMPUTACAO E SERVICOS DE DADOS LTDA. | D47: 159918.41 | E47: 27368.59 | F47: =D47+E47 -> 187287 | G47: 133
C48: PADDLE | D48: 2669.8 | E48: 0 | F48: =D48+E48 -> 2669.8
C49: CASTELBRAS DESIGN, COMUNICACAO E TECNOLOGIA DA INFORMACAO LTDA | D49: 2016 | E49: 0 | F49: =D49+E49 -> 2016
C50: WEBSHARE RNW PROXY 42 | D50: 1399.84 | E50: 0 | F50: =D50+E50 -> 1399.84
C51: NT - 001/001 - GODADDY BRASIL | D51: 222.93 | E51: 0 | F51: =D51+E51 -> 222.93
C52: 1043181 - 009/026 - TURBOCLOUD | D52: 35.9 | E52: 0 | F52: =D52+E52 -> 35.9
A53: 6.2.1.03.002 | B53: Custo de Licença de Sofware e Sistemas | C53: TOTAL DA CONTA | D53: =SUM(D54:D77) -> 119226.56 | E53: =SUM(E54:E77) -> 0 | F53: =SUM(F54:F77) -> 119226.56
C54: CARBIGDATA TECNOLOGIA E INTELIGENCIA S/A | D54: 37680 | E54: 0 | F54: =D54+E54 -> 37680
C55: APPCUES | D55: 19025.68 | E55: 0 | F55: =D55+E55 -> 19025.68
C56: POTELO SISTEMAS DE INFORMACAO LTDA | D56: 10000 | E56: 0 | F56: =D56+E56 -> 10000
C57: ANTHROPIC CLAUDE TEAM | D57: 8927.27 | E57: 0 | F57: =D57+E57 -> 8927.27
C58: BRIGHT DATA | D58: 8272.88 | E58: 0 | F58: =D58+E58 -> 8272.88
C59: ATLASSIAN JIRA | D59: 6460.28 | E59: 0 | F59: =D59+E59 -> 6460.28
C60: TWILIO SEGMENT | D60: 5433.95 | E60: 0 | F60: =D60+E60 -> 5433.95
C61: OCRDATASOLUTIONS | D61: 4943.25 | E61: 0 | F61: =D61+E61 -> 4943.25
C62: PAYPAL *ALTWEBLLCFZ | D62: 3353.27 | E62: 0 | F62: =D62+E62 -> 3353.27
C63: BAGOLIN E BASTIANELLO CONSULTORIA LTDA | D63: 3000 | E63: 0 | F63: =D63+E63 -> 3000
C64: METABASE INC | D64: 2595.47 | E64: 0 | F64: =D64+E64 -> 2595.47
C65: MAGAZINE LUIZA S/A | D65: 2267.95 | E65: 0 | F65: =D65+E65 -> 2267.95
... C77: NVOIP PLATAF | D77: 29 | E77: 0 | F77: =D77+E77 -> 29
A78: 6.2.1.03.003 | B78: Custo de APIs de Terceiros | C78: TOTAL DA CONTA | D78: =SUM(D79:D90) -> 422766.52 | E78: =SUM(E79:E90) -> 3905.02 | F78: =SUM(F79:F90) -> 426671.54
C79: PAYPAL *PAYPROGLOBA | D79: 1106.47 | E79: 11088.53 | F79: =D79+E79 -> 12195 | G79: 136
C80: DIGESTO PESQUISA E BANCO DE DADOS LTDA | D80: 176091.75 | E80: -10442.75 | F80: =D80+E80 -> 165649 | G80: 124, 128
C81: BIG DATA SOLUCOES EM TECNOLOGIA DE INFORMATICA S.A. | D81: 19799.41 | E81: 2548.59 | F81: =D81+E81 -> 22348 | G81: 127, 135
C82: JUDIT TECNOLOGIA DA INFORMACAO LTDA | D82: 38715.35 | E82: 710.65 | F82: =D82+E82 -> 39426 | G82: 126, 132
C83: VIR SERVICOS DE INFORMACOES LTDA | D83: 81355.6 | E83: 0 | F83: =D83+E83 -> 81355.6
C84: NOVA DD POSITIVO REPRESENTACOES LTDA. | D84: 42744.82 | E84: 0 | F84: =D84+E84 -> 42744.82
C85: PAYPRO-CHARGE | D85: 31705.16 | E85: 0 | F85: =D85+E85 -> 31705.16
C86: DATACUBE SERVICO DE INFORMACAO VIA WEB LTDA | D86: 11753.03 | E86: 0 | F86: =D86+E86 -> 11753.03
C87: 58320 - 001/001 - DOCSALES | D87: 6298.33 | E87: 0 | F87: =D87+E87 -> 6298.33
C88: 57736 - 001/001 - DOCSALES | D88: 6232.22 | E88: 0 | F88: =D88+E88 -> 6232.22
C89: DEBITO DIRETO SERVICOS DE PAGAMENTOS S.A. | D89: 4009.5 | E89: 0 | F89: =D89+E89 -> 4009.5
C90: CODERABBIT | D90: 2954.88 | E90: 0 | F90: =D90+E90 -> 2954.88
A91: 4.1.1.01.003 | B91: Bolsa Estágio | C91: TOTAL DA CONTA | D91: =SUM(D92:D92) -> 1500 | E91: =SUM(E92:E92) -> 0 | F91: =SUM(F92:F92) -> 1500
C92: Fopag: DIAS BOLSA AUXILIO 06/2026: - Rúbrica 8797 | D92: 1500 | E92: 0 | F92: =D92+E92 -> 1500
A93: 4.1.1.01.005 | B93: Férias | C93: TOTAL DA CONTA | D93: =SUM(D94:D94) -> 125 | E93: =SUM(E94:E94) -> 0 | F93: =SUM(F94:F94) -> 125
C94: Fopag: Valor da Provisão 06/2026: - Rúbrica 1 | D94: 125 | E94: 0 | F94: =D94+E94 -> 125
A95: 4.1.2.01.001 | B95: Telefonia e Internet | C95: TOTAL DA CONTA | D95: =SUM(D96:D98) -> 1800.91 | E95: =SUM(E96:E98) -> 0 | F95: =SUM(F96:F98) -> 1800.91
C96: Sim Digital - RVT | D96: 1140.87 | E96: 0 | F96: =D96+E96 -> 1140.87
C97: STARLINK BRAZIL SERVICOS DE INTERNET LTDA. | D97: 471.04 | E97: 0 | F97: =D97+E97 -> 471.04
C98: Avato | D98: 189 | E98: 0 | F98: =D98+E98 -> 189
A99: 4.1.2.01.002 | B99: Serviços e Equipamentos de TI | C99: TOTAL DA CONTA | D99: =SUM(D100:D102) -> 16377.65 | E99: =SUM(E100:E102) -> 0 | F99: =SUM(F100:F102) -> 16377.65
C100: KABUM S.A. | D100: 14744.28 | E100: 0 | F100: =D100+E100 -> 14744.28
C101: DELL COMPUTADORES DO BRASIL LTDA | D101: 1604.39 | E101: 0 | F101: =D101+E101 -> 1604.39
C102: PILOTO COMERCIO LTDA | D102: 28.98 | E102: 0 | F102: =D102+E102 -> 28.98
A103: 4.1.2.01.003 | B103: Licença de Sofware e Sistemas (SaaS) | C103: TOTAL DA CONTA | D103: =SUM(D104:D131) -> 164951.29 | E103: =SUM(E104:E131) -> 57416.63 | F103: =SUM(F104:F131) -> 222367.92
C104: TREBLE.AI | D104: 0 | E104: 57416.63 | F104: =D104+E104 -> 57416.63 | G104: 130
C105: MICROSOFT DO BRASIL IMPORTACAO E COMERCIO DE SOFTWARE E VIDEO GAMES LTDA | D105: 90606.76 | E105: 0 | F105: =D105+E105 -> 90606.76
C106: AUGMENT CODE | D106: 17669.07 | E106: 0 | F106: =D106+E106 -> 17669.07
C107: TREBLE.AI DO BRASIL SERVICOS DIGITAIS LTDA. | D107: 14672.44 | E107: 0 | F107: =D107+E107 -> 14672.44
C108: LINKEDIN | D108: 5699.28 | E108: 0 | F108: =D108+E108 -> 5699.28
C109: IPROYAL | D109: 5668.24 | E109: 0 | F109: =D109+E109 -> 5668.24
C110: JOINVIXBRASIL SERVICOS DE INTERNET LTDA | D110: 5000 | E110: 0 | F110: =D110+E110 -> 5000
C111: CLOUD HUMANS TECNOLOGIA LTDA. | D111: 4855 | E111: 0 | F111: =D111+E111 -> 4855
C112: ZOHO CORPORATION BRASIL TECNOLOGIA LTDA. | D112: 4347.74 | E112: 0 | F112: =D112+E112 -> 4347.74
C113: OMIEXPERIENCE LTDA. | D113: 3221.07 | E113: 0 | F113: =D113+E113 -> 3221.07
C114: SLACK | D114: 2477.88 | E114: 0 | F114: =D114+E114 -> 2477.88
C115: OPENAI CHATGPT | D115: 2142.3 | E115: 0 | F115: =D115+E115 -> 2142.3
C116: DISCOURSE.ORG | D116: 1568.37 | E116: 0 | F116: =D116+E116 -> 1568.37
... C131: CANVAS BRASIL LTDA | D131: 37.49 | E131: 0 | F131: =D131+E131 -> 37.49
A132: 4.1.2.02.001 | B132: Aluguel | C132: TOTAL DA CONTA | D132: =SUM(D133:D134) -> 18767.06 | E132: =SUM(E133:E134) -> 0 | F132: =SUM(F133:F134) -> 18767.06
C133: WEWORK SERVICOS DE ESCRITORIO LTDA. | D133: 13251.5 | E133: 0 | F133: =D133+E133 -> 13251.5
C134: CAMARA DE DIRIGENTES LOJISTAS DE SANTA MARIA | D134: 5515.56 | E134: 0 | F134: =D134+E134 -> 5515.56
A135: 4.1.2.02.002 | B135: Energia Elétrica | C135: TOTAL DA CONTA | D135: =SUM(D136:D136) -> 703.71 | E135: =SUM(E136:E136) -> 0 | F135: =SUM(F136:F136) -> 703.71
C136: RGE ENERGIA ELETRICA | D136: 703.71 | E136: 0 | F136: =D136+E136 -> 703.71
A137: 4.1.2.02.005 | B137: Manutenções Prediais | C137: TOTAL DA CONTA | D137: =SUM(D138:D141) -> 1141 | E137: =SUM(E138:E141) -> 0 | F137: =SUM(F138:F141) -> 1141
C138: K. H. S. COMERCIO DE TECNOLOGIA LTDA | D138: 569 | E138: 0 | F138: =D138+E138 -> 569
C139: 51.199.027 BIBIANA PAIM DA SILVA | D139: 480 | E139: 0 | F139: =D139+E139 -> 480
C140: CASA ONLINE COMERCIO E VAREJO LTDA | D140: 46 | E140: 0 | F140: =D140+E140 -> 46
C141: 000.037.922 - 001/001 - MERCADOLIVRE | D141: 46 | E141: 0 | F141: =D141+E141 -> 46
A142: 4.1.2.04.001 | B142: Passagens Aereas e Rodoviárias | C142: TOTAL DA CONTA | D142: =SUM(D143:D144) -> 7153.7 | E142: =SUM(E143:E144) -> 0 | F142: =SUM(F143:F144) -> 7153.7
...

Sheet Notas e pendências
A1: Nota explicativa e pendências da Jusfy — a Syhus não precisa fazer nada aqui
A2: A: a única nota explicativa — competência 2025 que caiu em 2026 (o exercício de 2025 já fechou, então fica em 2026), por fornecedor, pra auditoria e CFO. B: pendências que dependem de resposta da Jusfy (cada uma com o valor e o que falta). C: parece erro, mas o P&L diz que o valor é devido — não mexer sem a Jusfy confirmar.
A4: A. NOTA EXPLICATIVA — Competência 2025 lançada em 2026 (fica em 2026: exercício de 2025 encerrado)
A5: Fornecedor (razão) | B5: Mês | C5: Valor | D5: Conta | E5: Linha do P&L | F5: Explicação
A6: SWILE DO BRASIL S.A. | B6: Jan | C6: 144755 | D6: 4.1.6.01.007 Serviços de Terceiros - Internos | E6: Swile (bônus e benefício) | F6: Bônus de líderes de dez/2025 pago via Swile em jan (NF 1762064). A Controladoria confirmou na rodada anterior que o excesso de jan é bônus, e no gerencial ele está em dez/2025.
A7: DIGESTO PESQUISA E BANCO DE DADOS LTDA | B7: Jan | C7: 138361.9 | D7: 6.2.1.03.003 Custo de APIs de Terceiros | E7: Digesto Pesquisa e Banco de Dados Ltda (Jusbrasil) | F7: Este fornecedor fatura depois do mês de uso (nos outros meses a NF de um mês entra no seguinte). A NF 37368 (R$ 138.362) lançada(s) em jan não correspondem a nenhum mês de 2026: são de dez/2025. Sair da despesa de 2026.
A8: AMAZON AWS SERVICOS BRASIL LTDA | B8: Jan | C8: 107263.42 | D8: 6.2.1.03.001 Custo de Hospedagem e Infraestrutura (Cloud) | E8: Amazon Cloud | F8: Este fornecedor fatura depois do mês de uso (nos outros meses a NF de um mês entra no seguinte). A NF s/nº (R$ 107.263) lançada(s) em jan não correspondem a nenhum mês de 2026: são de dez/2025. Sair da despesa de 2026.
A9: VIR SERVICOS DE INFORMACOES LTDA | B9: Jan | C9: 84888.4 | D9: 6.2.1.03.003 Custo de APIs de Terceiros | E9: Vir Servicos de Informacoes Ltda (Correct Data) | F9: Este fornecedor fatura depois do mês de uso (nos outros meses a NF de um mês entra no seguinte). A NF 6289 (R$ 84.888) lançada(s) em jan não correspondem a nenhum mês de 2026: são de dez/2025. Sair da despesa de 2026.
A10: NOVA DD POSITIVO REPRESENTACOES LTDA. | B10: Jan | C10: 39535.74 | D10: 6.2.1.03.003 Custo de APIs de Terceiros | E10: Nova Dd Positivo Representacoes Ltda. | F10: Este fornecedor fatura depois do mês de uso (nos outros meses a NF de um mês entra no seguinte). A NF 397 (R$ 39.536) lançada(s) em jan não correspondem a nenhum mês de 2026: são de dez/2025. Sair da despesa de 2026.
A11: JULIANO LIMA DA SILVA LTDA | B11: Jan | C11: 30000 | D11: 4.1.6.01.007 Serviços de Terceiros - Internos | E11: Juliano Lima | F11: NF 30 de R$ 30.000 lançada em Jan tem o valor de dez/2025 no ERP (ERP dez/2025 salário); em 2026 o valor é outro. É competência 2025: sai da despesa de 2026 (contra a provisão de 2025).
A12: JUDIT TECNOLOGIA DA INFORMACAO LTDA | B12: Jan | C12: 28491 | D12: 6.2.1.03.003 Custo de APIs de Terceiros | E12: Judit Tecnologia da Informacao Ltda | F12: Este fornecedor fatura depois do mês de uso (nos outros meses a NF de um mês entra no seguinte). A NF 504 (R$ 28.491) lançada(s) em jan não correspondem a nenhum mês de 2026: são de dez/2025. Sair da despesa de 2026.
A13: KARINE C GOMBERG SERVICOS ADMINISTRATIVOS | B13: Jan | C13: 22500 | D13: 4.1.6.01.007 Serviços de Terceiros - Internos | E13: Karine Gomberg | F13: NF 53 de R$ 22.500 entrou em jan, mas o gerencial de jan é outra nota. É competência dez/2025: sai da despesa de 2026 (contra a provisão de 2025).
A14: BRUNO JOSE SOBREIRA CAVALIERI LTDA | B14: Jan | C14: 22000 | D14: 4.1.6.01.007 Serviços de Terceiros - Internos | E14: Bruno José Sobreira Cavalieri | F14: NF 1 de R$ 22.000 lançada em Jan tem o valor de dez/2025 no ERP (ERP dez/2025 salário); em 2026 o valor é outro. É competência 2025: sai da despesa de 2026 (contra a provisão de 2025).
A15: ROCHA CASTANHA SOLUCOES LTDA | B15: Jan | C15: 22000 | D15: 4.1.6.01.007 Serviços de Terceiros - Internos | E15: Clarissa Castanha | F15: NF 202600000000028 de R$ 22.000 lançada em Jan tem o valor de dez/2025 no ERP (ERP dez/2025 salário); em 2026 o valor é outro. É competência 2025: sai da despesa de 2026 (contra a provisão de 2025).
A16: APPCUES | B16: Jan | C16: 20036.07 | D16: 6.2.1.03.002 Custo de Licença de Sofware e Sistemas | E16: Appcues | F16: Este fornecedor fatura depois do mês de uso (nos outros meses a NF de um mês entra no seguinte). A NF s/nº (R$ 20.036) lançada(s) em jan não correspondem a nenhum mês de 2026: são de dez/2025. Sair da despesa de 2026.
A17: BIG DATA SOLUCOES EM TECNOLOGIA DE INFORMATICA S.A. | B17: Jan | C17: 19922.37 | D17: 6.2.1.03.003 Custo de APIs de Terceiros | E17: Big Data Solucoes em Tecnologia de Informatica S.A. | F17: Este fornecedor fatura depois do mês de uso (nos outros meses a NF de um mês entra no seguinte). A NF 152 (R$ 19.922) lançada(s) em jan não correspondem a nenhum mês de 2026: são de dez/2025. Sair da despesa de 2026.
... A244: Mensal - Ramon - s - Ramon de Sousa Pereira | B244: Mai | C244: -15500 | D244: 6.2.1.01.001 Custos com Serviços de Terceiros - Internos | E244: Ramon de Sousa Pereira | F244: Estorno/cancelamento de NF de 01/12/2025 (2025) lançado em Mai/2026, reduzindo a despesa de 2026. É de 2025: lançar contra o resultado de 2025, não contra a despesa de 2026. O gerencial de Mai não tem esse valor.
A245: TOTAL (239 linhas) | C245: 1216735.6
A247: B1a. Google Ads — valor certo por competência (razão = base da Mari); ajustar o P&L
A248: Mês | C248: NFs Google no razão | D248: Base da Mari (ERP, competência) | E248: P&L hoje | F248: Ajuste no P&L (valor certo − P&L)
A249: Janeiro | C249: 507493.95 | D249: 507493.95 | E249: 501335.46 | F249: 6158.49
A250: Fevereiro | C250: 587911.77 | D250: 587911.77 | E250: 587911 | F250: 0.77
A251: Março | C251: 832108.38 | D251: 832108.38 | E251: 812105.21 | F251: 20003.17
A252: Abril | C252: 714588.92 | D252: 714588.92 | E252: 701900.06 | F252: 12688.86
A253: Maio | C253: 1057894.2 | D253: 1057894.2 | E253: 1057894 | F253: 0.17
A254: Junho | C254: 1182057.7 | D254: 1182057.7 | E254: 1177023.6 | F254: 5034.06
A255: TOTAL | C255: 4882054.8 | D255: 4882054.8 | E255: 4838169.3 | F255: 43885.52
A256: Base da Mari: linhas GOOGLE BRASIL / GOOGLE WORKSPACE classificadas em 5.1.1 Aquisição Digital (ADS), somadas por competência (todas as contas da Google: SaaS, Jusmatch, Enterprise, Internacional). Em jan, a NF 35933274 (R$ 9.349,64) está no ERP como "GOOGLE WORKSPACE", classe ADS.
A258: B1b. Imposto retido — o razão lança o valor bruto da NF; o ERP (e o P&L) tem o líquido pago
A259: Fornecedor (razão) | B259: Mês | C259: Diferença no mês | D259: NF (razão) → pago (ERP) | E259: Retido | F259: O que decidir
A260: RECH & LONGO LTDA | B260: Jan | C260: 149 | D260: NF 31 9.916 → 9.767 | E260: 149 (1,50%) | F260: Contábil está certo (despesa = valor bruto da NF). O P&L usa o valor pago ao fornecedor. Decidir: P&L passa a usar o bruto, ou o retido entra na linha de impostos.
A261: CARBIGDATA TECNOLOGIA E INTELIGENCIA S/A | B261: Fev | C261: 730 | D261: NF 2725 11.868 → 11.138 | E261: 730 (6,15%) | F261: Contábil está certo (despesa = valor bruto da NF). O P&L usa o valor pago ao fornecedor. Decidir: P&L passa a usar o bruto, ou o retido entra na linha de impostos.
A262: RECH & LONGO LTDA | B262: Fev | C262: 149 | D262: NF 58 9.916 → 9.767 | E262: 149 (1,50%) | F262: Contábil está certo (despesa = valor bruto da NF). O P&L usa o valor pago ao fornecedor. Decidir: P&L passa a usar o bruto, ou o retido entra na linha de impostos.
A263: CARBIGDATA TECNOLOGIA E INTELIGENCIA S/A | B263: Mar | C263: 1480 | D263: NF 3092 24.060 → 22.580 | E263: 1.480 (6,15%) | F263: Contábil está certo (despesa = valor bruto da NF). O P&L usa o valor pago ao fornecedor. Decidir: P&L passa a usar o bruto, ou o retido entra na linha de impostos.
A264: RECH & LONGO LTDA | B264: Mar | C264: 149.01 | D264: NF 117 9.916 → 9.767 | E264: 149 (1,50%) | F264: Contábil está certo (despesa = valor bruto da NF). O P&L usa o valor pago ao fornecedor. Decidir: P&L passa a usar o bruto, ou o retido entra na linha de impostos.
A265: DE LUCA & OLIVEIRA ADVOGADOS ASSOCIADOS. | B265: Mar | C265: 148 | D265: NF 1750 2.400 → 2.252 | E265: 148 (6,15%) | F265: Contábil está certo (despesa = valor bruto da NF). O P&L usa o valor pago ao fornecedor. Decidir: P&L passa a usar o bruto, ou o retido entra na linha de impostos.
A266: CARBIGDATA TECNOLOGIA E INTELIGENCIA S/A | B266: Abr | C266: 2614 | D266: NF 3165 42.504 → 39.890 | E266: 2.614 (6,15%) | F266: Contábil está certo (despesa = valor bruto da NF). O P&L usa o valor pago ao fornecedor. Decidir: P&L passa a usar o bruto, ou o retido entra na linha de impostos.
A267: LINKEDIN | B267: Abr | C267: 244.23 | D267: NF FATURA 4.991 → 4.747 | E267: 244 (4,89%) | F267: Contábil está certo (despesa = valor bruto da NF). O P&L usa o valor pago ao fornecedor. Decidir: P&L passa a usar o bruto, ou o retido entra na linha de impostos.
A268: DE LUCA & OLIVEIRA ADVOGADOS ASSOCIADOS. | B268: Abr | C268: 221 | D268: NF 1766 3.600 → 3.379 | E268: 221 (6,15%) | F268: Contábil está certo (despesa = valor bruto da NF). O P&L usa o valor pago ao fornecedor. Decidir: P&L passa a usar o bruto, ou o retido entra na linha de impostos.
A269: RECH & LONGO LTDA | B269: Abr | C269: 149 | D269: NF 167 9.916 → 9.767 | E269: 149 (1,50%) | F269: Contábil está certo (despesa = valor bruto da NF). O P&L usa o valor pago ao fornecedor. Decidir: P&L passa a usar o bruto, ou o retido entra na linha de impostos.
A270: CARBIGDATA TECNOLOGIA E INTELIGENCIA S/A | B270: Mai | C270: 2890 | D270: NF 3416 46.992 → 44.102 | E270: 2.890 (6,15%) | F270: Contábil está certo (despesa = valor bruto da NF). O P&L usa o valor pago ao fornecedor. Decidir: P&L passa a usar o bruto, ou o retido entra na linha de impostos.
A271: DE LUCA & OLIVEIRA ADVOGADOS ASSOCIADOS. | B271: Mai | C271: 86 | D271: NF 1782 1.400 → 1.314 | E271: 86 (6,15%) | F271: Contábil está certo (despesa = valor bruto da NF). O P&L usa o valor pago ao fornecedor. Decidir: P&L passa a usar o bruto, ou o retido entra na linha de impostos.
... A274: DE LUCA & OLIVEIRA ADVOGADOS ASSOCIADOS. | B274: Jun | C274: 130 | D274: NF 1796 2.000 → 1.870 | E274: 130 (6,50%) | F274: Contábil está certo (despesa = valor bruto da NF). O P&L usa o valor pago ao fornecedor. Decidir: P&L passa a usar o bruto, ou o retido entra na linha de impostos.
A275: TOTAL (15 linhas) | C275: 12116.6
A277: B1c. Para a Jusfy classificar — a nota está na base da Mari, mas o P&L tem menos para este fornecedor
A278: Fornecedor (razão) | B278: Mês | C278: A mais no razão | D278: Razão × P&L do fornecedor no mês | E278: O que a base da Mari mostra | F278: Classificação da Jusfy
A279: 36.139.757 ALAN OLIVEIRA | B279: Jan | C279: 60.68 | D279: 5.000 × 4.939 | E279: Notas do razão no ERP no mesmo mês (5.000). O P&L deste fornecedor tem menos.
A280: 35.376.951 ALBERTO PEREIRA LOPES DA SILVA JUNIOR | B280: Jun | C280: 1173.61 | D280: 1.174 × 0 | E280: Mesma nota no ERP em outro mês (1.174 → Mai), e o razão desse mês já tem a nota dele: parece a mesma NF lançada duas vezes.
A281: ATLASSIAN | B281: Mai | C281: 4118.81 | D281: 8.599 × 478 | E281: Mesma nota no ERP em outro mês (4.119 → Abr), e o razão desse mês já tem a nota dele: parece a mesma NF lançada duas vezes.
A282: ATLASSIAN | B282: Mai | C282: 3636.51 | D282: 8.599 × 478 | E282: Notas do razão no ERP no mesmo mês (4.480). O P&L deste fornecedor tem menos.
A283: AUGMENT CODE | B283: Fev | C283: 1611.59 | D283: 4.417 × 2.740 | E283: Mesma nota no ERP em outro mês (4.417 → Jan), e o razão desse mês já tem a nota dele: parece a mesma NF lançada duas vezes.
A284: 52.406.739 BEATRIZ FONSECA SALES | B284: Mar | C284: 330.05 | D284: 1.550 × 1.220 | E284: Mesma nota no ERP em outro mês (1.550 → Fev), e o razão desse mês já tem a nota dele: parece a mesma NF lançada duas vezes.
A285: 52.406.739 BEATRIZ FONSECA SALES | B285: Jun | C285: 353.19 | D285: 1.100 × 747 | E285: Mesma nota no ERP em outro mês (1.100 → Mai), e o razão desse mês já tem a nota dele: parece a mesma NF lançada duas vezes.
A286: BENDITA IMAGEM ASSESSORIA DE IMPRENSA LTDA | B286: Jan | C286: 91.01 | D286: 7.500 × 7.409 | E286: Notas do razão no ERP no mesmo mês (7.500). O P&L deste fornecedor tem menos.
A287: BENDITA IMAGEM ASSESSORIA DE IMPRENSA LTDA | B287: Mar | C287: 180.3 | D287: 7.500 × 7.320 | E287: Notas do razão no ERP no mesmo mês (7.500). O P&L deste fornecedor tem menos.
A288: BENDITA IMAGEM ASSESSORIA DE IMPRENSA LTDA | B288: Abr | C288: 133.17 | D288: 7.500 × 7.367 | E288: Notas do razão no ERP no mesmo mês (7.500). O P&L deste fornecedor tem menos.
A289: COMPANY HERO LTDA | B289: Mar | C289: 625.3 | D289: 625 × 701 | E289: Mesma nota no ERP em outro mês (625 → Fev), e o razão desse mês já tem a nota dele: parece a mesma NF lançada duas vezes.
A290: DE LUCA & OLIVEIRA ADVOGADOS ASSOCIADOS. | B290: Fev | C290: 2000 | D290: 2.000 × 0 | E290: Notas do razão no ERP no mesmo mês (2.000). O P&L deste fornecedor tem menos.
... A343: VMO*VIMEO.COM | B343: Jun | C343: 100.56 | D343: 105 × 4 | E343: Mesma nota no ERP em outro mês (105 → Mai), e o razão desse mês já tem a nota dele: parece a mesma NF lançada duas vezes.
A344: TOTAL (65 linhas) | C344: 95830.2
A346: B2. Pendência Jusfy — fornecedor do razão que não está no P&L (conferido na base do ERP)
A347: Fornecedor (razão) | B347: Mês | C347: Valor | D347: Conta | E347: Situação | F347: Evidência / o que falta
A348: Fopag: DIAS BOLSA AUXILIO 02/2026: - Rúbrica 8797 | B348: Fev | C348: 1500 | D348: 4.1.1.01.003 Bolsa Estágio | E348: Folha sem cadastro no painel de pessoas | F348: Linha da folha (Fopag) — bolsa-auxílio/provisão de estagiário. Não está no painel de pessoas, por isso não entra no P&L de RH. Jusfy: incluir a pessoa no Cadastro/painel ou confirmar que fica fora.
A349: Fopag: DIAS BOLSA AUXILIO 03/2026: - Rúbrica 8797 | B349: Mar | C349: 1500 | D349: 4.1.1.01.003 Bolsa Estágio | E349: Folha sem cadastro no painel de pessoas | F349: Linha da folha (Fopag) — bolsa-auxílio/provisão de estagiário. Não está no painel de pessoas, por isso não entra no P&L de RH. Jusfy: incluir a pessoa no Cadastro/painel ou confirmar que fica fora.
A350: Fopag: DIAS BOLSA AUXILIO 04/2026: - Rúbrica 8797 | B350: Abr | C350: 1500 | D350: 4.1.1.01.003 Bolsa Estágio | E350: Folha sem cadastro no painel de pessoas | F350: Linha da folha (Fopag) — bolsa-auxílio/provisão de estagiário. Não está no painel de pessoas, por isso não entra no P&L de RH. Jusfy: incluir a pessoa no Cadastro/painel ou confirmar que fica fora.
A351: Fopag: DIAS BOLSA AUXILIO 05/2026: - Rúbrica 8797 | B351: Mai | C351: 1500 | D351: 4.1.1.01.003 Bolsa Estágio | E351: Folha sem cadastro no painel de pessoas | F351: Linha da folha (Fopag) — bolsa-auxílio/provisão de estagiário. Não está no painel de pessoas, por isso não entra no P&L de RH. Jusfy: incluir a pessoa no Cadastro/painel ou confirmar que fica fora.
A352: Fopag: DIAS BOLSA AUXILIO 06/2026: - Rúbrica 8797 | B352: Jun | C352: 1500 | D352: 4.1.1.01.003 Bolsa Estágio | E352: Folha sem cadastro no painel de pessoas | F352: Linha da folha (Fopag) — bolsa-auxílio/provisão de estagiário. Não está no painel de pessoas, por isso não entra no P&L de RH. Jusfy: incluir a pessoa no Cadastro/painel ou confirmar que fica fora.
A353: Fopag: DIAS BOLSA AUXILIO 01/2026: - Rúbrica 8797 | B353: Jan | C353: 1300 | D353: 4.1.1.01.003 Bolsa Estágio | E353: Folha sem cadastro no painel de pessoas | F353: Linha da folha (Fopag) — bolsa-auxílio/provisão de estagiário. Não está no painel de pessoas, por isso não entra no P&L de RH. Jusfy: incluir a pessoa no Cadastro/painel ou confirmar que fica fora.
A354: Fopag: Valor da Provisão 01/2026: - Rúbrica 1 | B354: Jan | C354: 125 | D354: 4.1.1.01.005 Férias | E354: Folha sem cadastro no painel de pessoas | F354: Linha da folha (Fopag) — bolsa-auxílio/provisão de estagiário. Não está no painel de pessoas, por isso não entra no P&L de RH. Jusfy: incluir a pessoa no Cadastro/painel ou confirmar que fica fora.
A355: Fopag: Valor da Provisão 02/2026: - Rúbrica 1 | B355: Fev | C355: 125 | D355: 4.1.1.01.005 Férias | E355: Folha sem cadastro no painel de pessoas | F355: Linha da folha (Fopag) — bolsa-auxílio/provisão de estagiário. Não está no painel de pessoas, por isso não entra no P&L de RH. Jusfy: incluir a pessoa no Cadastro/painel ou confirmar que fica fora.
A356: Fopag: Valor da Provisão 03/2026: - Rúbrica 1 | B356: Mar | C356: 125 | D356: 4.1.1.01.005 Férias | E356: Folha sem cadastro no painel de pessoas | F356: Linha da folha (Fopag) — bolsa-auxílio/provisão de estagiário. Não está no painel de pessoas, por isso não entra no P&L de RH. Jusfy: incluir a pessoa no Cadastro/painel ou confirmar que fica fora.
A357: Fopag: Valor da Provisão 04/2026: - Rúbrica 1 | B357: Abr | C357: 125 | D357: 4.1.1.01.005 Férias | E357: Folha sem cadastro no painel de pessoas | F357: Linha da folha (Fopag) — bolsa-auxílio/provisão de estagiário. Não está no painel de pessoas, por isso não entra no P&L de RH. Jusfy: incluir a pessoa no Cadastro/painel ou confirmar que fica fora.
A358: Fopag: Valor da Provisão 05/2026: - Rúbrica 1 | B358: Mai | C358: 125 | D358: 4.1.1.01.005 Férias | E358: Folha sem cadastro no painel de pessoas | F358: Linha da folha (Fopag) — bolsa-auxílio/provisão de estagiário. Não está no painel de pessoas, por isso não entra no P&L de RH. Jusfy: incluir a pessoa no Cadastro/painel ou confirmar que fica fora.
A359: Fopag: Valor da Provisão 06/2026: - Rúbrica 1 | B359: Jun | C359: 125 | D359: 4.1.1.01.005 Férias | E359: Folha sem cadastro no painel de pessoas | F359: Linha da folha (Fopag) — bolsa-auxílio/provisão de estagiário. Não está no painel de pessoas, por isso não entra no P&L de RH. Jusfy: incluir a pessoa no Cadastro/painel ou confirmar que fica fora.
... A403: MAGAZINE LUIZA S/A | B403: Jun | C403: 422.4 | D403: 6.2.1.03.002 Custo de Licença de Sofware e Sistemas | E403: Possível lançamento em dobro no razão | F403: As notas de jun citam os mesmos números das notas de abril (que já estão certas, em brindes), com valor um pouco diferente e em conta de custo de software. Syhus confirma se é repetição; se for, excluir.
A404: TOTAL em aberto (56 linhas) | C404: 50003.11
A405: Cursos e Treinamentos | B405: Jan | C405: 9040 | D405: 4.1.6.02.001 Cursos e Treinamentos | E405: Já casado | F405: Provisão de cursos de jan (R$ 9.040) feita a pedido da Jusfy: completa o auxílio educacional de jan do ERP (R$ 13.800 = Lucas 2.700 + CSP 2.060 + provisão 9.040).
A406: 59.794.104 LUCAS MARCHESE WINFIELD | B406: Mar | C406: 3600 | D406: 4.1.6.02.001 Cursos e Treinamentos | E406: Já casado | F406: No ERP: 5.2.5. Auxílio Educacional, competência 2026-03, R$ 3.600. Entra no P&L dentro de "HR Expenses & Payroll".
A407: 59.794.104 LUCAS MARCHESE WINFIELD | B407: Abr | C407: 3600 | D407: 4.1.6.02.001 Cursos e Treinamentos | E407: Já casado | F407: No ERP: 5.2.5. Auxílio Educacional, competência 2026-04, R$ 3.600. Entra no P&L dentro de "HR Expenses & Payroll".
A408: 59.794.104 LUCAS MARCHESE WINFIELD | B408: Mai | C408: 3600 | D408: 4.1.6.02.001 Cursos e Treinamentos | E408: Já casado | F408: No ERP: 5.2.5. Auxílio Educacional, competência 2026-05, R$ 3.600. Entra no P&L dentro de "HR Expenses & Payroll".
A409: 59.794.104 LUCAS MARCHESE WINFIELD | B409: Jun | C409: 3600 | D409: 4.1.6.02.001 Cursos e Treinamentos | E409: Já casado | F409: No ERP: 5.2.5. Auxílio Educacional, competência 2026-06, R$ 3.600. Entra no P&L dentro de "HR Expenses & Payroll".
A410: 59.794.104 LUCAS MARCHESE WINFIELD | B410: Jan | C410: 2700 | D410: 4.1.6.02.001 Cursos e Treinamentos | E410: Já casado | F410: No ERP: 5.2.5. Auxílio Educacional, competência 2026-02, R$ 2.700. Entra no P&L dentro de "HR Expenses & Payroll".
A411: 59.794.104 LUCAS MARCHESE WINFIELD | B411: Fev | C411: 2700 | D411: 4.1.6.02.001 Cursos e Treinamentos | E411: Já casado | F411: No ERP: 5.2.5. Auxílio Educacional, competência 2026-02, R$ 2.700. Entra no P&L dentro de "HR Expenses & Payroll".
A412: CSP TREINAMENTO EM DESENVOLVIMENTO GERENCIAL LTDA | B412: Jan | C412: 2060 | D412: 4.1.6.02.001 Cursos e Treinamentos | E412: Já casado | F412: Parte do auxílio educacional de jan do ERP (R$ 13.800).
A413: Já casados com a linha de RH do P&L (8 linhas) | C413: 30900 | F413: Não são pendência: entram no P&L dentro de "HR Expenses & Payroll" (auxílio educacional).
A415: B3. Pendência Jusfy — linha agregada do P&L com diferença e sem fornecedor provado no razão
A416: Linha do P&L | B416: Mês | C416: Diferença | D416: Conta | E416: Tipo | F416: O que falta
A417: Hotels | B417: Jan | C417: 39361.72 | D417: 4.1.2.04.005 Hotel e Pousadas | E417: PROVISIONAR | F417: O P&L não abre esta linha por fornecedor e o razão não mostra qual fornecedor falta/sobra. R$ 39.362 de Jan foram lançados em Fev. Provisionar em Jan. Jusfy: dizer o fornecedor (ou mandar a NF).
A418: Hotels | B418: Jan | C418: 1331.22 | D418: 4.1.2.04.005 Hotel e Pousadas | E418: PROVISIONAR | F418: O P&L não abre esta linha por fornecedor e o razão não mostra qual fornecedor falta/sobra. Razão tem R$ 1.331 a menos que o gerencial em Jan. Provisionar a diferença em Jan. Jusfy: dizer o fornecedor (ou mandar a NF).
A419: Airline and Bus Tickets | B419: Jan | C419: 8917.35 | D419: 4.1.2.04.001 Passagens Aereas e Rodoviárias | E419: PROVISIONAR | F419: O P&L não abre esta linha por fornecedor e o razão não mostra qual fornecedor falta/sobra. Razão tem R$ 8.917 a menos que o gerencial em Jan. Provisionar a diferença em Jan. Jusfy: dizer o fornecedor (ou mandar a NF).
A420: Meals | B420: Jan | C420: 2664.37 | D420: 4.1.2.04.002 Lanches e Refeições | E420: PROVISIONAR | F420: O P&L não abre esta linha por fornecedor e o razão não mostra qual fornecedor falta/sobra. R$ 2.664 de Jan foram lançados em Fev. Provisionar em Jan. Jusfy: dizer o fornecedor (ou mandar a NF).
A421: Meals | B421: Jan | C421: 488.81 | D421: 4.1.2.04.002 Lanches e Refeições | E421: PROVISIONAR | F421: O P&L não abre esta linha por fornecedor e o razão não mostra qual fornecedor falta/sobra. Razão tem R$ 489 a menos que o gerencial em Jan. Provisionar a diferença em Jan. Jusfy: dizer o fornecedor (ou mandar a NF).
A422: Telephony and Internet | B422: Jan | C422: 128.6 | D422: 4.1.2.01.001 Telefonia e Internet | E422: PROVISIONAR | F422: O P&L não abre esta linha por fornecedor e o razão não mostra qual fornecedor falta/sobra. R$ 129 de Jan foram lançados em Fev. Provisionar em Jan. Jusfy: dizer o fornecedor (ou mandar a NF).
A423: Telephony and Internet | B423: Jan | C423: 158.79 | D423: 4.1.2.01.001 Telefonia e Internet | E423: PROVISIONAR | F423: O P&L não abre esta linha por fornecedor e o razão não mostra qual fornecedor falta/sobra. Razão tem R$ 159 a menos que o gerencial em Jan. Provisionar a diferença em Jan. Jusfy: dizer o fornecedor (ou mandar a NF).
A424: Electrical Energy | B424: Jan | C424: 2897.29 | D424: 4.1.2.02.002 Energia Elétrica | E424: PROVISIONAR | F424: O P&L não abre esta linha por fornecedor e o razão não mostra qual fornecedor falta/sobra. Razão tem R$ 2.897 a menos que o gerencial em Jan. Provisionar a diferença em Jan. Jusfy: dizer o fornecedor (ou mandar a NF).
A425: Maintenance | B425: Jan | C425: 2200 | D425: 4.1.2.02.005 Manutenções Prediais | E425: PROVISIONAR | F425: O P&L não abre esta linha por fornecedor e o razão não mostra qual fornecedor falta/sobra. R$ 2.200 de Jan foram lançados em Fev. Provisionar em Jan. Jusfy: dizer o fornecedor (ou mandar a NF).
A426: Maintenance | B426: Jan | C426: 1550 | D426: 4.1.2.02.005 Manutenções Prediais | E426: PROVISIONAR | F426: O P&L não abre esta linha por fornecedor e o razão não mostra qual fornecedor falta/sobra. Razão tem R$ 1.550 a menos que o gerencial em Jan. Provisionar a diferença em Jan. Jusfy: dizer o fornecedor (ou mandar a NF).
A427: Tax suppliers | B427: Jan | C427: -473 | D427: 4.1.4.01.001 Taxa de Fiscalização e Licença e Funcionamento | E427: REVERTER (NF adiantada) | F427: O P&L não abre esta linha por fornecedor e o razão não mostra qual fornecedor falta/sobra. R$ 473 lançados em Jan são de Fev (lançado antes da competência). Reverter em Jan. Jusfy: dizer o fornecedor (ou mandar a NF).
A428: Processos Judiciais - Clientes | B428: Jan | C428: 6362 | D428: 4.1.8.09.004 Despesa com Contingências | E428: PROVISIONAR | F428: O P&L não abre esta linha por fornecedor e o razão não mostra qual fornecedor falta/sobra. Razão tem R$ 6.362 a menos que o gerencial em Jan. Provisionar a diferença em Jan. Jusfy: dizer o fornecedor (ou mandar a NF).
... A497: Other Executive Leadership-related Suppliers | B497: Jun | C497: 558 | D497: 4.1.8.09.003 | E497: PROVISIONAR | F497: O P&L não abre esta linha por fornecedor e o razão não mostra qual fornecedor falta/sobra. NF de Jun ainda não entrou. Provisionar R$ 558 em Jun (baixa no mês em que a NF entrar). Jusfy: dizer o fornecedor (ou mandar a NF).
...

Sheet Validar Tesouraria
A1: Validar com a tesouraria — notas do razão que não estão na base da Mari
A2: Cada linha é uma nota que a Syhus lançou e que não aparece no ERP (procurada por fornecedor e valor, de 2 meses antes a 1 mês depois, inclusive quando o ERP quebra a nota por centro de custo). Tesouraria marca se foi paga e se é da Jusfy. Se foi paga e é da Jusfy: falta no ERP (entra no P&L). Se não: a Syhus exclui. "Diferença do fornecedor no mês" é quanto o razão tem a mais que o P&L naquele fornecedor e mês.
A4: Nº | B4: Mês | C4: Fornecedor (razão) | D4: NF / documento | E4: Valor | F4: Conta | G4: Histórico no razão | H4: Diferença do fornecedor no mês | I4: Foi paga? (S/N) | J4: É da Jusfy? (S/N) | K4: Observação
A5: 1 | B5: Jan | C5: SYHUS CONTABILIDADE SOCIEDADE SIMPLES LTDA | D5: 31339 | E5: 19289.18 | F5: 4.1.6.01.001 Serviços Contábeis | G5: Compra/Serviço Tomado conforme nota fiscal nº 31339 do fornecedor SYHUS CONTABILIDADE SOCIEDADE SIMPLES LTDA | H5: 10171.18
A6: 2 | B6: Jan | C6: GUILHERME LOPES BRANCO 03239562030 | D6: 22 | E6: 3800 | F6: 4.1.2.05.007 Feiras e Eventos | G6: 724 - GUILHERME LOPES BRANCO 03239562030 Compra/Serviço Tomado conforme nota fiscal nº 22 do fornecedor GUILHERME LOPES BRANCO 03239562030 | H6: 6689.46
A7: 3 | B7: Jan | C7: LILIANE MAZZUIA PEREIRA | D7: 563 | E7: 1467.01 | F7: 4.1.8.09.001 Brindes | G7: 740 - LILIANE MAZZUIA PEREIRA Compra/Serviço Tomado conforme nota fiscal nº 563 do fornecedor LILIANE MAZZUIA PEREIRA | H7: 6689.46
A8: 4 | B8: Jan | C8: 3M AGROPEC E COM LTDA | D8: 42999 | E8: 38.49 | F8: 4.1.8.09.001 Brindes | G8: 742 - 3M AGROPEC E COM LTDA Compra/Serviço Tomado conforme nota fiscal nº 42999 do fornecedor 3M AGROPEC E COM LTDA | H8: 6689.46
A9: 5 | B9: Jan | C9: FLOR COMERCIO E IMPORTACAO LTDA | D9: 83916 | E9: 235.56 | F9: 4.1.8.09.002 Confraternização | G9: 736 - FLOR COMERCIO E IMPORTACAO LTDA Compra/Serviço Tomado conforme nota fiscal nº 83916 do fornecedor FLOR COMERCIO E IMPORTACAO LTDA | H9: 6689.46
A10: 6 | B10: Jan | C10: DELAINE ILHA DA SILVA 02466060027 | D10: 64921937 | E10: 267 | F10: 4.1.8.09.002 Confraternização | G10: 620 - DELAINE ILHA DA SILVA 02466060027 Compra/Serviço Tomado conforme nota fiscal nº 64921937 do fornecedor DELAINE ILHA DA SILVA 02466060027 | H10: 6689.46
A11: 7 | B11: Jan | C11: ONIX MULTICOISAS LTDA | D11: 784 | E11: 881.4 | F11: 4.1.8.09.002 Confraternização | G11: 483 - ONIX MULTICOISAS LTDA Compra/Serviço Tomado conforme nota fiscal nº 784 do fornecedor ONIX MULTICOISAS LTDA | H11: 6689.46
A12: 8 | B12: Jan | C12: EXPRESSITO MAQUINAS E GRAOS PARA CAFE ESPRESSO LTDA | D12: 55 | E12: 1378.8 | F12: 4.1.2.05.001 Copa e Cozinha | G12: 738 - EXPRESSITO MAQUINAS E GRAOS PARA CAFE ESPRESSO LTDA Compra/Serviço Tomado conforme nota fiscal nº 55 do fornecedor EXPRESSITO MAQUINAS E GRAOS PARA CAFE ESPRESSO LTDA | H12: 3153.55
A13: 9 | B13: Jan | C13: EMPORIO DE DOCES AVELOZ LTDA | D13: 29160 | E13: 269.94 | F13: 4.1.2.05.001 Copa e Cozinha | G13: 739 - EMPORIO DE DOCES AVELOZ LTDA Compra/Serviço Tomado conforme nota fiscal nº 29160 do fornecedor EMPORIO DE DOCES AVELOZ LTDA | H13: 3153.55
A14: 10 | B14: Jan | C14: MADE IN NATURAL COMERCIO DE ALIMENTOS E PRODUTOS ECOLOGICOS | D14: 19821 | E14: 353.59 | F14: 4.1.2.05.001 Copa e Cozinha | G14: 735 - MADE IN NATURAL COMERCIO DE ALIMENTOS E PRODUTOS ECOLOGICOS Compra/Serviço Tomado conforme nota fiscal nº 19821 do fornecedor MADE IN NATURAL COMERCIO DE ALIMENTOS E PRODUTOS ECOLOGICOS | H14: 3153.55
A15: 11 | B15: Jan | C15: GJK SHOPPING LTDA | D15: 907897 | E15: 27.99 | F15: 4.1.2.05.001 Copa e Cozinha | G15: 731 - GJK SHOPPING LTDA Compra/Serviço Tomado conforme nota fiscal nº 907897 do fornecedor GJK SHOPPING LTDA | H15: 3153.55
A16: 12 | B16: Jan | C16: CIA ZAFFARI COM E IND - LOJA 24 | D16: 28592 | E16: 18.32 | F16: 4.1.2.05.001 Copa e Cozinha | G16: 744 - CIA ZAFFARI COM E IND - LOJA 24 Compra/Serviço Tomado conforme nota fiscal nº 28592 do fornecedor CIA ZAFFARI COM E IND - LOJA 24 | H16: 3153.55
... A77: 73 | B77: Jun | C77: OMIEXPERIENCE LTDA. | D77: 3776869 | E77: 306.27 | F77: 4.1.2.01.003 Licença de Sofware e Sistemas (SaaS) | G77: 375 - OMIEXPERIENCE LTDA. Compra/Serviço Tomado conforme nota fiscal nº 3776869 do fornecedor OMIEXPERIENCE LTDA. | H77: 156.07
C78: TOTAL (73 notas; diferença de 34 fornecedor-mês) | H78: 100423.47

Sheet Pedir NF à Syhus
A1: Pedir a nota à Syhus — lançamentos sem número de NF
A2: Lançamentos sem nº de nota que também não aparecem no ERP quando procurados por fornecedor e valor. A Syhus manda a nota (ou o comprovante) de cada um; sem documento, o lançamento sai.
A4: Nº | B4: Mês | C4: Fornecedor (razão) | D4: NF / documento | E4: Valor | F4: Conta | G4: Histórico no razão | H4: Diferença do fornecedor no mês | I4: NF recebida? (S/N) | J4: Observação
A5: 1 | B5: Jan | C5: DELAINE ILHA DA SILVA 02466060027 | D5: sem nº | E5: 267 | F5: 4.1.8.09.002 Confraternização | G5: 342 - Cartão de Crédito - Kamino DELAINE ILHA DA SILVA 02466060027 4.1.8.09.002 - Confraternização | H5: 267
A6: 2 | B6: Fev | C6: CLOUD HUMANS TECNOLOGIA LTDA. | D6: sem nº | E6: 10255 | F6: 4.1.2.01.003 Licença de Sofware e Sistemas (SaaS) | G6: 930 - Provisão de Fornecedores Compra/Serviço Tomado conforme nota fiscal nº CLOUD HUMANS TECNOLOGIA LTDA. | H6: 2592.04
A7: 3 | B7: Fev | C7: Juan Carlo | D7: sem nº | E7: 824.64 | F7: 4.1.8.10.001 Despesas Indedutíveis | G7: 42 - Adiantamentos a Fornecedores Pagamento Juan Carlo - 05/02/2025 | H7: 149
A8: 4 | B8: Fev | C8: Juan Carlo | D8: sem nº | E8: 44.9 | F8: 4.1.8.10.001 Despesas Indedutíveis | G8: 42 - Adiantamentos a Fornecedores Pagamento ref. Juan Carlo - 12/05/2025 | H8: 149
A9: 5 | B9: Fev | C9: Serviços de Terceiros Reembols - Custos com Pessoal - 49.927.077 Juan Carlo Altmayer | D9: sem nº | E9: 44.9 | F9: 4.1.8.10.001 Despesas Indedutíveis | G9: 42 - Adiantamentos a Fornecedores Serviços de Terceiros Reembols - Custos com Pessoal - 49.927.077 Juan Carlo Altmayer - 19/06/2025 | H9: 149
A10: 6 | B10: Fev | C10: PADDLE.NET LEONARDOAI | D10: sem nº | E10: 53.97 | F10: 4.1.8.10.001 Despesas Indedutíveis | G10: 42 - Adiantamentos a Fornecedores PADDLE.NET LEONARDOAI - 31/05/2025 | H10: 53.97
A11: 7 | B11: Jun | C11: STARLINK BRAZIL SERVICOS DE INTERNET LTDA. | D11: sem nº | E11: 235.52 | F11: 4.1.2.01.001 Telefonia e Internet | G11: 353 - Cartão de Crédito - Banrisul PAGAMENTO DE CONTA A PAGAR - - 001/001 - STARLINK BRAZIL SERVICOS DE INTERNET LTDA. | H11: 110.26
C12: TOTAL (7 notas; diferença de 5 fornecedor-mês) | H12: 3172.27
